{"n_qubits": 10, "qubits": [1, 2, 3, 4, 5, 6, 7, 8, 9, 10], "fci_energy": -54.57328681352594, "hf_energy": -54.537375346091956, "CS_SRE": [0.021137117245211456, 0.033679240540836076, 0.041773297492196666, 0.047700487907474956, 0.05404816102254684, 0.07484517760503555, 0.10133685348566489, 0.10229349135536848, 0.1022748113687867, 0.10224608024973315], "CS_energy": [-54.54507515446701, -54.54867758179197, -54.55178244293854, -54.555871742586206, -54.55763122548632, -54.565265170789694, -54.573059774810154, -54.57315413456426, -54.57320833032192, -54.57328681352595], "overlaps": [0.9962957153526929, 0.9941170885981877, 0.9927242946533744, 0.9917045756662278, 0.9906114350927498, 0.9870324005083346, 0.9824980969746522, 0.982333980948384, 0.9823372030684387, 0.9823422446335052], "solver": "scipy", "data": {"molecule_id": "H2N-_singlet_C2v", "qubit_encoding": "JW", "unit": "Angstrom", "basis": "sto-3g", "charge": -1, "multiplicity": 1, "spin": 0, "geometry": "N 0.0000000000 0.0000000000 0.0423133333\nH 0.0000000000 0.7232400000 0.6135433333\nH 0.0000000000 -0.7232400000 0.6135433333", "n_qubits": 14, "n_particles": {"total": 10, "alpha": 5, "beta": 5}, "hf_array": [1, 1, 1, 1, 1, 1, 1, 1, 1, 1, 0, 0, 0, 0], "hf_method": "pyscf.scf.hf_symm.SymAdaptedRHF", "convergence_threshold": 1e-06, "point_group": {"groupname": "C2v", "topgroup": "C2v"}, "alpha": 0.9, "calculated_properties": {"HF": {"energy": -54.537375346091956, "converged": true}, "MP2": {"energy": -54.563080466972906, "converged": null}, "CISD": {"energy": -54.57292652830386, "converged": true}, "CCSD": {"energy": -54.57321097931258, "converged": true, "t1_diagnostic": 0.001235234862041261}, "FCI": {"energy": -54.57328681352594, "converged": true, "spin_matches_target": true, "multiplicity": 1.0000000000000506, "oscillatory_converged": false, "oscillation_energy_change": null}}, "auxiliary_operators": {"number_operator": {"IIIIIIIIIIIIII": 7.0, "ZIIIIIIIIIIIII": -0.5, "IZIIIIIIIIIIII": -0.5, "IIZIIIIIIIIIII": -0.5, "IIIZIIIIIIIIII": -0.5, "IIIIZIIIIIIIII": -0.5, "IIIIIZIIIIIIII": -0.5, "IIIIIIZIIIIIII": -0.5, "IIIIIIIZIIIIII": -0.5, "IIIIIIIIZIIIII": -0.5, "IIIIIIIIIZIIII": -0.5, "IIIIIIIIIIZIII": -0.5, "IIIIIIIIIIIZII": -0.5, "IIIIIIIIIIIIZI": -0.5, "IIIIIIIIIIIIIZ": -0.5}, "N_alpha": {"IIIIIIIIIIIIII": 3.5, "ZIIIIIIIIIIIII": -0.5, "IIZIIIIIIIIIII": -0.5, "IIIIZIIIIIIIII": -0.5, "IIIIIIZIIIIIII": -0.5, "IIIIIIIIZIIIII": -0.5, "IIIIIIIIIIZIII": -0.5, "IIIIIIIIIIIIZI": -0.5}, "N_beta": {"IIIIIIIIIIIIII": 3.5, "IZIIIIIIIIIIII": -0.5, "IIIZIIIIIIIIII": -0.5, "IIIIIZIIIIIIII": -0.5, "IIIIIIIZIIIIII": -0.5, "IIIIIIIIIZIIII": -0.5, "IIIIIIIIIIIZII": -0.5, "IIIIIIIIIIIIIZ": -0.5}, "S^2_operator": {"IIIIIIIIIIIIII": 2.625, "IIIIZZIIIIIIII": -0.375, "IIIIIIIIIIIIZZ": -0.375, "IIIIIIIIZZIIII": -0.375, "IIIIIIIIIIZZII": -0.375, "IIIIIIZZIIIIII": -0.375, "IIZZIIIIIIIIII": -0.375, "ZZIIIIIIIIIIII": -0.375, "IZZIIIIIIIIIII": -0.125, "IIIIIIIIIIYXYX": 0.125, "IIIIIIIIIIYXXY": -0.125, "IIIIIIIIIIXXYY": 0.125, "IIIIIIIIIIXXXX": 0.125, "IIIIIIIIIIYYYY": 0.125, "IIIIIIIIIIYYXX": 0.125, "IIIIIIIIIIXYYX": -0.125, "IIIIIIIIIIXYXY": 0.125, "IZIIIIZIIIIIII": -0.125, "ZIZIIIIIIIIIII": 0.125, "IZIZIIIIIIIIII": 0.125, "ZIIZIIIIIIIIII": -0.125, "IZIIIZIIIIIIII": 0.125, "ZIIIIZIIIIIIII": -0.125, "IZIIZIIIIIIIII": -0.125, "ZIIIIIZIIIIIII": 0.125, "ZIIIIIIZIIIIII": -0.125, "ZIIIIIIIZIIIII": 0.125, "ZIIIIIIIIZIIII": -0.125, "ZIIIIIIIIIZIII": 0.125, "ZIIIIIIIIIIZII": -0.125, "ZIIIIIIIIIIIZI": 0.125, "ZIIIIIIIIIIIIZ": -0.125, "ZIIIZIIIIIIIII": 0.125, "IIIIIIIIXYIIXY": 0.125, "IIIIIIIIYYIIXX": 0.125, "IZIIIIIZIIIIII": 0.125, "IIIIIIYXIIXYII": -0.125, "IIIIIIXXIIYYII": 0.125, "IIIIIIXXIIXXII": 0.125, "IIIIIIYYIIYYII": 0.125, "IIIIIIYYIIXXII": 0.125, "IIIIIIXYIIYXII": -0.125, "IIIIIIXYIIXYII": 0.125, "IIIIIIYXIIIIYX": 0.125, "IIIIIIYXIIIIXY": -0.125, "IIIIIIXXIIIIYY": 0.125, "IIIIIIXXIIIIXX": 0.125, "IIIIIIYYIIIIYY": 0.125, "IIIIIIYYIIIIXX": 0.125, "IIIIIIIIXYIIYX": -0.125, "IIIIIIXYIIIIYX": -0.125, "IIIIIIIIYXYXII": 0.125, "IIIIIIIIYXXYII": -0.125, "IIIIIIIIXXYYII": 0.125, "IIIIIIIIXXXXII": 0.125, "IIIIIIIIYYYYII": 0.125, "IIIIIIIIYYXXII": 0.125, "IIIIIIIIXYYXII": -0.125, "IIIIIIIIXYXYII": 0.125, "IIIIIIIIYXIIYX": 0.125, "IIIIIIIIYXIIXY": -0.125, "IIIIIIIIXXIIYY": 0.125, "IIIIIIIIXXIIXX": 0.125, "IIIIIIIIYYIIYY": 0.125, "IIIIIIXYIIIIXY": 0.125, "IZIIIIIIZIIIII": -0.125, "IZIIIIIIIZIIII": 0.125, "IZIIIIIIIIZIII": -0.125, "IIIIIZIIZIIIII": -0.125, "IIIIIZIIIZIIII": 0.125, "IIIIIZIIIIZIII": -0.125, "IIIIIZIIIIIZII": 0.125, "IIIIIZIIIIIIZI": -0.125, "IIIIIZIIIIIIIZ": 0.125, "IIIIIIZIZIIIII": 0.125, "IIIIIIZIIZIIII": -0.125, "IIIIIIZIIIZIII": 0.125, "IIIIIIZIIIIZII": -0.125, "IIIIIIZIIIIIZI": 0.125, "IIIIIIZIIIIIIZ": -0.125, "IIIIIIIZZIIIII": -0.125, "IIIIIZIZIIIIII": 0.125, "IIIIIIIZIZIIII": 0.125, "IIIIIIIZIIIZII": 0.125, "IIIIIIIZIIIIZI": -0.125, "IIIIIIIZIIIIIZ": 0.125, "IIIIIIIIZIZIII": 0.125, "IIIIIIIIZIIZII": -0.125, "IIIIIIIIZIIIZI": 0.125, "IIIIIIIIZIIIIZ": -0.125, "IIIIIIIIIZZIII": -0.125, "IIIIIIIIIZIZII": 0.125, "IIIIIIIIIZIIZI": -0.125, "IIIIIIIIIZIIIZ": 0.125, "IIIIIIIIIIZIZI": 0.125, "IIIIIIIIIIZIIZ": -0.125, "IIIIIIIZIIZIII": -0.125, "IIIIIZZIIIIIII": -0.125, "IIIIZIIIIIIIIZ": -0.125, "IIIIZIIIIIIIZI": 0.125, "IZIIIIIIIIIZII": 0.125, "IZIIIIIIIIIIZI": -0.125, "IZIIIIIIIIIIIZ": 0.125, "IIZIZIIIIIIIII": 0.125, "IIZIIZIIIIIIII": -0.125, "IIZIIIZIIIIIII": 0.125, "IIZIIIIZIIIIII": -0.125, "IIZIIIIIZIIIII": 0.125, "IIZIIIIIIZIIII": -0.125, "IIZIIIIIIIZIII": 0.125, "IIZIIIIIIIIZII": -0.125, "IIZIIIIIIIIIZI": 0.125, "IIZIIIIIIIIIIZ": -0.125, "IIIZZIIIIIIIII": -0.125, "IIIZIZIIIIIIII": 0.125, "IIIZIIZIIIIIII": -0.125, "IIIZIIIZIIIIII": 0.125, "IIIZIIIIZIIIII": -0.125, "IIIZIIIIIZIIII": 0.125, "IIIZIIIIIIZIII": -0.125, "IIIZIIIIIIIZII": 0.125, "IIIZIIIIIIIIZI": -0.125, "IIIZIIIIIIIIIZ": 0.125, "IIIIZIZIIIIIII": 0.125, "IIIIZIIZIIIIII": -0.125, "IIIIZIIIZIIIII": 0.125, "IIIIZIIIIZIIII": -0.125, "IIIIZIIIIIZIII": 0.125, "IIIIZIIIIIIZII": -0.125, "IIIIIIYXIIYXII": 0.125, "IIIIIIXYXYIIII": 0.125, "IIIIIIYYYYIIII": 0.125, "IIIIIIYYXXIIII": 0.125, "YXIIIIIIIIYXII": 0.125, "YXIIIIIIIIXYII": -0.125, "XXIIIIIIIIYYII": 0.125, "XXIIIIIIIIXXII": 0.125, "YYIIIIIIIIYYII": 0.125, "YYIIIIIIIIXXII": 0.125, "XYIIIIIIIIYXII": -0.125, "XYIIIIIIIIXYII": 0.125, "YXIIIIIIIIIIYX": 0.125, "YXIIIIIIIIIIXY": -0.125, "XXIIIIIIIIIIYY": 0.125, "XXIIIIIIIIIIXX": 0.125, "YYIIIIIIIIIIYY": 0.125, "XYIIIIIIXYIIII": 0.125, "YYIIIIIIIIIIXX": 0.125, "XYIIIIIIIIIIXY": 0.125, "IIYXYXIIIIIIII": 0.125, "IIYXXYIIIIIIII": -0.125, "IIXXYYIIIIIIII": 0.125, "IIXXXXIIIIIIII": 0.125, "IIYYYYIIIIIIII": 0.125, "IIYYXXIIIIIIII": 0.125, "IIXYYXIIIIIIII": -0.125, "IIXYXYIIIIIIII": 0.125, "IIYXIIYXIIIIII": 0.125, "IIYXIIXYIIIIII": -0.125, "IIXXIIYYIIIIII": 0.125, "IIXXIIXXIIIIII": 0.125, "XYIIIIIIIIIIYX": -0.125, "IIYYIIYYIIIIII": 0.125, "XYIIIIIIYXIIII": -0.125, "YYIIIIIIYYIIII": 0.125, "YXYXIIIIIIIIII": 0.125, "YXXYIIIIIIIIII": -0.125, "XXYYIIIIIIIIII": 0.125, "XXXXIIIIIIIIII": 0.125, "YYYYIIIIIIIIII": 0.125, "YYXXIIIIIIIIII": 0.125, "XYYXIIIIIIIIII": -0.125, "XYXYIIIIIIIIII": 0.125, "YXIIYXIIIIIIII": 0.125, "YXIIXYIIIIIIII": -0.125, "XXIIYYIIIIIIII": 0.125, "XXIIXXIIIIIIII": 0.125, "YYIIYYIIIIIIII": 0.125, "YYIIIIIIXXIIII": 0.125, "YYIIXXIIIIIIII": 0.125, "XYIIXYIIIIIIII": 0.125, "YXIIIIYXIIIIII": 0.125, "YXIIIIXYIIIIII": -0.125, "XXIIIIYYIIIIII": 0.125, "XXIIIIXXIIIIII": 0.125, "YYIIIIYYIIIIII": 0.125, "YYIIIIXXIIIIII": 0.125, "XYIIIIYXIIIIII": -0.125, "XYIIIIXYIIIIII": 0.125, "YXIIIIIIYXIIII": 0.125, "YXIIIIIIXYIIII": -0.125, "XXIIIIIIYYIIII": 0.125, "XXIIIIIIXXIIII": 0.125, "XYIIYXIIIIIIII": -0.125, "IIYYIIXXIIIIII": 0.125, "IIXYIIYXIIIIII": -0.125, "IIXYIIXYIIIIII": 0.125, "IIIIYXIIXYIIII": -0.125, "IIIIXXIIYYIIII": 0.125, "IIIIXXIIXXIIII": 0.125, "IIIIYYIIYYIIII": 0.125, "IIIIYYIIXXIIII": 0.125, "IIIIXYIIYXIIII": -0.125, "IIIIXYIIXYIIII": 0.125, "IIIIYXIIIIYXII": 0.125, "IIIIYXIIIIXYII": -0.125, "IIIIXXIIIIYYII": 0.125, "IIIIXXIIIIXXII": 0.125, "IIIIYYIIIIYYII": 0.125, "IIIIYYIIIIXXII": 0.125, "IIIIYXIIYXIIII": 0.125, "IIIIXYIIIIYXII": -0.125, "IIIIYXIIIIIIYX": 0.125, "IIIIYXIIIIIIXY": -0.125, "IIIIXXIIIIIIYY": 0.125, "IIIIXXIIIIIIXX": 0.125, "IIIIYYIIIIIIYY": 0.125, "IIIIYYIIIIIIXX": 0.125, "IIIIXYIIIIIIYX": -0.125, "IIIIXYIIIIIIXY": 0.125, "IIIIIIYXYXIIII": 0.125, "IIIIIIYXXYIIII": -0.125, "IIIIIIXXYYIIII": 0.125, "IIIIIIXXXXIIII": 0.125, "IIIIIIIIIIIZZI": -0.125, "IIIIXYIIIIXYII": 0.125, "IIIIXYXYIIIIII": 0.125, "IIIIXYYXIIIIII": -0.125, "IIIIYYXXIIIIII": 0.125, "IIYXIIIIYXIIII": 0.125, "IIYXIIIIXYIIII": -0.125, "IIXXIIIIYYIIII": 0.125, "IIXXIIIIXXIIII": 0.125, "IIYYIIIIYYIIII": 0.125, "IIYYIIIIXXIIII": 0.125, "IIXYIIIIYXIIII": -0.125, "IIXYIIIIXYIIII": 0.125, "IIYXIIIIIIYXII": 0.125, "IIYXIIIIIIXYII": -0.125, "IIXXIIIIIIYYII": 0.125, "IIXXIIIIIIXXII": 0.125, "IIYYIIIIIIYYII": 0.125, "IIYYIIIIIIXXII": 0.125, "IIXYIIIIIIYXII": -0.125, "IIXYIIIIIIXYII": 0.125, "IIYXIIIIIIIIYX": 0.125, "IIYXIIIIIIIIXY": -0.125, "IIXXIIIIIIIIYY": 0.125, "IIXXIIIIIIIIXX": 0.125, "IIYYIIIIIIIIYY": 0.125, "IIYYIIIIIIIIXX": 0.125, "IIXYIIIIIIIIYX": -0.125, "IIXYIIIIIIIIXY": 0.125, "IIIIYXYXIIIIII": 0.125, "IIIIYXXYIIIIII": -0.125, "IIIIXXYYIIIIII": 0.125, "IIIIXXXXIIIIII": 0.125, "IIIIYYYYIIIIII": 0.125, "IIIIIIXYYXIIII": -0.125, "IIIIIIIIIIIZIZ": 0.125}, "UCCSD_operator": {"IIIIXYIIIIIIXX": -0.007451529407051401, "IIIIYYIIIIIIXY": -0.007451529407051401, "IIIIXXIIIIIIXY": 0.007451529407051401, "IIIIYXIIIIIIXX": -0.007451529407051401, "IIIIYXIIIIIIYY": 0.007451529407051401, "IIIIYYIIIIIIYX": -0.007451529407051401, "IIIIXXIIIIIIYX": 0.007451529407051401, "IIIIXYIIIIIIYY": 0.007451529407051401, "IIIIIIXYIIIIXX": -0.0057726002083809905, "IIIIIIXXIIIIXY": 0.0057726002083809905, "IIIIIIYYIIIIXY": -0.0057726002083809905, "IIIIIIXYIIIIYY": 0.0057726002083809905, "IIIIIIYXIIIIYY": 0.0057726002083809905, "IIIIIIYYIIIIYX": -0.0057726002083809905, "IIIIIIXXIIIIYX": 0.0057726002083809905, "IIIIIIYXIIIIXX": -0.0057726002083809905, "IIIIXXIIIIYXII": 0.004510386202204762, "IIIIYYIIIIYXII": -0.004510386202204762, "IIIIYXIIIIYYII": 0.004510386202204762, "IIIIXYIIIIYYII": 0.004510386202204762, "IIIIYXIIIIXXII": -0.004510386202204762, "IIIIXYIIIIXXII": -0.004510386202204762, "IIIIXXIIIIXYII": 0.004510386202204762, "IIIIYYIIIIXYII": -0.004510386202204762, "IIYYIIIIIIXYII": -0.004475169603285584, "IIXXIIIIIIXYII": 0.004475169603285584, "IIXYIIIIIIXXII": -0.004475169603285584, "IIYXIIIIIIXXII": -0.004475169603285584, "IIYXIIIIIIYYII": 0.004475169603285584, "IIYYIIIIIIYXII": -0.004475169603285584, "IIXXIIIIIIYXII": 0.004475169603285584, "IIXYIIIIIIYYII": 0.004475169603285584, "IIIIIIIIXYXXII": -0.004350370900983135, "IIIIIIIIYYXYII": -0.004350370900983135, "IIIIIIIIYXXXII": -0.004350370900983135, "IIIIIIIIXXXYII": 0.004350370900983135, "IIIIIIIIXYYYII": 0.004350370900983135, "IIIIIIIIXXYXII": 0.004350370900983135, "IIIIIIIIYYYXII": -0.004350370900983135, "IIIIIIIIYXYYII": 0.004350370900983135, "IIIYXIIIIIIYYI": 0.003712892643390967, "IIIYYIIIIIIYXI": -0.003712892643390967, "IIIXXIIIIIIXYI": 0.003712892643390967, "IIYZZYIIIIXZZY": -0.003712892643390967, "IIXZZXIIIIXZZY": 0.003712892643390967, "IIIXXIIIIIIYXI": 0.003712892643390967, "IIYZZXIIIIXZZX": -0.003712892643390967, "IIYZZXIIIIYZZY": 0.003712892643390967, "IIXZZYIIIIYZZY": 0.003712892643390967, "IIIYYIIIIIIXYI": -0.003712892643390967, "IIXZZYIIIIXZZX": -0.003712892643390967, "IIIXYIIIIIIXXI": -0.003712892643390967, "IIIYXIIIIIIXXI": -0.003712892643390967, "IIIXYIIIIIIYYI": 0.003712892643390967, "IIYZZYIIIIYZZX": -0.003712892643390967, "IIXZZXIIIIYZZX": 0.003712892643390967, "IIIIYZZYIIIYXI": 0.003674493120534467, "IIIIXZZXIIIYXI": -0.003674493120534467, "IIIIYZZYIIIXYI": 0.003674493120534467, "IIIIXZZXIIIXYI": -0.003674493120534467, "IIIIIYYIIIYZZX": 0.003674493120534467, "IIIIYZZXIIIYYI": -0.003674493120534467, "IIIIIYXIIIYZZY": -0.003674493120534467, "IIIIIXYIIIYZZY": -0.003674493120534467, "IIIIIYXIIIXZZX": 0.003674493120534467, "IIIIIXYIIIXZZX": 0.003674493120534467, "IIIIIXXIIIXZZY": -0.003674493120534467, "IIIIIYYIIIXZZY": 0.003674493120534467, "IIIIXZZYIIIXXI": 0.003674493120534467, "IIIIYZZXIIIXXI": 0.003674493120534467, "IIIIXZZYIIIYYI": -0.003674493120534467, "IIIIIXXIIIYZZX": -0.003674493120534467, "IIIYZZYIIIXYII": 0.0032514166634459805, "IIIXZZXIIIXYII": -0.0032514166634459805, "IIIXZZYIIIXXII": 0.0032514166634459805, "IIIYZZXIIIXXII": 0.0032514166634459805, "IIIXZZYIIIYYII": -0.0032514166634459805, "IIIYZZXIIIYYII": -0.0032514166634459805, "IIIYZZYIIIYXII": 0.0032514166634459805, "IIIXZZXIIIYXII": -0.0032514166634459805, "IIYZZZZYIIYXII": -0.0032514166634459805, "IIYZZZZXIIYYII": 0.0032514166634459805, "IIXZZZZYIIYYII": 0.0032514166634459805, "IIYZZZZXIIXXII": -0.0032514166634459805, "IIXZZZZXIIYXII": 0.0032514166634459805, "IIXZZZZYIIXXII": -0.0032514166634459805, "IIXZZZZXIIXYII": 0.0032514166634459805, "IIYZZZZYIIXYII": -0.0032514166634459805, "IIIIIIXYIIYYII": 0.0031167225744928714, "IIIIIIYXIIXXII": -0.0031167225744928714, "IIIIIIXYIIXXII": -0.0031167225744928714, "IIIIIIYXIIYYII": 0.0031167225744928714, "IIIIIIXXIIXYII": 0.0031167225744928714, "IIIIIIXXIIYXII": 0.0031167225744928714, "IIIIIIYYIIYXII": -0.0031167225744928714, "IIIIIIYYIIXYII": -0.0031167225744928714, "IIIIIXYIIIIXXI": -0.0031039839483028545, "IIIIXZZXIIYZZX": 0.0031039839483028545, "IIIIYZZYIIYZZX": -0.0031039839483028545, "IIIIYZZXIIYZZY": 0.0031039839483028545, "IIIIXZZYIIYZZY": 0.0031039839483028545, "IIIIYZZXIIXZZX": -0.0031039839483028545, "IIIIXZZYIIXZZX": -0.0031039839483028545, "IIIIIXXIIIIXYI": 0.0031039839483028545, "IIIIIYYIIIIXYI": -0.0031039839483028545, "IIIIYZZYIIXZZY": -0.0031039839483028545, "IIIIIYXIIIIXXI": -0.0031039839483028545, "IIIIIXYIIIIYYI": 0.0031039839483028545, "IIIIIYXIIIIYYI": 0.0031039839483028545, "IIIIXZZXIIXZZY": 0.0031039839483028545, "IIIIIYYIIIIYXI": -0.0031039839483028545, "IIIIIXXIIIIYXI": 0.0031039839483028545, "IIYZZYIIIIIXYI": 0.0026773040283677827, "IIXZZXIIIIIXYI": -0.0026773040283677827, "IIXZZYIIIIIXXI": 0.0026773040283677827, "IIXZZXIIIIIYXI": -0.0026773040283677827, "IIIYYIIIIIXZZY": 0.0026773040283677827, "IIIXXIIIIIXZZY": -0.0026773040283677827, "IIIXYIIIIIXZZX": 0.0026773040283677827, "IIIYXIIIIIXZZX": 0.0026773040283677827, "IIIXYIIIIIYZZY": -0.0026773040283677827, "IIYZZXIIIIIXXI": 0.0026773040283677827, "IIIYXIIIIIYZZY": -0.0026773040283677827, "IIIYYIIIIIYZZX": 0.0026773040283677827, "IIIXXIIIIIYZZX": -0.0026773040283677827, "IIYZZYIIIIIYXI": 0.0026773040283677827, "IIYZZXIIIIIYYI": -0.0026773040283677827, "IIXZZYIIIIIYYI": -0.0026773040283677827, "IIYYIIIIIIIIXY": -0.002127391976514409, "IIXXIIIIIIIIXY": 0.002127391976514409, "IIXYIIIIIIIIXX": -0.002127391976514409, "IIXXIIIIIIIIYX": 0.002127391976514409, "IIYYIIIIIIIIYX": -0.002127391976514409, "IIYXIIIIIIIIYY": 0.002127391976514409, "IIXYIIIIIIIIYY": 0.002127391976514409, "IIYXIIIIIIIIXX": -0.002127391976514409, "IIIIIIXZZZYIII": -0.0016599850088427541, "IIIIIIIYZZZXII": 0.0016599850088427541, "IIIIIIYZZZXIII": 0.0016599850088427541, "IIIIIIIXZZZYII": -0.0016599850088427541, "IIIIIIIIYYIIYX": -0.0014806773232452861, "IIIIIIIIYXIIYY": 0.0014806773232452861, "IIIIIIIIXYIIYY": 0.0014806773232452861, "IIIIIIIIXXIIYX": 0.0014806773232452861, "IIIIIIIIYXIIXX": -0.0014806773232452861, "IIIIIIIIXYIIXX": -0.0014806773232452861, "IIIIIIIIXXIIXY": 0.0014806773232452861, "IIIIIIIIYYIIXY": -0.0014806773232452861, "IIXZXIIIIIXZYI": 0.0010355886150231843, "IIIYZYIIIIIXZY": -0.0010355886150231843, "IIIXZXIIIIIXZY": 0.0010355886150231843, "IIIXZYIIIIIXZX": -0.0010355886150231843, "IIXZYIIIIIXZXI": -0.0010355886150231843, "IIYZXIIIIIXZXI": -0.0010355886150231843, "IIXZYIIIIIYZYI": 0.0010355886150231843, "IIIXZXIIIIIYZX": 0.0010355886150231843, "IIIYZYIIIIIYZX": -0.0010355886150231843, "IIIYZXIIIIIYZY": 0.0010355886150231843, "IIIXZYIIIIIYZY": 0.0010355886150231843, "IIIYZXIIIIIXZX": -0.0010355886150231843, "IIYZYIIIIIXZYI": -0.0010355886150231843, "IIYZXIIIIIYZYI": 0.0010355886150231843, "IIYZYIIIIIYZXI": -0.0010355886150231843, "IIXZXIIIIIYZXI": 0.0010355886150231843, "IIIXZZZZZZZYII": 0.0007925357930026267, "IIIYZZZZZZZXII": -0.0007925357930026267, "IIXZZZZZZZYIII": 0.0007925357930026267, "IIYZZZZZZZXIII": -0.0007925357930026267, "IIIIIYZZZZZZZX": -0.0006563652308187081, "IIIIIXZZZZZZZY": 0.0006563652308187081, "IIIIXZZZZZZZYI": 0.0006563652308187081, "IIIIYZZZZZZZXI": -0.0006563652308187081, "IIXZZZZYIIIIYY": -0.000614199070815766, "IIXZZZZXIIIIXY": -0.000614199070815766, "IIYZZZZYIIIIXY": 0.000614199070815766, "IIYZZZZXIIIIYY": -0.000614199070815766, "IIYZZZZYIIIIYX": 0.000614199070815766, "IIYZZZZXIIIIXX": 0.000614199070815766, "IIXZZZZYIIIIXX": 0.000614199070815766, "IIXZZZZXIIIIYX": -0.000614199070815766, "IIIYZZYIIIIIXY": -0.000614199070815766, "IIIXZZYIIIIIXX": -0.000614199070815766, "IIIYZZXIIIIIXX": -0.000614199070815766, "IIIXZZXIIIIIYX": 0.000614199070815766, "IIIYZZYIIIIIYX": -0.000614199070815766, "IIIYZZXIIIIIYY": 0.000614199070815766, "IIIXZZYIIIIIYY": 0.000614199070815766, "IIIXZZXIIIIIXY": 0.000614199070815766, "IIIIIYZXIIIXZX": 0.0005705091722316125, "IIIIIXZXIIIXZY": -0.0005705091722316125, "IIIIIXZYIIIXZX": 0.0005705091722316125, "IIIIIXZYIIIYZY": -0.0005705091722316125, "IIIIIYZXIIIYZY": -0.0005705091722316125, "IIIIIYZYIIIYZX": 0.0005705091722316125, "IIIIIXZXIIIYZX": -0.0005705091722316125, "IIIIIYZYIIIXZY": 0.0005705091722316125, "IIIIYZYIIIYZXI": 0.0005705091722316125, "IIIIYZYIIIXZYI": 0.0005705091722316125, "IIIIXZXIIIXZYI": -0.0005705091722316125, "IIIIXZYIIIXZXI": 0.0005705091722316125, "IIIIXZXIIIYZXI": -0.0005705091722316125, "IIIIXZYIIIYZYI": -0.0005705091722316125, "IIIIYZXIIIYZYI": -0.0005705091722316125, "IIIIYZXIIIXZXI": 0.0005705091722316125, "YYIIIIIIIIYXII": -0.0001402495070900685, "XXIIIIIIIIYXII": 0.0001402495070900685, "YYIIIIIIIIXYII": -0.0001402495070900685, "XYIIIIIIIIXXII": -0.0001402495070900685, "XXIIIIIIIIXYII": 0.0001402495070900685, "XYIIIIIIIIYYII": 0.0001402495070900685, "YXIIIIIIIIYYII": 0.0001402495070900685, "YXIIIIIIIIXXII": -0.0001402495070900685, "IYZZZZXIIIIIYY": 0.00011780328156380895, "IYZZZZYIIIIIYX": -0.00011780328156380895, "XZZZZZZYIIIIYY": -0.00011780328156380895, "YZZZZZZXIIIIXX": 0.00011780328156380895, "XZZZZZZXIIIIXY": -0.00011780328156380895, "IXZZZZXIIIIIYX": 0.00011780328156380895, "IXZZZZYIIIIIYY": 0.00011780328156380895, "IXZZZZXIIIIIXY": 0.00011780328156380895, "IXZZZZYIIIIIXX": -0.00011780328156380895, "IYZZZZYIIIIIXY": -0.00011780328156380895, "YZZZZZZXIIIIYY": -0.00011780328156380895, "YZZZZZZYIIIIYX": 0.00011780328156380895, "XZZZZZZXIIIIYX": -0.00011780328156380895, "YZZZZZZYIIIIXY": 0.00011780328156380895, "IYZZZZXIIIIIXX": -0.00011780328156380895, "XZZZZZZYIIIIXX": 0.00011780328156380895, "XZZXIIIIIIIIXY": 0.00010679684419442214, "YZZYIIIIIIIIXY": -0.00010679684419442214, "IYYIIIIIIIIIXY": 0.00010679684419442214, "IXXIIIIIIIIIXY": -0.00010679684419442214, "IXYIIIIIIIIIXX": 0.00010679684419442214, "IYXIIIIIIIIIXX": 0.00010679684419442214, "IXYIIIIIIIIIYY": -0.00010679684419442214, "IYXIIIIIIIIIYY": -0.00010679684419442214, "IYYIIIIIIIIIYX": 0.00010679684419442214, "XZZYIIIIIIIIXX": -0.00010679684419442214, "IXXIIIIIIIIIYX": -0.00010679684419442214, "XZZYIIIIIIIIYY": 0.00010679684419442214, "YZZXIIIIIIIIXX": -0.00010679684419442214, "YZZXIIIIIIIIYY": 0.00010679684419442214, "YZZYIIIIIIIIYX": -0.00010679684419442214, "XZZXIIIIIIIIYX": 0.00010679684419442214, "XZZZYIIIIIYZYI": -8.653618039051505e-05, "IXZZZYIIIIIYZY": -8.653618039051505e-05, "IYZZZXIIIIIYZY": -8.653618039051505e-05, "IYZZZXIIIIIXZX": 8.653618039051505e-05, "IYZZZYIIIIIYZX": 8.653618039051505e-05, "XZZZYIIIIIXZXI": 8.653618039051505e-05, "YZZZXIIIIIXZXI": 8.653618039051505e-05, "XZZZXIIIIIXZYI": -8.653618039051505e-05, "YZZZYIIIIIXZYI": 8.653618039051505e-05, "IXZZZXIIIIIYZX": -8.653618039051505e-05, "YZZZXIIIIIYZYI": -8.653618039051505e-05, "IXZZZXIIIIIXZY": -8.653618039051505e-05, "IXZZZYIIIIIXZX": 8.653618039051505e-05, "IYZZZYIIIIIXZY": 8.653618039051505e-05, "XZZZXIIIIIYZXI": -8.653618039051505e-05, "YZZZYIIIIIYZXI": 8.653618039051505e-05, "YYIIIIIIIIIIXY": -8.08460830258614e-05, "XXIIIIIIIIIIXY": 8.08460830258614e-05, "XYIIIIIIIIIIXX": -8.08460830258614e-05, "YYIIIIIIIIIIYX": -8.08460830258614e-05, "YXIIIIIIIIIIYY": 8.08460830258614e-05, "XYIIIIIIIIIIYY": 8.08460830258614e-05, "YXIIIIIIIIIIXX": -8.08460830258614e-05, "XXIIIIIIIIIIYX": 8.08460830258614e-05, "XZZZZXIIIIYZZX": -5.3492490894083204e-05, "YZZZZYIIIIYZZX": 5.3492490894083204e-05, "YZZZZXIIIIYZZY": -5.3492490894083204e-05, "IYZZYIIIIIIXYI": 5.3492490894083204e-05, "YZZZZXIIIIXZZX": 5.3492490894083204e-05, "XZZZZYIIIIYZZY": -5.3492490894083204e-05, "IXZZXIIIIIIYXI": -5.3492490894083204e-05, "IYZZXIIIIIIYYI": -5.3492490894083204e-05, "IXZZYIIIIIIYYI": -5.3492490894083204e-05, "IYZZXIIIIIIXXI": 5.3492490894083204e-05, "IYZZYIIIIIIYXI": 5.3492490894083204e-05, "IXZZYIIIIIIXXI": 5.3492490894083204e-05, "XZZZZYIIIIXZZX": 5.3492490894083204e-05, "YZZZZYIIIIXZZY": 5.3492490894083204e-05, "IXZZXIIIIIIXYI": -5.3492490894083204e-05, "XZZZZXIIIIXZZY": -5.3492490894083204e-05, "XZZYIIIIIIYYII": 3.745717715123596e-05, "YZZXIIIIIIXXII": -3.745717715123596e-05, "YZZYIIIIIIYXII": -3.745717715123596e-05, "YZZXIIIIIIYYII": 3.745717715123596e-05, "XZZXIIIIIIYXII": 3.745717715123596e-05, "XZZXIIIIIIXYII": 3.745717715123596e-05, "YZZYIIIIIIXYII": -3.745717715123596e-05, "XZZYIIIIIIXXII": -3.745717715123596e-05, "IYYIIIIIIIXYII": 3.745717715123596e-05, "IYXIIIIIIIYYII": -3.745717715123596e-05, "IYYIIIIIIIYXII": 3.745717715123596e-05, "IXXIIIIIIIYXII": -3.745717715123596e-05, "IYXIIIIIIIXXII": 3.745717715123596e-05, "IXYIIIIIIIXXII": 3.745717715123596e-05, "IXXIIIIIIIXYII": -3.745717715123596e-05, "IXYIIIIIIIYYII": -3.745717715123596e-05, "XZZZZXIIIIIXYI": -3.304368949643185e-05, "XZZZZYIIIIIXXI": 3.304368949643185e-05, "YZZZZXIIIIIXXI": 3.304368949643185e-05, "XZZZZYIIIIIYYI": -3.304368949643185e-05, "YZZZZXIIIIIYYI": -3.304368949643185e-05, "YZZZZYIIIIIYXI": 3.304368949643185e-05, "XZZZZXIIIIIYXI": -3.304368949643185e-05, "IYZZYIIIIIXZZY": 3.304368949643185e-05, "IXZZXIIIIIXZZY": -3.304368949643185e-05, "IXZZYIIIIIXZZX": 3.304368949643185e-05, "IYZZXIIIIIXZZX": 3.304368949643185e-05, "IXZZYIIIIIYZZY": -3.304368949643185e-05, "IYZZXIIIIIYZZY": -3.304368949643185e-05, "IYZZYIIIIIYZZX": 3.304368949643185e-05, "IXZZXIIIIIYZZX": -3.304368949643185e-05, "YZZZZYIIIIIXYI": 3.304368949643185e-05, "XZZZZZZXIIYXII": 1.5477450107490506e-05, "IYZZZZYIIIXYII": 1.5477450107490506e-05, "IXZZZZXIIIXYII": -1.5477450107490506e-05, "IXZZZZYIIIXXII": 1.5477450107490506e-05, "IYZZZZXIIIXXII": 1.5477450107490506e-05, "IXZZZZYIIIYYII": -1.5477450107490506e-05, "IYZZZZXIIIYYII": -1.5477450107490506e-05, "IYZZZZYIIIYXII": 1.5477450107490506e-05, "YZZZZZZYIIYXII": -1.5477450107490506e-05, "IXZZZZXIIIYXII": -1.5477450107490506e-05, "XZZZZZZYIIYYII": 1.5477450107490506e-05, "YZZZZZZXIIXXII": -1.5477450107490506e-05, "YZZZZZZXIIYYII": 1.5477450107490506e-05, "XZZZZZZYIIXXII": -1.5477450107490506e-05, "XZZZZZZXIIXYII": 1.5477450107490506e-05, "YZZZZZZYIIXYII": -1.5477450107490506e-05, "IXZZZZZZZZZYII": -5.863617087127048e-06, "IYZZZZZZZZZXII": 5.863617087127048e-06, "XZZZZZZZZZYIII": -5.863617087127048e-06, "YZZZZZZZZZXIII": 5.863617087127048e-06}}, "hf_method_fallback": "standard", "generation_time_s": 6.259, "timestamp": "2026-03-10T21:38:16.550354+00:00", "formula_latex": "$\\mathrm{H_{2}N^{-}}$"}}