{"n_qubits": 13, "qubits": [1, 2, 3, 4, 5, 6, 7, 8, 9, 10, 11, 12, 13], "fci_energy": -2.215456616982313, "hf_energy": -2.1602658905185077, "CS_SRE": [0.06693046490542692, 0.06734772773254223, 0.07936036814128, 0.09260541897387438, 0.10740627861752228, 0.12507072817774206, 0.14754589519868913, 0.17102512565495487, 0.17512120651774046, 0.1815770063799841, 0.1815643322632316, 0.19501501461296886, 0.20728536398211028], "CS_energy": [-2.1696851144014166, -2.171992822965349, -2.1752185888597104, -2.1805186388951876, -2.183469470908198, -2.18812815544298, -2.194408260821819, -2.2029710939181, -2.20475327658753, -2.2081447183015617, -2.209063997414681, -2.2145787943512794, -2.21545661698273], "overlaps": [0.9879552744206265, 0.9880094725202577, 0.9859134404697968, 0.9836385907556459, 0.9810545862216673, 0.9780338433071103, 0.9741411798403549, 0.9701049685603835, 0.9694270150313626, 0.9683619041681778, 0.9683764892932384, 0.966125729876821, 0.9639644231506168], "solver": "scipy", "data": {"molecule_id": "H4_singlet_Dooh", "qubit_encoding": "JW", "unit": "Angstrom", "basis": "3-21g", "charge": 0, "multiplicity": 1, "spin": 0, "geometry": "H -1.2000000000 0.0000000000 0.0000000000\nH -0.4000000000 0.0000000000 0.0000000000\nH 0.4000000000 0.0000000000 0.0000000000\nH 1.2000000000 0.0000000000 0.0000000000", "n_qubits": 16, "n_particles": {"total": 4, "alpha": 2, "beta": 2}, "hf_array": [1, 1, 1, 1, 0, 0, 0, 0, 0, 0, 0, 0, 0, 0, 0, 0], "hf_method": "pyscf.scf.hf_symm.SymAdaptedRHF", "convergence_threshold": 1e-06, "point_group": {"groupname": "Dooh", "topgroup": "Dooh"}, "alpha": 0.8, "calculated_properties": {"HF": {"energy": -2.1602658905185077, "converged": true}, "MP2": {"energy": -2.1996162258419734, "converged": null}, "CISD": {"energy": -2.2145821112770063, "converged": true}, "CCSD": {"energy": -2.215143645677383, "converged": true, "t1_diagnostic": 0.008650550146843695}, "FCI": {"energy": -2.215456616982313, "converged": true, "spin_matches_target": true, "multiplicity": 1.0000000000000613, "oscillatory_converged": false, "oscillation_energy_change": null}}, "auxiliary_operators": {"number_operator": {"IIIIIIIIIIIIIIII": 8.0, "IIIIIIIIIIIIIZII": -0.5, "IIIIIIIIIIIIZIII": -0.5, "IIIIIIIIIIIZIIII": -0.5, "IIIIIIIIIIZIIIII": -0.5, "IIIIIIIIIZIIIIII": -0.5, "IIIIIIIIZIIIIIII": -0.5, "IIIIIIIIIIIIIIZI": -0.5, "IIIIIIIZIIIIIIII": -0.5, "IIIIIZIIIIIIIIII": -0.5, "IIIIZIIIIIIIIIII": -0.5, "IIIZIIIIIIIIIIII": -0.5, "IIZIIIIIIIIIIIII": -0.5, "IZIIIIIIIIIIIIII": -0.5, "ZIIIIIIIIIIIIIII": -0.5, "IIIIIIZIIIIIIIII": -0.5, "IIIIIIIIIIIIIIIZ": -0.5}, "N_alpha": {"IIIIIIIIIIIIIIII": 4.0, "ZIIIIIIIIIIIIIII": -0.5, "IIZIIIIIIIIIIIII": -0.5, "IIIIZIIIIIIIIIII": -0.5, "IIIIIIZIIIIIIIII": -0.5, "IIIIIIIIZIIIIIII": -0.5, "IIIIIIIIIIZIIIII": -0.5, "IIIIIIIIIIIIZIII": -0.5, "IIIIIIIIIIIIIIZI": -0.5}, "N_beta": {"IIIIIIIIIIIIIIII": 4.0, "IZIIIIIIIIIIIIII": -0.5, "IIIZIIIIIIIIIIII": -0.5, "IIIIIZIIIIIIIIII": -0.5, "IIIIIIIZIIIIIIII": -0.5, "IIIIIIIIIZIIIIII": -0.5, "IIIIIIIIIIIZIIII": -0.5, "IIIIIIIIIIIIIZII": -0.5, "IIIIIIIIIIIIIIIZ": -0.5}, "S^2_operator": {"IIIIIIIIIIIIIIII": 3.0, "ZZIIIIIIIIIIIIII": -0.375, "IIIIZZIIIIIIIIII": -0.375, "IIIIIIIIIIIIZZII": -0.375, "IIIIIIIIIIIIIIZZ": -0.375, "IIIIIIIIZZIIIIII": -0.375, "IIZZIIIIIIIIIIII": -0.375, "IIIIIIZZIIIIIIII": -0.375, "IIIIIIIIIIZZIIII": -0.375, "ZIIZIIIIIIIIIIII": -0.125, "ZIZIIIIIIIIIIIII": 0.125, "IIIIIIIIIIIIXYXY": 0.125, "IIIIIIIIIIIIXYYX": -0.125, "IIIIIIIIIIIIYYYY": 0.125, "IIIIIIIIIIIIXXXX": 0.125, "IIIIIIIIIIIIXXYY": 0.125, "IIIIIIIIIIIIYXXY": -0.125, "IIIIIIIIIIIIYXYX": 0.125, "IIIIIIIIIIXYIIXY": 0.125, "IIIIIIIIIIXYIIYX": -0.125, "IIIIIIIIIIYYIIXX": 0.125, "IIIIIIIIIIIIYYXX": 0.125, "ZIIIZIIIIIIIIIII": 0.125, "ZIIIIIZIIIIIIIII": 0.125, "IIIIIIIIIIYYIIYY": 0.125, "IZIIIIIIIIZIIIII": -0.125, "IZIIIIIIIZIIIIII": 0.125, "IZIIIIIIZIIIIIII": -0.125, "IZIIIIIZIIIIIIII": 0.125, "IZIIIIZIIIIIIIII": -0.125, "IZIIIZIIIIIIIIII": 0.125, "IZIIZIIIIIIIIIII": -0.125, "IZIZIIIIIIIIIIII": 0.125, "ZIIIIZIIIIIIIIII": -0.125, "IZZIIIIIIIIIIIII": -0.125, "ZIIIIIIIIIIIIIZI": 0.125, "ZIIIIIIIIIIIIZII": -0.125, "ZIIIIIIIIIIIZIII": 0.125, "ZIIIIIIIIIIZIIII": -0.125, "ZIIIIIIIIIZIIIII": 0.125, "ZIIIIIIIIZIIIIII": -0.125, "ZIIIIIIIZIIIIIII": 0.125, "ZIIIIIIZIIIIIIII": -0.125, "ZIIIIIIIIIIIIIIZ": -0.125, "IIIIIIIIIIXXIIXX": 0.125, "IIIIIIIIIIYXIIXY": -0.125, "IZIIIIIIIIIZIIII": 0.125, "IIIIIIIIXXIIXXII": 0.125, "IIIIIIIIXXIIYYII": 0.125, "IIIIIIIIYXIIXYII": -0.125, "IIIIIIIIYXIIYXII": 0.125, "IIIIIIIIXYXYIIII": 0.125, "IIIIIIIIXYYXIIII": -0.125, "IIIIIIIIYYXXIIII": 0.125, "IIIIIIIIYYYYIIII": 0.125, "IIIIIIIIXXXXIIII": 0.125, "IIIIIIIIXXYYIIII": 0.125, "IIIIIIIIYXXYIIII": -0.125, "IIIIIIIIYXYXIIII": 0.125, "IIIIIIXYIIIIIIXY": 0.125, "IIIIIIXYIIIIIIYX": -0.125, "IIIIIIYYIIIIIIXX": 0.125, "IIIIIIYYIIIIIIYY": 0.125, "IIIIIIXXIIIIIIXX": 0.125, "IIIIIIIIYYIIYYII": 0.125, "IIIIIIIIIIXXIIYY": 0.125, "IIIIIIIIYYIIXXII": 0.125, "IIIIIIIIXYIIXYII": 0.125, "IIIIIIIIIIYXIIYX": 0.125, "IIIIIIIIIIXYXYII": 0.125, "IIIIIIIIIIXYYXII": -0.125, "IIIIIIIIIIYYXXII": 0.125, "IIIIIIIIIIYYYYII": 0.125, "IIIIIIIIIIXXXXII": 0.125, "IIIIIIIIIIXXYYII": 0.125, "IIIIIIIIIIYXXYII": -0.125, "IIIIIIIIIIYXYXII": 0.125, "IIIIIIIIXYIIIIXY": 0.125, "IIIIIIIIXYIIIIYX": -0.125, "IIIIIIIIYYIIIIXX": 0.125, "IIIIIIIIYYIIIIYY": 0.125, "IIIIIIIIXXIIIIXX": 0.125, "IIIIIIIIXXIIIIYY": 0.125, "IIIIIIIIYXIIIIXY": -0.125, "IIIIIIIIYXIIIIYX": 0.125, "IIIIIIIIXYIIYXII": -0.125, "IZIIIIIIIIIIZIII": -0.125, "IZIIIIIIIIIIIIZI": -0.125, "IIIIIIXXIIIIIIYY": 0.125, "IIIIIIIZIIIIIIIZ": 0.125, "IIIIIIIZIIIIIIZI": -0.125, "IIIIIIIZIIIIIZII": 0.125, "IIIIIIIZIIIIZIII": -0.125, "IIIIIIIZIIIZIIII": 0.125, "IIIIIIIZIIZIIIII": -0.125, "IIIIIIIZIZIIIIII": 0.125, "IIIIIIIZZIIIIIII": -0.125, "IIIIIIZIIIIIIIIZ": -0.125, "IIIIIIZIIIIIIIZI": 0.125, "IIIIIIZIIIIIIZII": -0.125, "IIIIIIZIIIIIZIII": 0.125, "IIIIIIZIIIIZIIII": -0.125, "IIIIIIZIIIZIIIII": 0.125, "IIIIIIZIIZIIIIII": -0.125, "IIIIIIZIZIIIIIII": 0.125, "IIIIIZIIIIIIIIIZ": 0.125, "IIIIIIIIZIZIIIII": 0.125, "IIIIIIIIZIIZIIII": -0.125, "IIIIIIIIZIIIZIII": 0.125, "IIIIIIIIZIIIIZII": -0.125, "IIIIIIIIIIIIZIIZ": -0.125, "IIIIIIIIIIIIZIZI": 0.125, "IIIIIIIIIIIZIIIZ": 0.125, "IIIIIIIIIIIZIIZI": -0.125, "IIIIIIIIIIIZIZII": 0.125, "IIIIIIIIIIIZZIII": -0.125, "IIIIIIIIIIZIIIIZ": -0.125, "IIIIIIIIIIZIIIZI": 0.125, "IIIIIZIIIIIIIIZI": -0.125, "IIIIIIIIIIZIIZII": -0.125, "IIIIIIIIIZIIIIIZ": 0.125, "IIIIIIIIIZIIIIZI": -0.125, "IIIIIIIIIZIIIZII": 0.125, "IIIIIIIIIZIIZIII": -0.125, "IIIIIIIIIZIZIIII": 0.125, "IIIIIIIIIZZIIIII": -0.125, "IIIIIIIIZIIIIIIZ": -0.125, "IIIIIIIIZIIIIIZI": 0.125, "IIIIIIIIIIZIZIII": 0.125, "IIIIIZIIIIIIIZII": 0.125, "IIIIIZIIIIIIZIII": -0.125, "IIIIIZIIIIIZIIII": 0.125, "IIIZIIIIZIIIIIII": -0.125, "IIIZIIIZIIIIIIII": 0.125, "IIIZIIZIIIIIIIII": -0.125, "IIIZIZIIIIIIIIII": 0.125, "IIIZZIIIIIIIIIII": -0.125, "IIZIIIIIIIIIIIIZ": -0.125, "IIZIIIIIIIIIIIZI": 0.125, "IIZIIIIIIIIIIZII": -0.125, "IIIZIIIIIZIIIIII": 0.125, "IIZIIIIIIIIIZIII": 0.125, "IIZIIIIIIIZIIIII": 0.125, "IIZIIIIIIZIIIIII": -0.125, "IIZIIIIIZIIIIIII": 0.125, "IIZIIIIZIIIIIIII": -0.125, "IIZIIIZIIIIIIIII": 0.125, "IIZIIZIIIIIIIIII": -0.125, "IIZIZIIIIIIIIIII": 0.125, "IZIIIIIIIIIIIIIZ": 0.125, "IIZIIIIIIIIZIIII": -0.125, "IZIIIIIIIIIIIZII": 0.125, "IIIZIIIIIIZIIIII": -0.125, "IIIZIIIIIIIIZIII": -0.125, "IIIIIZIIIIZIIIII": -0.125, "IIIIIZIIIZIIIIII": 0.125, "IIIIIZIIZIIIIIII": -0.125, "IIIIIZIZIIIIIIII": 0.125, "IIIIIZZIIIIIIIII": -0.125, "IIIIZIIIIIIIIIIZ": -0.125, "IIIIZIIIIIIIIIZI": 0.125, "IIIIZIIIIIIIIZII": -0.125, "IIIZIIIIIIIZIIII": 0.125, "IIIIZIIIIIIIZIII": 0.125, "IIIIZIIIIIZIIIII": 0.125, "IIIIZIIIIZIIIIII": -0.125, "IIIIZIIIZIIIIIII": 0.125, "IIIIZIIZIIIIIIII": -0.125, "IIIIZIZIIIIIIIII": 0.125, "IIIZIIIIIIIIIIIZ": 0.125, "IIIZIIIIIIIIIIZI": -0.125, "IIIZIIIIIIIIIZII": 0.125, "IIIIZIIIIIIZIIII": -0.125, "IIIIIIYXIIIIIIXY": -0.125, "IIIIIIXYIIIIXYII": 0.125, "IIIIIIIIIIIIIZZI": -0.125, "IIXXXXIIIIIIIIII": 0.125, "IIXXYYIIIIIIIIII": 0.125, "IIYXXYIIIIIIIIII": -0.125, "IIYXYXIIIIIIIIII": 0.125, "XYIIIIIIIIIIIIXY": 0.125, "XYIIIIIIIIIIIIYX": -0.125, "YYIIIIIIIIIIIIXX": 0.125, "YYIIIIIIIIIIIIYY": 0.125, "XXIIIIIIIIIIIIXX": 0.125, "XXIIIIIIIIIIIIYY": 0.125, "YXIIIIIIIIIIIIXY": -0.125, "YXIIIIIIIIIIIIYX": 0.125, "XYIIIIIIIIIIXYII": 0.125, "XYIIIIIIIIIIYXII": -0.125, "YYIIIIIIIIIIXXII": 0.125, "YYIIIIIIIIIIYYII": 0.125, "XXIIIIIIIIIIXXII": 0.125, "IIYYYYIIIIIIIIII": 0.125, "XXIIIIIIIIIIYYII": 0.125, "IIYYXXIIIIIIIIII": 0.125, "IIXYXYIIIIIIIIII": 0.125, "IIYXIIIIIIYXIIII": 0.125, "IIXYIIIIXYIIIIII": 0.125, "IIXYIIIIYXIIIIII": -0.125, "IIYYIIIIXXIIIIII": 0.125, "IIYYIIIIYYIIIIII": 0.125, "IIXXIIIIXXIIIIII": 0.125, "IIXXIIIIYYIIIIII": 0.125, "IIYXIIIIXYIIIIII": -0.125, "IIYXIIIIYXIIIIII": 0.125, "IIXYIIXYIIIIIIII": 0.125, "IIXYIIYXIIIIIIII": -0.125, "IIYYIIXXIIIIIIII": 0.125, "IIYYIIYYIIIIIIII": 0.125, "IIXXIIXXIIIIIIII": 0.125, "IIXXIIYYIIIIIIII": 0.125, "IIYXIIXYIIIIIIII": -0.125, "IIYXIIYXIIIIIIII": 0.125, "IIXYYXIIIIIIIIII": -0.125, "YXIIIIIIIIIIXYII": -0.125, "YXIIIIIIIIIIYXII": 0.125, "XYIIIIIIIIXYIIII": 0.125, "YXIIIIYXIIIIIIII": 0.125, "XYIIXYIIIIIIIIII": 0.125, "XYIIYXIIIIIIIIII": -0.125, "YYIIXXIIIIIIIIII": 0.125, "YYIIYYIIIIIIIIII": 0.125, "XXIIXXIIIIIIIIII": 0.125, "XXIIYYIIIIIIIIII": 0.125, "YXIIXYIIIIIIIIII": -0.125, "YXIIYXIIIIIIIIII": 0.125, "XYXYIIIIIIIIIIII": 0.125, "XYYXIIIIIIIIIIII": -0.125, "YYXXIIIIIIIIIIII": 0.125, "YYYYIIIIIIIIIIII": 0.125, "XXXXIIIIIIIIIIII": 0.125, "XXYYIIIIIIIIIIII": 0.125, "YXXYIIIIIIIIIIII": -0.125, "YXYXIIIIIIIIIIII": 0.125, "YXIIIIXYIIIIIIII": -0.125, "XXIIIIYYIIIIIIII": 0.125, "XXIIIIXXIIIIIIII": 0.125, "YYIIIIYYIIIIIIII": 0.125, "XYIIIIIIIIYXIIII": -0.125, "YYIIIIIIIIXXIIII": 0.125, "YYIIIIIIIIYYIIII": 0.125, "XXIIIIIIIIXXIIII": 0.125, "XXIIIIIIIIYYIIII": 0.125, "YXIIIIIIIIXYIIII": -0.125, "YXIIIIIIIIYXIIII": 0.125, "XYIIIIIIXYIIIIII": 0.125, "IIYXIIIIIIXYIIII": -0.125, "XYIIIIIIYXIIIIII": -0.125, "YYIIIIIIYYIIIIII": 0.125, "XXIIIIIIXXIIIIII": 0.125, "XXIIIIIIYYIIIIII": 0.125, "YXIIIIIIXYIIIIII": -0.125, "YXIIIIIIYXIIIIII": 0.125, "XYIIIIXYIIIIIIII": 0.125, "XYIIIIYXIIIIIIII": -0.125, "YYIIIIXXIIIIIIII": 0.125, "YYIIIIIIXXIIIIII": 0.125, "IIXXIIIIIIYYIIII": 0.125, "IIXXIIIIIIXXIIII": 0.125, "IIYYIIIIIIYYIIII": 0.125, "IIIIIIYXYXIIIIII": 0.125, "IIIIXYIIIIIIIIXY": 0.125, "IIIIXYIIIIIIIIYX": -0.125, "IIIIYYIIIIIIIIXX": 0.125, "IIIIYYIIIIIIIIYY": 0.125, "IIIIXXIIIIIIIIXX": 0.125, "IIIIXXIIIIIIIIYY": 0.125, "IIIIYXIIIIIIIIXY": -0.125, "IIIIYXIIIIIIIIYX": 0.125, "IIIIXYIIIIIIXYII": 0.125, "IIIIXYIIIIIIYXII": -0.125, "IIIIYYIIIIIIXXII": 0.125, "IIIIYYIIIIIIYYII": 0.125, "IIIIXXIIIIIIXXII": 0.125, "IIIIXXIIIIIIYYII": 0.125, "IIIIYXIIIIIIXYII": -0.125, "IIIIYXIIIIIIYXII": 0.125, "IIIIIIYXXYIIIIII": -0.125, "IIIIIIXXYYIIIIII": 0.125, "IIIIIIXXXXIIIIII": 0.125, "IIIIIIYYYYIIIIII": 0.125, "IIIIIIXYIIIIYXII": -0.125, "IIIIIIYYIIIIXXII": 0.125, "IIIIIIYYIIIIYYII": 0.125, "IIIIIIXXIIIIXXII": 0.125, "IIIIIIXXIIIIYYII": 0.125, "IIIIIIYXIIIIXYII": -0.125, "IIIIIIYXIIIIYXII": 0.125, "IIIIIIXYIIXYIIII": 0.125, "IIIIXYIIIIXYIIII": 0.125, "IIIIIIXYIIYXIIII": -0.125, "IIIIIIYYIIYYIIII": 0.125, "IIIIIIXXIIXXIIII": 0.125, "IIIIIIXXIIYYIIII": 0.125, "IIIIIIYXIIXYIIII": -0.125, "IIIIIIYXIIYXIIII": 0.125, "IIIIIIXYXYIIIIII": 0.125, "IIIIIIXYYXIIIIII": -0.125, "IIIIIIYYXXIIIIII": 0.125, "IIIIIIYYIIXXIIII": 0.125, "IIIIIIYXIIIIIIYX": 0.125, "IIIIXYIIIIYXIIII": -0.125, "IIIIYYIIIIYYIIII": 0.125, "IIYYIIIIIIIIIIXX": 0.125, "IIYYIIIIIIIIIIYY": 0.125, "IIXXIIIIIIIIIIXX": 0.125, "IIXXIIIIIIIIIIYY": 0.125, "IIYXIIIIIIIIIIXY": -0.125, "IIYXIIIIIIIIIIYX": 0.125, "IIXYIIIIIIIIXYII": 0.125, "IIXYIIIIIIIIYXII": -0.125, "IIYYIIIIIIIIXXII": 0.125, "IIYYIIIIIIIIYYII": 0.125, "IIXXIIIIIIIIXXII": 0.125, "IIXXIIIIIIIIYYII": 0.125, "IIYXIIIIIIIIXYII": -0.125, "IIYXIIIIIIIIYXII": 0.125, "IIXYIIIIIIXYIIII": 0.125, "IIXYIIIIIIYXIIII": -0.125, "IIYYIIIIIIXXIIII": 0.125, "IIXYIIIIIIIIIIYX": -0.125, "IIXYIIIIIIIIIIXY": 0.125, "IIIIYXYXIIIIIIII": 0.125, "IIIIYXXYIIIIIIII": -0.125, "IIIIXXIIIIXXIIII": 0.125, "IIIIXXIIIIYYIIII": 0.125, "IIIIYXIIIIXYIIII": -0.125, "IIIIYXIIIIYXIIII": 0.125, "IIIIXYIIXYIIIIII": 0.125, "IIIIXYIIYXIIIIII": -0.125, "IIIIYYIIXXIIIIII": 0.125, "IIIIYYIIYYIIIIII": 0.125, "IIIIYYIIIIXXIIII": 0.125, "IIIIXXIIXXIIIIII": 0.125, "IIIIYXIIXYIIIIII": -0.125, "IIIIYXIIYXIIIIII": 0.125, "IIIIXYXYIIIIIIII": 0.125, "IIIIXYYXIIIIIIII": -0.125, "IIIIYYXXIIIIIIII": 0.125, "IIIIYYYYIIIIIIII": 0.125, "IIIIXXXXIIIIIIII": 0.125, "IIIIXXYYIIIIIIII": 0.125, "IIIIXXIIYYIIIIII": 0.125, "IIIIIIIIIIIIIZIZ": 0.125}, "UCCSD_operator": {"IIYYXYIIIIIIIIII": -0.014871549871577973, "IIXXXYIIIIIIIIII": 0.014871549871577973, "IIXYXXIIIIIIIIII": -0.014871549871577973, "IIXXYXIIIIIIIIII": 0.014871549871577973, "IIXYYYIIIIIIIIII": 0.014871549871577973, "IIYXYYIIIIIIIIII": 0.014871549871577973, "IIYYYXIIIIIIIIII": -0.014871549871577973, "IIYXXXIIIIIIIIII": -0.014871549871577973, "XXIIYXIIIIIIIIII": 0.005330508480034204, "YYIIYXIIIIIIIIII": -0.005330508480034204, "YXIIYYIIIIIIIIII": 0.005330508480034204, "YXIIXXIIIIIIIIII": -0.005330508480034204, "XYIIXXIIIIIIIIII": -0.005330508480034204, "YYIIXYIIIIIIIIII": -0.005330508480034204, "XYIIYYIIIIIIIIII": 0.005330508480034204, "XXIIXYIIIIIIIIII": 0.005330508480034204, "IIIXZZZZZZZYIIII": 0.005306731171230875, "IIIYZZZZZZZXIIII": -0.005306731171230875, "IIYZZZZZZZXIIIII": -0.005306731171230875, "IIXZZZZZZZYIIIII": 0.005306731171230875, "IIYZZZXIIIIIIIII": -0.004921740391816631, "IIXZZZYIIIIIIIII": 0.004921740391816631, "IIIYZZZXIIIIIIII": -0.004921740391816631, "IIIXZZZYIIIIIIII": 0.004921740391816631, "IIYYIYZZZZZZXIII": -0.004355093697266111, "IIYXIYZZZZZZYIII": 0.004355093697266111, "IIYYIXZZZZZZYIII": -0.004355093697266111, "IIXXIXZZZZZZYIII": 0.004355093697266111, "IIXXIYZZZZZZXIII": 0.004355093697266111, "IIXYIXZZZZZZXIII": -0.004355093697266111, "IIXYIYZZZZZZYIII": 0.004355093697266111, "IIYXIXZZZZZZXIII": -0.004355093697266111, "IIYYXZZZZZZZZYII": 0.004355093697266111, "IIYXYZZZZZZZZYII": -0.004355093697266111, "IIYYYZZZZZZZZXII": 0.004355093697266111, "IIXXYZZZZZZZZXII": -0.004355093697266111, "IIYXXZZZZZZZZXII": 0.004355093697266111, "IIXYXZZZZZZZZXII": 0.004355093697266111, "IIXXXZZZZZZZZYII": -0.004355093697266111, "IIXYYZZZZZZZZYII": -0.004355093697266111, "XZZXYZZXIIIIIIII": -0.004242840575740279, "IYXIIXXIIIIIIIII": 0.004242840575740279, "IXXIIYXIIIIIIIII": -0.004242840575740279, "IYYIIYXIIIIIIIII": 0.004242840575740279, "IYXIIYYIIIIIIIII": -0.004242840575740279, "IXYIIYYIIIIIIIII": -0.004242840575740279, "IXYIIXXIIIIIIIII": 0.004242840575740279, "IXXIIXYIIIIIIIII": -0.004242840575740279, "IYYIIXYIIIIIIIII": 0.004242840575740279, "YZZYXZZYIIIIIIII": 0.004242840575740279, "YZZYYZZXIIIIIIII": 0.004242840575740279, "YZZXYZZYIIIIIIII": -0.004242840575740279, "XZZYYZZYIIIIIIII": -0.004242840575740279, "XZZYXZZXIIIIIIII": 0.004242840575740279, "XZZXXZZYIIIIIIII": -0.004242840575740279, "YZZXXZZXIIIIIIII": 0.004242840575740279, "XZZXYZZZZZZZZZZX": 0.0037759892796607806, "YZZYYZZZZZZZZZZX": -0.0037759892796607806, "YZZXYZZZZZZZZZZY": 0.0037759892796607806, "XZZYYZZZZZZZZZZY": 0.0037759892796607806, "IYXIIYZZZZZZZZYI": 0.0037759892796607806, "IXYIIYZZZZZZZZYI": 0.0037759892796607806, "IYXIIXZZZZZZZZXI": -0.0037759892796607806, "IXYIIXZZZZZZZZXI": -0.0037759892796607806, "YZZXXZZZZZZZZZZX": -0.0037759892796607806, "IXXIIXZZZZZZZZYI": 0.0037759892796607806, "IXXIIYZZZZZZZZXI": 0.0037759892796607806, "IYYIIYZZZZZZZZXI": -0.0037759892796607806, "YZZYXZZZZZZZZZZY": -0.0037759892796607806, "XZZXXZZZZZZZZZZY": 0.0037759892796607806, "XZZYXZZZZZZZZZZX": -0.0037759892796607806, "IYYIIXZZZZZZZZYI": -0.0037759892796607806, "YZZZXIIIIIIIIIII": -0.0037552706204632643, "XZZZYIIIIIIIIIII": 0.0037552706204632643, "IXZZZYIIIIIIIIII": 0.0037552706204632643, "IYZZZXIIIIIIIIII": -0.0037552706204632643, "IIXXIIYXIIIIIIII": 0.003688616798986361, "IIYYIIYXIIIIIIII": -0.003688616798986361, "IIYYIIXYIIIIIIII": -0.003688616798986361, "IIYXIIYYIIIIIIII": 0.003688616798986361, "IIXYIIYYIIIIIIII": 0.003688616798986361, "IIYXIIXXIIIIIIII": -0.003688616798986361, "IIXYIIXXIIIIIIII": -0.003688616798986361, "IIXXIIXYIIIIIIII": 0.003688616798986361, "XXIIIYZZZZZZXIII": 0.0030824232719752144, "YYIIIYZZZZZZXIII": -0.0030824232719752144, "YXIIIXZZZZZZXIII": -0.0030824232719752144, "XYIIIYZZZZZZYIII": 0.0030824232719752144, "YXIIIYZZZZZZYIII": 0.0030824232719752144, "YYIIXZZZZZZZZYII": 0.0030824232719752144, "YYIIYZZZZZZZZXII": 0.0030824232719752144, "XYIIXZZZZZZZZXII": 0.0030824232719752144, "YXIIXZZZZZZZZXII": 0.0030824232719752144, "YXIIYZZZZZZZZYII": -0.0030824232719752144, "XXIIYZZZZZZZZXII": -0.0030824232719752144, "XXIIXZZZZZZZZYII": -0.0030824232719752144, "XYIIIXZZZZZZXIII": -0.0030824232719752144, "XYIIYZZZZZZZZYII": -0.0030824232719752144, "XXIIIXZZZZZZYIII": 0.0030824232719752144, "YYIIIXZZZZZZYIII": -0.0030824232719752144, "IXZXIYZXIIIIIIII": -0.0030061566362315625, "IYZYIYZXIIIIIIII": 0.0030061566362315625, "IYZXIYZYIIIIIIII": -0.0030061566362315625, "IXZYIYZYIIIIIIII": -0.0030061566362315625, "IYZXIXZXIIIIIIII": 0.0030061566362315625, "IXZYIXZXIIIIIIII": 0.0030061566362315625, "IXZXIXZYIIIIIIII": -0.0030061566362315625, "IYZYIXZYIIIIIIII": 0.0030061566362315625, "YZYIYZXIIIIIIIII": 0.0030061566362315625, "YZYIXZYIIIIIIIII": 0.0030061566362315625, "XZXIXZYIIIIIIIII": -0.0030061566362315625, "XZYIXZXIIIIIIIII": 0.0030061566362315625, "YZXIXZXIIIIIIIII": 0.0030061566362315625, "XZYIYZYIIIIIIIII": -0.0030061566362315625, "XZXIYZXIIIIIIIII": -0.0030061566362315625, "YZXIYZYIIIIIIIII": -0.0030061566362315625, "YYIIIIIIIIIIIIXY": -0.002658208775311218, "YYIIIIIIIIIIIIYX": -0.002658208775311218, "YXIIIIIIIIIIIIYY": 0.002658208775311218, "XYIIIIIIIIIIIIYY": 0.002658208775311218, "YXIIIIIIIIIIIIXX": -0.002658208775311218, "XYIIIIIIIIIIIIXX": -0.002658208775311218, "XXIIIIIIIIIIIIXY": 0.002658208775311218, "XXIIIIIIIIIIIIYX": 0.002658208775311218, "IXZZZZZZZYIIIIII": 0.0025774930932378013, "YZZZZZZZXIIIIIII": -0.0025774930932378013, "XZZZZZZZYIIIIIII": 0.0025774930932378013, "IYZZZZZZZXIIIIII": -0.0025774930932378013, "YXIIIIYYIIIIIIII": 0.0025519180031784, "XYIIIIYYIIIIIIII": 0.0025519180031784, "YXIIIIXXIIIIIIII": -0.0025519180031784, "XXIIIIYXIIIIIIII": 0.0025519180031784, "YYIIIIYXIIIIIIII": -0.0025519180031784, "XYIIIIXXIIIIIIII": -0.0025519180031784, "XXIIIIXYIIIIIIII": 0.0025519180031784, "YYIIIIXYIIIIIIII": -0.0025519180031784, "IIYYIXZZYIIIIIII": -0.002522003146895572, "IIXXIXZZYIIIIIII": 0.002522003146895572, "IIYXIYZZYIIIIIII": 0.002522003146895572, "IIYYXZZZZYIIIIII": 0.002522003146895572, "IIXYIXZZXIIIIIII": -0.002522003146895572, "IIXXXZZZZYIIIIII": -0.002522003146895572, "IIXYXZZZZXIIIIII": 0.002522003146895572, "IIYXYZZZZYIIIIII": -0.002522003146895572, "IIYYYZZZZXIIIIII": 0.002522003146895572, "IIXYYZZZZYIIIIII": -0.002522003146895572, "IIYXXZZZZXIIIIII": 0.002522003146895572, "IIYYIYZZXIIIIIII": -0.002522003146895572, "IIXXIYZZXIIIIIII": 0.002522003146895572, "IIXYIYZZYIIIIIII": 0.002522003146895572, "IIYXIXZZXIIIIIII": -0.002522003146895572, "IIXXYZZZZXIIIIII": -0.002522003146895572, "YYIIIIIIXYIIIIII": -0.002495242302874494, "XXIIIIIIXYIIIIII": 0.002495242302874494, "XYIIIIIIXXIIIIII": -0.002495242302874494, "YXIIIIIIXXIIIIII": -0.002495242302874494, "XYIIIIIIYYIIIIII": 0.002495242302874494, "YYIIIIIIYXIIIIII": -0.002495242302874494, "YXIIIIIIYYIIIIII": 0.002495242302874494, "XXIIIIIIYXIIIIII": 0.002495242302874494, "IIXYIIIIIIIIYYII": 0.002464205615831223, "IIYXIIIIIIIIXXII": -0.002464205615831223, "IIXXIIIIIIIIXYII": 0.002464205615831223, "IIYYIIIIIIIIXYII": -0.002464205615831223, "IIYXIIIIIIIIYYII": 0.002464205615831223, "IIYYIIIIIIIIYXII": -0.002464205615831223, "IIXXIIIIIIIIYXII": 0.002464205615831223, "IIXYIIIIIIIIXXII": -0.002464205615831223, "IIYXIIIIXXIIIIII": -0.002452472789205757, "IIXXIIIIYXIIIIII": 0.002452472789205757, "IIYYIIIIYXIIIIII": -0.002452472789205757, "IIXYIIIIXXIIIIII": -0.002452472789205757, "IIYYIIIIXYIIIIII": -0.002452472789205757, "IIXXIIIIXYIIIIII": 0.002452472789205757, "IIXYIIIIYYIIIIII": 0.002452472789205757, "IIYXIIIIYYIIIIII": 0.002452472789205757, "IIYYIIIIIIXYIIII": -0.0023862447578453963, "IIXXIIIIIIXYIIII": 0.0023862447578453963, "IIXYIIIIIIXXIIII": -0.0023862447578453963, "IIYYIIIIIIYXIIII": -0.0023862447578453963, "IIXYIIIIIIYYIIII": 0.0023862447578453963, "IIYXIIIIIIYYIIII": 0.0023862447578453963, "IIXXIIIIIIYXIIII": 0.0023862447578453963, "IIYXIIIIIIXXIIII": -0.0023862447578453963, "YYIIIIIIIIIIXYII": -0.0023526202867800643, "XXIIIIIIIIIIYXII": 0.0023526202867800643, "YYIIIIIIIIIIYXII": -0.0023526202867800643, "XYIIIIIIIIIIYYII": 0.0023526202867800643, "YXIIIIIIIIIIYYII": 0.0023526202867800643, "XYIIIIIIIIIIXXII": -0.0023526202867800643, "XXIIIIIIIIIIXYII": 0.0023526202867800643, "YXIIIIIIIIIIXXII": -0.0023526202867800643, "XZZYIYZZZZZZZZYI": -0.002299634683645309, "XZZYIXZZZZZZZZXI": 0.002299634683645309, "YZZXIXZZZZZZZZXI": 0.002299634683645309, "IYYIXZZZZZZZZZZY": 0.002299634683645309, "IXXIXZZZZZZZZZZY": -0.002299634683645309, "YZZXIYZZZZZZZZYI": -0.002299634683645309, "YZZYIYZZZZZZZZXI": 0.002299634683645309, "XZZXIYZZZZZZZZXI": -0.002299634683645309, "XZZXIXZZZZZZZZYI": -0.002299634683645309, "YZZYIXZZZZZZZZYI": 0.002299634683645309, "IXXIYZZZZZZZZZZX": -0.002299634683645309, "IYXIYZZZZZZZZZZY": -0.002299634683645309, "IYYIYZZZZZZZZZZX": 0.002299634683645309, "IYXIXZZZZZZZZZZX": 0.002299634683645309, "IXYIXZZZZZZZZZZX": 0.002299634683645309, "IXYIYZZZZZZZZZZY": -0.002299634683645309, "IYXIIIIIIIIIIYYI": -0.002138894664345848, "IXXIIIIIIIIIIYXI": -0.002138894664345848, "IYYIIIIIIIIIIYXI": 0.002138894664345848, "IYYIIIIIIIIIIXYI": 0.002138894664345848, "IXYIIIIIIIIIIYYI": -0.002138894664345848, "XZZXIIIIIIIIYZZX": -0.002138894664345848, "YZZYIIIIIIIIYZZX": 0.002138894664345848, "YZZXIIIIIIIIYZZY": -0.002138894664345848, "YZZXIIIIIIIIXZZX": 0.002138894664345848, "XZZYIIIIIIIIXZZX": 0.002138894664345848, "XZZXIIIIIIIIXZZY": -0.002138894664345848, "YZZYIIIIIIIIXZZY": 0.002138894664345848, "IXXIIIIIIIIIIXYI": -0.002138894664345848, "IXYIIIIIIIIIIXXI": 0.002138894664345848, "IYXIIIIIIIIIIXXI": 0.002138894664345848, "XZZYIIIIIIIIYZZY": -0.002138894664345848, "YXIIIIXZZZZZZZZX": 0.002060110258008147, "XXIIIIIXZZZZZZYI": 0.002060110258008147, "XYIIIIIXZZZZZZXI": -0.002060110258008147, "YXIIIIIXZZZZZZXI": -0.002060110258008147, "XYIIIIIYZZZZZZYI": 0.002060110258008147, "YXIIIIIYZZZZZZYI": 0.002060110258008147, "YYIIIIIYZZZZZZXI": -0.002060110258008147, "XXIIIIIYZZZZZZXI": 0.002060110258008147, "XXIIIIYZZZZZZZZX": -0.002060110258008147, "YYIIIIYZZZZZZZZX": 0.002060110258008147, "YXIIIIYZZZZZZZZY": -0.002060110258008147, "XYIIIIYZZZZZZZZY": -0.002060110258008147, "YYIIIIXZZZZZZZZY": 0.002060110258008147, "XYIIIIXZZZZZZZZX": 0.002060110258008147, "YYIIIIIXZZZZZZYI": -0.002060110258008147, "XXIIIIXZZZZZZZZY": -0.002060110258008147, "YZZYIIIIYZZXIIII": -0.001995265569610946, "YZZXIIIIYZZYIIII": 0.001995265569610946, "XZZYIIIIYZZYIIII": 0.001995265569610946, "YZZXIIIIXZZXIIII": -0.001995265569610946, "XZZYIIIIXZZXIIII": -0.001995265569610946, "XZZXIIIIXZZYIIII": 0.001995265569610946, "YZZYIIIIXZZYIIII": -0.001995265569610946, "IYYIIIIIIXYIIIII": -0.001995265569610946, "IXXIIIIIIYXIIIII": 0.001995265569610946, "IYYIIIIIIYXIIIII": -0.001995265569610946, "IYXIIIIIIYYIIIII": 0.001995265569610946, "IYXIIIIIIXXIIIII": -0.001995265569610946, "IXYIIIIIIXXIIIII": -0.001995265569610946, "IXXIIIIIIXYIIIII": 0.001995265569610946, "IXYIIIIIIYYIIIII": 0.001995265569610946, "XZZXIIIIYZZXIIII": 0.001995265569610946, "IIYYIIIIIXZZYIII": 0.0018533615432803528, "IIXXIIIIIXZZYIII": -0.0018533615432803528, "IIXYIIIIIXZZXIII": 0.0018533615432803528, "IIXYIIIIIYZZYIII": -0.0018533615432803528, "IIYXIIIIIYZZYIII": -0.0018533615432803528, "IIYYIIIIIYZZXIII": 0.0018533615432803528, "IIXXIIIIIYZZXIII": -0.0018533615432803528, "IIXXIIIIYZZZZXII": 0.0018533615432803528, "IIYYIIIIYZZZZXII": -0.0018533615432803528, "IIYXIIIIYZZZZYII": 0.0018533615432803528, "IIYXIIIIIXZZXIII": 0.0018533615432803528, "IIYXIIIIXZZZZXII": -0.0018533615432803528, "IIXYIIIIXZZZZXII": -0.0018533615432803528, "IIXXIIIIXZZZZYII": 0.0018533615432803528, "IIYYIIIIXZZZZYII": -0.0018533615432803528, "IIXYIIIIYZZZZYII": 0.0018533615432803528, "IIXXIIIIIIIIIIXY": 0.0017311776399328443, "IIXYIIIIIIIIIIXX": -0.0017311776399328443, "IIYXIIIIIIIIIIXX": -0.0017311776399328443, "IIYXIIIIIIIIIIYY": 0.0017311776399328443, "IIYYIIIIIIIIIIYX": -0.0017311776399328443, "IIXXIIIIIIIIIIYX": 0.0017311776399328443, "IIXYIIIIIIIIIIYY": 0.0017311776399328443, "IIYYIIIIIIIIIIXY": -0.0017311776399328443, "YZZYIXZZZZYIIIII": -0.001701136230099996, "YZZYIYZZZZXIIIII": -0.001701136230099996, "YZZXIYZZZZYIIIII": 0.001701136230099996, "XZZYIYZZZZYIIIII": 0.001701136230099996, "YZZXIXZZZZXIIIII": -0.001701136230099996, "XZZYIXZZZZXIIIII": -0.001701136230099996, "XZZXIXZZZZYIIIII": 0.001701136230099996, "IXXIXZZZZZZYIIII": 0.001701136230099996, "IYYIXZZZZZZYIIII": -0.001701136230099996, "IXXIYZZZZZZXIIII": 0.001701136230099996, "IYYIYZZZZZZXIIII": -0.001701136230099996, "IYXIYZZZZZZYIIII": 0.001701136230099996, "IYXIXZZZZZZXIIII": -0.001701136230099996, "IXYIXZZZZZZXIIII": -0.001701136230099996, "IXYIYZZZZZZYIIII": 0.001701136230099996, "XZZXIYZZZZXIIIII": 0.001701136230099996, "XZZXIIIIIXYIIIII": -0.001636619667595247, "YZZYIIIIIXYIIIII": 0.001636619667595247, "XZZYIIIIIXXIIIII": 0.001636619667595247, "YZZYIIIIIYXIIIII": 0.001636619667595247, "IYYIIIIIXZZYIIII": 0.001636619667595247, "IXXIIIIIXZZYIIII": -0.001636619667595247, "IXYIIIIIXZZXIIII": 0.001636619667595247, "XZZYIIIIIYYIIIII": -0.001636619667595247, "YZZXIIIIIXXIIIII": 0.001636619667595247, "YZZXIIIIIYYIIIII": -0.001636619667595247, "XZZXIIIIIYXIIIII": -0.001636619667595247, "IXXIIIIIYZZXIIII": -0.001636619667595247, "IYYIIIIIYZZXIIII": 0.001636619667595247, "IYXIIIIIYZZYIIII": -0.001636619667595247, "IXYIIIIIYZZYIIII": -0.001636619667595247, "IYXIIIIIXZZXIIII": 0.001636619667595247, "XZZYIIIYYIIIIIII": 0.001495424414197477, "XZZXIIIYXIIIIIII": 0.001495424414197477, "IYXIIIXZZXIIIIII": -0.001495424414197477, "IXXIIIXZZYIIIIII": 0.001495424414197477, "IYYIIIXZZYIIIIII": -0.001495424414197477, "YZZYIIIYXIIIIIII": -0.001495424414197477, "IXYIIIXZZXIIIIII": -0.001495424414197477, "XZZYIIIXXIIIIIII": -0.001495424414197477, "XZZXIIIXYIIIIIII": 0.001495424414197477, "YZZYIIIXYIIIIIII": -0.001495424414197477, "IXYIIIYZZYIIIIII": 0.001495424414197477, "YZZXIIIXXIIIIIII": -0.001495424414197477, "IYXIIIYZZYIIIIII": 0.001495424414197477, "IYYIIIYZZXIIIIII": -0.001495424414197477, "IXXIIIYZZXIIIIII": 0.001495424414197477, "YZZXIIIYYIIIIIII": 0.001495424414197477, "IXZXIXZZZZZZZZZY": 0.0014763545960154718, "YZXIXZZZZZZZZZXI": -0.0014763545960154718, "XZYIYZZZZZZZZZYI": 0.0014763545960154718, "YZXIYZZZZZZZZZYI": 0.0014763545960154718, "YZYIYZZZZZZZZZXI": -0.0014763545960154718, "XZXIYZZZZZZZZZXI": 0.0014763545960154718, "IXZYIXZZZZZZZZZX": -0.0014763545960154718, "IYZYIXZZZZZZZZZY": -0.0014763545960154718, "IYZXIXZZZZZZZZZX": -0.0014763545960154718, "YZYIXZZZZZZZZZYI": -0.0014763545960154718, "XZXIXZZZZZZZZZYI": 0.0014763545960154718, "XZYIXZZZZZZZZZXI": -0.0014763545960154718, "IXZYIYZZZZZZZZZY": 0.0014763545960154718, "IXZXIYZZZZZZZZZX": 0.0014763545960154718, "IYZYIYZZZZZZZZZX": -0.0014763545960154718, "IYZXIYZZZZZZZZZY": 0.0014763545960154718, "IYXIIYZZZZYIIIII": -0.0014495634156915032, "IYYIIYZZZZXIIIII": 0.0014495634156915032, "IXXIIYZZZZXIIIII": -0.0014495634156915032, "XZZXYZZZZZZXIIII": -0.0014495634156915032, "YZZYYZZZZZZXIIII": 0.0014495634156915032, "YZZYXZZZZZZYIIII": 0.0014495634156915032, "XZZXXZZZZZZYIIII": -0.0014495634156915032, "XZZYXZZZZZZXIIII": 0.0014495634156915032, "YZZXXZZZZZZXIIII": 0.0014495634156915032, "XZZYYZZZZZZYIIII": -0.0014495634156915032, "IYYIIXZZZZYIIIII": 0.0014495634156915032, "YZZXYZZZZZZYIIII": -0.0014495634156915032, "IXXIIXZZZZYIIIII": -0.0014495634156915032, "IXYIIXZZZZXIIIII": 0.0014495634156915032, "IYXIIXZZZZXIIIII": 0.0014495634156915032, "IXYIIYZZZZYIIIII": -0.0014495634156915032, "IXYIIIIYYIIIIIII": -0.0014494814724924964, "IYXIIIIXXIIIIIII": 0.0014494814724924964, "IYXIIIIYYIIIIIII": -0.0014494814724924964, "IYYIIIIYXIIIIIII": 0.0014494814724924964, "IXXIIIIYXIIIIIII": -0.0014494814724924964, "IXYIIIIXXIIIIIII": 0.0014494814724924964, "IYYIIIIXYIIIIIII": 0.0014494814724924964, "IXXIIIIXYIIIIIII": -0.0014494814724924964, "YZZYIIYZZXIIIIII": 0.0014494814724924964, "YZZYIIXZZYIIIIII": 0.0014494814724924964, "XZZXIIXZZYIIIIII": -0.0014494814724924964, "XZZXIIYZZXIIIIII": -0.0014494814724924964, "XZZYIIXZZXIIIIII": 0.0014494814724924964, "XZZYIIYZZYIIIIII": -0.0014494814724924964, "YZZXIIYZZYIIIIII": -0.0014494814724924964, "YZZXIIXZZXIIIIII": 0.0014494814724924964, "YZZYIIIIIIIIIXYI": -0.0013148638667153704, "XZZXIIIIIIIIIXYI": 0.0013148638667153704, "XZZYIIIIIIIIIXXI": -0.0013148638667153704, "YZZXIIIIIIIIIXXI": -0.0013148638667153704, "IYYIIIIIIIIIYZZX": -0.0013148638667153704, "IXXIIIIIIIIIYZZX": 0.0013148638667153704, "IXYIIIIIIIIIYZZY": 0.0013148638667153704, "IYXIIIIIIIIIXZZX": -0.0013148638667153704, "IXYIIIIIIIIIXZZX": -0.0013148638667153704, "IXXIIIIIIIIIXZZY": 0.0013148638667153704, "IYYIIIIIIIIIXZZY": -0.0013148638667153704, "XZZYIIIIIIIIIYYI": 0.0013148638667153704, "IYXIIIIIIIIIYZZY": 0.0013148638667153704, "YZZXIIIIIIIIIYYI": 0.0013148638667153704, "XZZXIIIIIIIIIYXI": 0.0013148638667153704, "YZZYIIIIIIIIIYXI": -0.0013148638667153704, "IXZZZZZZZZZZZYII": -0.0012873612773762228, "IYZZZZZZZZZZZXII": 0.0012873612773762228, "XZZZZZZZZZZZYIII": -0.0012873612773762228, "YZZZZZZZZZZZXIII": 0.0012873612773762228, "XZZYIIIIIIYZZYII": 0.001280068179517161, "IYXIIIIIIIIYYIII": 0.001280068179517161, "IXYIIIIIIIIYYIII": 0.001280068179517161, "YZZXIIIIIIXZZXII": -0.001280068179517161, "IYYIIIIIIIIYXIII": -0.001280068179517161, "IXXIIIIIIIIYXIII": 0.001280068179517161, "YZZYIIIIIIYZZXII": -0.001280068179517161, "XZZXIIIIIIYZZXII": 0.001280068179517161, "IYXIIIIIIIIXXIII": -0.001280068179517161, "YZZXIIIIIIYZZYII": 0.001280068179517161, "XZZYIIIIIIXZZXII": -0.001280068179517161, "IXYIIIIIIIIXXIII": -0.001280068179517161, "IXXIIIIIIIIXYIII": 0.001280068179517161, "YZZYIIIIIIXZZYII": -0.001280068179517161, "XZZXIIIIIIXZZYII": 0.001280068179517161, "IYYIIIIIIIIXYIII": -0.001280068179517161, "YZZYIXYIIIIIIIII": -0.0012366839395087164, "IXYIYZZYIIIIIIII": 0.0012366839395087164, "XZZYIYYIIIIIIIII": 0.0012366839395087164, "XZZYIXXIIIIIIIII": -0.0012366839395087164, "IYXIYZZYIIIIIIII": 0.0012366839395087164, "XZZXIXYIIIIIIIII": 0.0012366839395087164, "YZZXIXXIIIIIIIII": -0.0012366839395087164, "IXXIYZZXIIIIIIII": 0.0012366839395087164, "IYYIYZZXIIIIIIII": -0.0012366839395087164, "IYYIXZZYIIIIIIII": -0.0012366839395087164, "IXXIXZZYIIIIIIII": 0.0012366839395087164, "XZZXIYXIIIIIIIII": 0.0012366839395087164, "YZZYIYXIIIIIIIII": -0.0012366839395087164, "YZZXIYYIIIIIIIII": 0.0012366839395087164, "IXYIXZZXIIIIIIII": -0.0012366839395087164, "IYXIXZZXIIIIIIII": -0.0012366839395087164, "IIXYIIXZZZZZZZZX": 0.0011942303529983399, "IIXXIIXZZZZZZZZY": -0.0011942303529983399, "IIYYIIXZZZZZZZZY": 0.0011942303529983399, "IIXXIIIYZZZZZZXI": 0.0011942303529983399, "IIYXIIIYZZZZZZYI": 0.0011942303529983399, "IIYYIIIYZZZZZZXI": -0.0011942303529983399, "IIYXIIXZZZZZZZZX": 0.0011942303529983399, "IIYXIIYZZZZZZZZY": -0.0011942303529983399, "IIYYIIYZZZZZZZZX": 0.0011942303529983399, "IIXXIIYZZZZZZZZX": -0.0011942303529983399, "IIXYIIIXZZZZZZXI": -0.0011942303529983399, "IIXYIIIYZZZZZZYI": 0.0011942303529983399, "IIXXIIIXZZZZZZYI": 0.0011942303529983399, "IIYYIIIXZZZZZZYI": -0.0011942303529983399, "IIXYIIYZZZZZZZZY": -0.0011942303529983399, "IIYXIIIXZZZZZZXI": -0.0011942303529983399, "IXZXIIIXZZZZZYII": -0.0011867120331960138, "IXZYIIIXZZZZZXII": 0.0011867120331960138, "IYZXIIIXZZZZZXII": 0.0011867120331960138, "IXZYIIIYZZZZZYII": -0.0011867120331960138, "IYZXIIIYZZZZZYII": -0.0011867120331960138, "IYZYIIIYZZZZZXII": 0.0011867120331960138, "IXZXIIIYZZZZZXII": -0.0011867120331960138, "IYZYIIIXZZZZZYII": 0.0011867120331960138, "YZYIIIXZZZZZYIII": 0.0011867120331960138, "YZXIIIYZZZZZYIII": -0.0011867120331960138, "XZYIIIYZZZZZYIII": -0.0011867120331960138, "YZXIIIXZZZZZXIII": 0.0011867120331960138, "XZYIIIXZZZZZXIII": 0.0011867120331960138, "XZXIIIXZZZZZYIII": -0.0011867120331960138, "XZXIIIYZZZZZXIII": -0.0011867120331960138, "YZYIIIYZZZZZXIII": 0.0011867120331960138, "YYIIIIIIIIYXIIII": -0.0011518846242984317, "XXIIIIIIIIYXIIII": 0.0011518846242984317, "XYIIIIIIIIXXIIII": -0.0011518846242984317, "XXIIIIIIIIXYIIII": 0.0011518846242984317, "YYIIIIIIIIXYIIII": -0.0011518846242984317, "YXIIIIIIIIYYIIII": 0.0011518846242984317, "XYIIIIIIIIYYIIII": 0.0011518846242984317, "YXIIIIIIIIXXIIII": -0.0011518846242984317, "YZZYIIIYZZZZXIII": 0.001094107469176113, "XZZXIIIXZZZZYIII": -0.001094107469176113, "YZZYIIIXZZZZYIII": 0.001094107469176113, "YZZXIIIXZZZZXIII": 0.001094107469176113, "XZZYIIIXZZZZXIII": 0.001094107469176113, "YZZXIIIYZZZZYIII": -0.001094107469176113, "XZZYIIIYZZZZYIII": -0.001094107469176113, "IYYIIIXZZZZZZYII": 0.001094107469176113, "XZZXIIIYZZZZXIII": -0.001094107469176113, "IYXIIIYZZZZZZYII": -0.001094107469176113, "IYYIIIYZZZZZZXII": 0.001094107469176113, "IXXIIIYZZZZZZXII": -0.001094107469176113, "IYXIIIXZZZZZZXII": 0.001094107469176113, "IXYIIIYZZZZZZYII": -0.001094107469176113, "IXXIIIXZZZZZZYII": -0.001094107469176113, "IXYIIIXZZZZZZXII": 0.001094107469176113, "YYIIIYZZXIIIIIII": 0.0010896394203308067, "XXIIYZZZZXIIIIII": 0.0010896394203308067, "YYIIXZZZZYIIIIII": -0.0010896394203308067, "XXIIXZZZZYIIIIII": 0.0010896394203308067, "XXIIIYZZXIIIIIII": -0.0010896394203308067, "XYIIYZZZZYIIIIII": 0.0010896394203308067, "YXIIXZZZZXIIIIII": -0.0010896394203308067, "XYIIXZZZZXIIIIII": -0.0010896394203308067, "YXIIYZZZZYIIIIII": 0.0010896394203308067, "YXIIIYZZYIIIIIII": -0.0010896394203308067, "XYIIIYZZYIIIIIII": -0.0010896394203308067, "YXIIIXZZXIIIIIII": 0.0010896394203308067, "YYIIYZZZZXIIIIII": -0.0010896394203308067, "YYIIIXZZYIIIIIII": 0.0010896394203308067, "XXIIIXZZYIIIIIII": -0.0010896394203308067, "XYIIIXZZXIIIIIII": 0.0010896394203308067, "YZZXIIIIIIIXXIII": 0.0010227025972055547, "XZZXIIIIIIIYXIII": -0.0010227025972055547, "XZZXIIIIIIIXYIII": -0.0010227025972055547, "XZZYIIIIIIIXXIII": 0.0010227025972055547, "YZZXIIIIIIIYYIII": -0.0010227025972055547, "XZZYIIIIIIIYYIII": -0.0010227025972055547, "YZZYIIIIIIIXYIII": 0.0010227025972055547, "YZZYIIIIIIIYXIII": 0.0010227025972055547, "IXYIIIIIIIYZZYII": -0.0010227025972055547, "IYXIIIIIIIYZZYII": -0.0010227025972055547, "IYXIIIIIIIXZZXII": 0.0010227025972055547, "IXYIIIIIIIXZZXII": 0.0010227025972055547, "IXXIIIIIIIXZZYII": -0.0010227025972055547, "IYYIIIIIIIXZZYII": 0.0010227025972055547, "IYYIIIIIIIYZZXII": 0.0010227025972055547, "IXXIIIIIIIYZZXII": -0.0010227025972055547, "YZYIIIIIIIIIYZXI": 0.0008240307976304776, "YZXIIIIIIIIIYZYI": -0.0008240307976304776, "YZYIIIIIIIIIXZYI": 0.0008240307976304776, "XZXIIIIIIIIIXZYI": -0.0008240307976304776, "XZYIIIIIIIIIXZXI": 0.0008240307976304776, "XZXIIIIIIIIIYZXI": -0.0008240307976304776, "IXZXIIIIIIIIIXZY": -0.0008240307976304776, "XZYIIIIIIIIIYZYI": -0.0008240307976304776, "IXZXIIIIIIIIIYZX": -0.0008240307976304776, "IYZYIIIIIIIIIYZX": 0.0008240307976304776, "IYZXIIIIIIIIIYZY": -0.0008240307976304776, "IXZYIIIIIIIIIYZY": -0.0008240307976304776, "IYZXIIIIIIIIIXZX": 0.0008240307976304776, "IXZYIIIIIIIIIXZX": 0.0008240307976304776, "IYZYIIIIIIIIIXZY": 0.0008240307976304776, "YZXIIIIIIIIIXZXI": 0.0008240307976304776, "IIXYIIXZZZZXIIII": 0.00076069471860502, "IIYXIIXZZZZXIIII": 0.00076069471860502, "IIXYIIYZZZZYIIII": -0.00076069471860502, "IIYXIIYZZZZYIIII": -0.00076069471860502, "IIYYIIYZZZZXIIII": 0.00076069471860502, "IIXXIIYZZZZXIIII": -0.00076069471860502, "IIXYIIIYZZYIIIII": 0.00076069471860502, "IIYXIIIXZZXIIIII": -0.00076069471860502, "IIXYIIIXZZXIIIII": -0.00076069471860502, "IIXXIIIYZZXIIIII": 0.00076069471860502, "IIYYIIIXZZYIIIII": -0.00076069471860502, "IIXXIIIXZZYIIIII": 0.00076069471860502, "IIXXIIXZZZZYIIII": -0.00076069471860502, "IIYYIIIYZZXIIIII": -0.00076069471860502, "IIYYIIXZZZZYIIII": 0.00076069471860502, "IIYXIIIYZZYIIIII": 0.00076069471860502, "YXIIIIIIXZZZZXII": 0.00069268568685722, "XYIIIIIIYZZZZYII": -0.00069268568685722, "YXIIIIIIYZZZZYII": -0.00069268568685722, "YYIIIIIIYZZZZXII": 0.00069268568685722, "XXIIIIIIYZZZZXII": -0.00069268568685722, "XYIIIIIIIYZZYIII": 0.00069268568685722, "XYIIIIIIXZZZZXII": 0.00069268568685722, "XXIIIIIIXZZZZYII": -0.00069268568685722, "XXIIIIIIIXZZYIII": 0.00069268568685722, "YXIIIIIIIXZZXIII": -0.00069268568685722, "XYIIIIIIIXZZXIII": -0.00069268568685722, "YYIIIIIIXZZZZYII": 0.00069268568685722, "YYIIIIIIIXZZYIII": -0.00069268568685722, "YXIIIIIIIYZZYIII": 0.00069268568685722, "YYIIIIIIIYZZXIII": -0.00069268568685722, "XXIIIIIIIYZZXIII": 0.00069268568685722, "IIXXIIIIIIIXZZYI": 0.0006597680656952186, "IIYXIIIIIIIYZZYI": 0.0006597680656952186, "IIYYIIIIIIIXZZYI": -0.0006597680656952186, "IIXYIIIIIIIXZZXI": -0.0006597680656952186, "IIXYIIIIIIXZZZZX": 0.0006597680656952186, "IIYXIIIIIIXZZZZX": 0.0006597680656952186, "IIXYIIIIIIYZZZZY": -0.0006597680656952186, "IIYXIIIIIIYZZZZY": -0.0006597680656952186, "IIYYIIIIIIYZZZZX": 0.0006597680656952186, "IIXXIIIIIIYZZZZX": -0.0006597680656952186, "IIXXIIIIIIXZZZZY": -0.0006597680656952186, "IIYXIIIIIIIXZZXI": -0.0006597680656952186, "IIXYIIIIIIIYZZYI": 0.0006597680656952186, "IIYYIIIIIIIYZZXI": -0.0006597680656952186, "IIXXIIIIIIIYZZXI": 0.0006597680656952186, "IIYYIIIIIIXZZZZY": 0.0006597680656952186, "XZZYIIIIIYZZZZYI": -0.0005831930769675972, "YZZXIIIIIXZZZZXI": 0.0005831930769675972, "YZZYIIIIIXZZZZYI": 0.0005831930769675972, "IXXIIIIIYZZZZZZX": -0.0005831930769675972, "YZZYIIIIIYZZZZXI": 0.0005831930769675972, "XZZXIIIIIYZZZZXI": -0.0005831930769675972, "YZZXIIIIIYZZZZYI": -0.0005831930769675972, "XZZXIIIIIXZZZZYI": -0.0005831930769675972, "IYYIIIIIYZZZZZZX": 0.0005831930769675972, "IYXIIIIIYZZZZZZY": -0.0005831930769675972, "IXYIIIIIYZZZZZZY": -0.0005831930769675972, "IYXIIIIIXZZZZZZX": 0.0005831930769675972, "IXXIIIIIXZZZZZZY": -0.0005831930769675972, "IYYIIIIIXZZZZZZY": 0.0005831930769675972, "XZZYIIIIIXZZZZXI": 0.0005831930769675972, "IXYIIIIIXZZZZZZX": 0.0005831930769675972, "IXYIIIIIIYZZZZYI": 0.0005135266257220596, "IYXIIIIIIXZZZZXI": -0.0005135266257220596, "YZZXIIIIXZZZZZZX": -0.0005135266257220596, "YZZXIIIIYZZZZZZY": 0.0005135266257220596, "YZZYIIIIYZZZZZZX": -0.0005135266257220596, "IXYIIIIIIXZZZZXI": -0.0005135266257220596, "IXXIIIIIIXZZZZYI": 0.0005135266257220596, "IYYIIIIIIXZZZZYI": -0.0005135266257220596, "XZZYIIIIYZZZZZZY": 0.0005135266257220596, "XZZXIIIIYZZZZZZX": 0.0005135266257220596, "IYXIIIIIIYZZZZYI": 0.0005135266257220596, "XZZYIIIIXZZZZZZX": -0.0005135266257220596, "XZZXIIIIXZZZZZZY": 0.0005135266257220596, "YZZYIIIIXZZZZZZY": -0.0005135266257220596, "IXXIIIIIIYZZZZXI": 0.0005135266257220596, "IYYIIIIIIYZZZZXI": -0.0005135266257220596, "YYIIIIIYZZXIIIII": -0.0004974152254627477, "YXIIIIIXZZXIIIII": -0.0004974152254627477, "YXIIIIIYZZYIIIII": 0.0004974152254627477, "XXIIIIIYZZXIIIII": 0.0004974152254627477, "YYIIIIXZZZZYIIII": 0.0004974152254627477, "XYIIIIXZZZZXIIII": 0.0004974152254627477, "YXIIIIXZZZZXIIII": 0.0004974152254627477, "XYIIIIYZZZZYIIII": -0.0004974152254627477, "YXIIIIYZZZZYIIII": -0.0004974152254627477, "YYIIIIYZZZZXIIII": 0.0004974152254627477, "XXIIIIYZZZZXIIII": -0.0004974152254627477, "XXIIIIXZZZZYIIII": -0.0004974152254627477, "XYIIIIIXZZXIIIII": -0.0004974152254627477, "XYIIIIIYZZYIIIII": 0.0004974152254627477, "XXIIIIIXZZYIIIII": 0.0004974152254627477, "YYIIIIIXZZYIIIII": -0.0004974152254627477, "IYZXIIIIIXZXIIII": -0.000358645902015699, "YZXIIIIIYZYIIIII": 0.000358645902015699, "XZXIIIIIYZXIIIII": 0.000358645902015699, "IYZXIIIIIYZYIIII": 0.000358645902015699, "IYZYIIIIIYZXIIII": -0.000358645902015699, "IXZXIIIIIYZXIIII": 0.000358645902015699, "YZYIIIIIYZXIIIII": -0.000358645902015699, "IXZYIIIIIXZXIIII": -0.000358645902015699, "IXZYIIIIIYZYIIII": 0.000358645902015699, "IXZXIIIIIXZYIIII": 0.000358645902015699, "XZXIIIIIXZYIIIII": 0.000358645902015699, "YZYIIIIIXZYIIIII": -0.000358645902015699, "XZYIIIIIXZXIIIII": -0.000358645902015699, "YZXIIIIIXZXIIIII": -0.000358645902015699, "XZYIIIIIYZYIIIII": 0.000358645902015699, "IYZYIIIIIXZYIIII": -0.000358645902015699, "XZYIIIIIIIYZYIII": 0.00025736558231160634, "YZYIIIIIIIYZXIII": -0.00025736558231160634, "YZXIIIIIIIXZXIII": -0.00025736558231160634, "YZYIIIIIIIXZYIII": -0.00025736558231160634, "XZYIIIIIIIXZXIII": -0.00025736558231160634, "XZXIIIIIIIXZYIII": 0.00025736558231160634, "YZXIIIIIIIYZYIII": 0.00025736558231160634, "XZXIIIIIIIYZXIII": 0.00025736558231160634, "IXZXIIIIIIIYZXII": 0.00025736558231160634, "IYZYIIIIIIIXZYII": -0.00025736558231160634, "IXZXIIIIIIIXZYII": 0.00025736558231160634, "IXZYIIIIIIIXZXII": -0.00025736558231160634, "IXZYIIIIIIIYZYII": 0.00025736558231160634, "IYZXIIIIIIIYZYII": 0.00025736558231160634, "IYZYIIIIIIIYZXII": -0.00025736558231160634, "IYZXIIIIIIIXZXII": -0.00025736558231160634, "XZXIYZZZZZXIIIII": 0.0002515728144084927, "YZYIYZZZZZXIIIII": -0.0002515728144084927, "YZXIYZZZZZYIIIII": 0.0002515728144084927, "IXZYIYZZZZZYIIII": 0.0002515728144084927, "IYZXIYZZZZZYIIII": 0.0002515728144084927, "IYZYIYZZZZZXIIII": -0.0002515728144084927, "IXZXIYZZZZZXIIII": 0.0002515728144084927, "IYZYIXZZZZZYIIII": -0.0002515728144084927, "YZYIXZZZZZYIIIII": -0.0002515728144084927, "XZXIXZZZZZYIIIII": 0.0002515728144084927, "IXZXIXZZZZZYIIII": 0.0002515728144084927, "XZYIXZZZZZXIIIII": -0.0002515728144084927, "IYZXIXZZZZZXIIII": -0.0002515728144084927, "IXZYIXZZZZZXIIII": -0.0002515728144084927, "YZXIXZZZZZXIIIII": -0.0002515728144084927, "XZYIYZZZZZYIIIII": 0.0002515728144084927, "IIIXZZZZZZZZZZZY": -0.00021039604992930023, "IIIYZZZZZZZZZZZX": 0.00021039604992930023, "IIXZZZZZZZZZZZYI": -0.00021039604992930023, "IIYZZZZZZZZZZZXI": 0.00021039604992930023, "XXIIIIIIIIYZZZZX": 9.714586796850151e-05, "XYIIIIIIIIXZZZZX": -9.714586796850151e-05, "XXIIIIIIIIXZZZZY": 9.714586796850151e-05, "YYIIIIIIIIXZZZZY": -9.714586796850151e-05, "XYIIIIIIIIIYZZYI": -9.714586796850151e-05, "XXIIIIIIIIIYZZXI": -9.714586796850151e-05, "YYIIIIIIIIIYZZXI": 9.714586796850151e-05, "YXIIIIIIIIIYZZYI": -9.714586796850151e-05, "YXIIIIIIIIIXZZXI": 9.714586796850151e-05, "YYIIIIIIIIYZZZZX": -9.714586796850151e-05, "YXIIIIIIIIYZZZZY": 9.714586796850151e-05, "YXIIIIIIIIXZZZZX": -9.714586796850151e-05, "XYIIIIIIIIYZZZZY": 9.714586796850151e-05, "XYIIIIIIIIIXZZXI": 9.714586796850151e-05, "XXIIIIIIIIIXZZYI": -9.714586796850151e-05, "YYIIIIIIIIIXZZYI": 9.714586796850151e-05, "IYYIIIIXZZZZYIII": 9.260456401990062e-05, "IXXIIIIXZZZZYIII": -9.260456401990062e-05, "IYXIIIIXZZZZXIII": 9.260456401990062e-05, "IXYIIIIYZZZZYIII": -9.260456401990062e-05, "IXXIIIIYZZZZXIII": -9.260456401990062e-05, "IYYIIIIYZZZZXIII": 9.260456401990062e-05, "IYXIIIIYZZZZYIII": -9.260456401990062e-05, "IXYIIIIXZZZZXIII": 9.260456401990062e-05, "XZZXIIYZZZZZZXII": -9.260456401990062e-05, "YZZYIIYZZZZZZXII": 9.260456401990062e-05, "YZZXIIYZZZZZZYII": -9.260456401990062e-05, "YZZXIIXZZZZZZXII": 9.260456401990062e-05, "YZZYIIXZZZZZZYII": 9.260456401990062e-05, "XZZXIIXZZZZZZYII": -9.260456401990062e-05, "XZZYIIXZZZZZZXII": 9.260456401990062e-05, "XZZYIIYZZZZZZYII": -9.260456401990062e-05, "XZYIIIIIXZZZZZXI": 6.966645124553759e-05, "YZXIIIIIXZZZZZXI": 6.966645124553759e-05, "YZYIIIIIYZZZZZXI": 6.966645124553759e-05, "XZXIIIIIYZZZZZXI": -6.966645124553759e-05, "XZXIIIIIXZZZZZYI": -6.966645124553759e-05, "YZXIIIIIYZZZZZYI": -6.966645124553759e-05, "YZYIIIIIXZZZZZYI": 6.966645124553759e-05, "XZYIIIIIYZZZZZYI": -6.966645124553759e-05, "IXZXIIIIIXZZZZZY": -6.966645124553759e-05, "IXZYIIIIIXZZZZZX": 6.966645124553759e-05, "IYZXIIIIIXZZZZZX": 6.966645124553759e-05, "IXZYIIIIIYZZZZZY": -6.966645124553759e-05, "IYZYIIIIIXZZZZZY": 6.966645124553759e-05, "IYZXIIIIIYZZZZZY": -6.966645124553759e-05, "IYZYIIIIIYZZZZZX": 6.966645124553759e-05, "IXZXIIIIIYZZZZZX": -6.966645124553759e-05, "XZXIIIYZXIIIIIII": 4.594294170498069e-05, "YZYIIIYZXIIIIIII": -4.594294170498069e-05, "YZXIIIYZYIIIIIII": 4.594294170498069e-05, "YZYIIIXZYIIIIIII": -4.594294170498069e-05, "YZXIIIXZXIIIIIII": -4.594294170498069e-05, "XZXIIIXZYIIIIIII": 4.594294170498069e-05, "IXZXIIIYZXIIIIII": 4.594294170498069e-05, "IYZYIIIYZXIIIIII": -4.594294170498069e-05, "IYZXIIIYZYIIIIII": 4.594294170498069e-05, "IYZYIIIXZYIIIIII": -4.594294170498069e-05, "XZYIIIYZYIIIIIII": 4.594294170498069e-05, "IXZYIIIYZYIIIIII": 4.594294170498069e-05, "IXZYIIIXZXIIIIII": -4.594294170498069e-05, "IXZXIIIXZYIIIIII": 4.594294170498069e-05, "XZYIIIXZXIIIIIII": -4.594294170498069e-05, "IYZXIIIXZXIIIIII": -4.594294170498069e-05}}, "hf_method_fallback": "standard", "generation_time_s": 9.574, "timestamp": "2026-03-10T21:18:22.205599+00:00", "formula_latex": "$\\mathrm{H_{4}}$"}}