{"n_qubits": 16, "qubits": [1, 2, 3, 4, 5, 6, 7, 8, 9, 10, 11, 12, 13, 14, 15, 16], "fci_energy": -111.03228414270143, "hf_energy": -110.93711271020632, "CS_SRE": [0.05688376369944239, 0.113500677565116, 0.13767361021093666, 0.15927484934015795, 0.194510356969234, 0.1980591550894798, 0.2027209702239924, 0.20889290978537087, 0.21475481008401442, 0.22137596914337715, 0.230279475664321, 0.25919051403101967, 0.2591171629988933, 0.25900866581839294, 0.25900089849520663, 0.2589611726302391], "CS_energy": [-110.95297375206079, -110.96880912142467, -110.97356818360795, -110.97822503008575, -110.9982874054743, -111.00013226620368, -111.00529751153805, -111.01197520693792, -111.01626107880763, -111.02332189053101, -111.02831497860677, -111.03193428986711, -111.03202432005581, -111.03215826327111, -111.03219916176994, -111.03228414270569], "overlaps": [0.9898253621503988, 0.9798019740169145, 0.9756535029623215, 0.9719757341245199, 0.9662639665755681, 0.9656844043465351, 0.9649220000989205, 0.9639043063286943, 0.9629316558995268, 0.9618706659394547, 0.9604193416495024, 0.9555358599673971, 0.9555484616855299, 0.9555670262107377, 0.9555683533147559, 0.9555753054491799], "solver": "scipy", "data": {"molecule_id": "CO_singlet_Coov", "qubit_encoding": "JW", "unit": "Angstrom", "basis": "sto-3g", "charge": 0, "multiplicity": 1, "spin": 0, "geometry": "C 0.0000000000 0.0000000000 0.1128200000\nO 0.0000000000 0.0000000000 1.0153800000", "n_qubits": 20, "n_particles": {"total": 14, "alpha": 7, "beta": 7}, "hf_array": [1, 1, 1, 1, 1, 1, 1, 1, 1, 1, 1, 1, 1, 1, 0, 0, 0, 0, 0, 0], "hf_method": "pyscf.scf.hf_symm.SymAdaptedRHF", "convergence_threshold": 1e-06, "point_group": {"groupname": "Coov", "topgroup": "Coov"}, "alpha": 0.8, "calculated_properties": {"HF": {"energy": -110.93711271020632, "converged": true}, "MP2": {"energy": -111.02126950408159, "converged": null}, "CISD": {"energy": -111.02732634349869, "converged": true}, "CCSD": {"energy": -111.02947220218068, "converged": true, "t1_diagnostic": 0.007541006832597366}, "FCI": {"energy": -111.03228414270143, "converged": true, "spin_matches_target": true, "multiplicity": 1.000000000003558, "oscillatory_converged": false, "oscillation_energy_change": null}}, "auxiliary_operators": {"number_operator": {"IIIIIIIIIIIIIIIIIIII": 10.0, "IIIIIIIIIIIIIIIIIZII": -0.5, "IIIIIIIIIIIIIIIIZIII": -0.5, "IIIIIIIIIIIIIIIZIIII": -0.5, "IIIIIIIIIIIIIIZIIIII": -0.5, "IIIIIIIIIIIIIZIIIIII": -0.5, "IIIIIIIIIIIIZIIIIIII": -0.5, "IIIIIIIIIIIZIIIIIIII": -0.5, "IIIIIIIIIIZIIIIIIIII": -0.5, "IIIIIIIIIIIIIIIIIIZI": -0.5, "IIIIIIIIIZIIIIIIIIII": -0.5, "IIIIIIIZIIIIIIIIIIII": -0.5, "IIIIIIZIIIIIIIIIIIII": -0.5, "IIIIIZIIIIIIIIIIIIII": -0.5, "IIIIZIIIIIIIIIIIIIII": -0.5, "IIIZIIIIIIIIIIIIIIII": -0.5, "IIZIIIIIIIIIIIIIIIII": -0.5, "IZIIIIIIIIIIIIIIIIII": -0.5, "ZIIIIIIIIIIIIIIIIIII": -0.5, "IIIIIIIIZIIIIIIIIIII": -0.5, "IIIIIIIIIIIIIIIIIIIZ": -0.5}, "N_alpha": {"IIIIIIIIIIIIIIIIIIII": 5.0, "ZIIIIIIIIIIIIIIIIIII": -0.5, "IIZIIIIIIIIIIIIIIIII": -0.5, "IIIIZIIIIIIIIIIIIIII": -0.5, "IIIIIIZIIIIIIIIIIIII": -0.5, "IIIIIIIIZIIIIIIIIIII": -0.5, "IIIIIIIIIIZIIIIIIIII": -0.5, "IIIIIIIIIIIIZIIIIIII": -0.5, "IIIIIIIIIIIIIIZIIIII": -0.5, "IIIIIIIIIIIIIIIIZIII": -0.5, "IIIIIIIIIIIIIIIIIIZI": -0.5}, "N_beta": {"IIIIIIIIIIIIIIIIIIII": 5.0, "IZIIIIIIIIIIIIIIIIII": -0.5, "IIIZIIIIIIIIIIIIIIII": -0.5, "IIIIIZIIIIIIIIIIIIII": -0.5, "IIIIIIIZIIIIIIIIIIII": -0.5, "IIIIIIIIIZIIIIIIIIII": -0.5, "IIIIIIIIIIIZIIIIIIII": -0.5, "IIIIIIIIIIIIIZIIIIII": -0.5, "IIIIIIIIIIIIIIIZIIII": -0.5, "IIIIIIIIIIIIIIIIIZII": -0.5, "IIIIIIIIIIIIIIIIIIIZ": -0.5}, "S^2_operator": {"IIIIIIIIIIIIIIIIIIII": 3.75, "IIIIIIIIIIIIIIIIIIZZ": -0.375, "IIIIIIIIIIIIIIIIZZII": -0.375, "IIIIIIZZIIIIIIIIIIII": -0.375, "IIZZIIIIIIIIIIIIIIII": -0.375, "IIIIIIIIIIIIIIZZIIII": -0.375, "IIIIIIIIIIIIZZIIIIII": -0.375, "IIIIIIIIZZIIIIIIIIII": -0.375, "IIIIZZIIIIIIIIIIIIII": -0.375, "IIIIIIIIIIZZIIIIIIII": -0.375, "ZZIIIIIIIIIIIIIIIIII": -0.375, "ZIIIIIIIIZIIIIIIIIII": -0.125, "ZIIIIIIIZIIIIIIIIIII": 0.125, "ZIIIIIIZIIIIIIIIIIII": -0.125, "ZIIIIIZIIIIIIIIIIIII": 0.125, "ZIIIIZIIIIIIIIIIIIII": -0.125, "ZIIIZIIIIIIIIIIIIIII": 0.125, "ZIIZIIIIIIIIIIIIIIII": -0.125, "ZIZIIIIIIIIIIIIIIIII": 0.125, "IIIIIIIIIIIIIIIIXYXY": 0.125, "IIIIIIIIIIIIIIIIXYYX": -0.125, "IIIIIIIIIIIIIIIIYYXX": 0.125, "IIIIIIIIIIIIIIIIYYYY": 0.125, "IIIIIIIIIIIIIIIIXXXX": 0.125, "IIIIIIIIIIIIIIIIXXYY": 0.125, "IIIIIIIIIIIIIIIIYXXY": -0.125, "IIIIIIIIIIIIIIIIYXYX": 0.125, "IIIIIIIIXXIIIIIIIIYY": 0.125, "IIIIIIIIIIIIIIXYIIXY": 0.125, "IIIIIIIIIIIIIIXYIIYX": -0.125, "IIIIIIIIIIIIIIYYIIXX": 0.125, "IIIIIIIIIIIIIIYYIIYY": 0.125, "IIIIIIIIXXIIIIIIIIXX": 0.125, "IIIIIIIIIIIIIIXXIIXX": 0.125, "IIIIIIIIIIIIIIXXIIYY": 0.125, "IIIIIIIIIIIIIIYXIIXY": -0.125, "IIIIIIIIIIIIIIYXIIYX": 0.125, "IIIIIIIIIIIIIIXYXYII": 0.125, "IIIIIIIIIIIIIIXYYXII": -0.125, "ZIIIIIIIIIZIIIIIIIII": 0.125, "IIIIIIIIYYIIIIIIIIYY": 0.125, "IIIIIIIIIIYXYXIIIIII": 0.125, "ZIIIIIIIIIIIIZIIIIII": -0.125, "IIZIIIIIZIIIIIIIIIII": 0.125, "IIZIIIIZIIIIIIIIIIII": -0.125, "IIZIIIZIIIIIIIIIIIII": 0.125, "IIZIIZIIIIIIIIIIIIII": -0.125, "IIZIZIIIIIIIIIIIIIII": 0.125, "IZIIIIIIIIIIIIIIIIIZ": 0.125, "IZIIIIIIIIIIIIIIIIZI": -0.125, "IZIIIIIIIIIIIIIIIZII": 0.125, "IZIIIIIIIIIIIIIIZIII": -0.125, "IZIIIIIIIIIIIIIZIIII": 0.125, "IZIIIIIIIIIIIIZIIIII": -0.125, "IZIIIIIIIIIIIZIIIIII": 0.125, "IZIIIIIIIIIIZIIIIIII": -0.125, "IZIIIIIIIIIZIIIIIIII": 0.125, "IZIIIIIIIIZIIIIIIIII": -0.125, "IZIIIIIIIZIIIIIIIIII": 0.125, "IZIIIIIIZIIIIIIIIIII": -0.125, "IZIIIIIZIIIIIIIIIIII": 0.125, "IZIIIIZIIIIIIIIIIIII": -0.125, "IZIIIZIIIIIIIIIIIIII": 0.125, "IZIIZIIIIIIIIIIIIIII": -0.125, "IZIZIIIIIIIIIIIIIIII": 0.125, "IZZIIIIIIIIIIIIIIIII": -0.125, "ZIIIIIIIIIIIIIIIIIIZ": -0.125, "ZIIIIIIIIIIIIIIIIIZI": 0.125, "ZIIIIIIIIIIIIIIIIZII": -0.125, "ZIIIIIIIIIIIIIIIZIII": 0.125, "ZIIIIIIIIIIIIIIZIIII": -0.125, "ZIIIIIIIIIIIIIZIIIII": 0.125, "ZIIIIIIIIIIIZIIIIIII": 0.125, "ZIIIIIIIIIIZIIIIIIII": -0.125, "IIIIIIIIIIIIIIYYXXII": 0.125, "IIIIIIIIIIIIIIXXXXII": 0.125, "IIIIIIIIIIXXIIIIIIXX": 0.125, "IIIIIIIIIIXXIIIIIIYY": 0.125, "IIIIIIIIIIYXIIIIIIXY": -0.125, "IIIIIIIIIIYXIIIIIIYX": 0.125, "IIIIIIIIIIXYIIIIXYII": 0.125, "IIIIIIIIIIXYIIIIYXII": -0.125, "IIIIIIIIXYIIIIIIIIXY": 0.125, "IIIIIIIIIIYYIIIIXXII": 0.125, "IIIIIIIIIIYYIIIIYYII": 0.125, "IIIIIIIIIIXXIIIIXXII": 0.125, "IIIIIIIIIIXXIIIIYYII": 0.125, "IIIIIIIIIIYXIIIIXYII": -0.125, "IIIIIIIIIIYXIIIIYXII": 0.125, "IIIIIIIIIIYYIIIIIIYY": 0.125, "IIIIIIIIIIXYIIXYIIII": 0.125, "IIIIIIIIIIYYIIXXIIII": 0.125, "IIIIIIIIIIYYIIYYIIII": 0.125, "IIIIIIIIIIXXIIXXIIII": 0.125, "IIIIIIIIIIXXIIYYIIII": 0.125, "IIIIIIIIIIYXIIXYIIII": -0.125, "IIIIIIIIIIYXIIYXIIII": 0.125, "IIIIIIIIIIXYXYIIIIII": 0.125, "IIIIIIIIIIXYYXIIIIII": -0.125, "IIIIIIIIIIYYXXIIIIII": 0.125, "IIIIIIIIIIYYYYIIIIII": 0.125, "IIIIIIIIIIXXXXIIIIII": 0.125, "IIIIIIIIIIXXYYIIIIII": 0.125, "IIIIIIIIIIYXXYIIIIII": -0.125, "IIIIIIIIIIXYIIYXIIII": -0.125, "IIIIIIIIIIYYIIIIIIXX": 0.125, "IIIIIIIIIIXYIIIIIIYX": -0.125, "IIIIIIIIIIXYIIIIIIXY": 0.125, "IIIIIIIIIIIIIIXXYYII": 0.125, "IIZIIIIIIZIIIIIIIIII": -0.125, "IIIIIIIIIIIIIIYXYXII": 0.125, "IIIIIIIIYYIIIIIIIIXX": 0.125, "IIIIIIIIIIIIXYIIIIXY": 0.125, "IIIIIIIIIIIIXYIIIIYX": -0.125, "IIIIIIIIIIIIYYIIIIXX": 0.125, "IIIIIIIIIIIIYYIIIIYY": 0.125, "IIIIIIIIIIIIXXIIIIXX": 0.125, "IIIIIIIIIIIIXXIIIIYY": 0.125, "IIIIIIIIIIIIYXIIIIXY": -0.125, "IIIIIIIIIIIIYXIIIIYX": 0.125, "IIIIIIIIIIIIXYIIXYII": 0.125, "IIIIIIIIIIIIXYIIYXII": -0.125, "IIIIIIIIIIIIYYIIXXII": 0.125, "IIIIIIIIIIIIYYIIYYII": 0.125, "IIIIIIIIIIIIXXIIXXII": 0.125, "IIIIIIIIIIIIXXIIYYII": 0.125, "IIIIIIIIIIIIYXIIXYII": -0.125, "IIIIIIIIIIIIYXIIYXII": 0.125, "IIIIIIIIIIIIXYXYIIII": 0.125, "IIIIIIIIIIIIXYYXIIII": -0.125, "IIIIIIIIIIIIYYXXIIII": 0.125, "IIIIIIIIIIIIYYYYIIII": 0.125, "IIIIIIIIIIIIXXXXIIII": 0.125, "IIIIIIIIIIIIXXYYIIII": 0.125, "IIIIIIIIIIIIYXXYIIII": -0.125, "IIIIIIIIIIIIYXYXIIII": 0.125, "IIIIIIIIXYIIIIIIIIYX": -0.125, "IIIIIIIIIIIIIIYYYYII": 0.125, "IIIIIIIIIIIIIIYXXYII": -0.125, "IIZIIIIIIIZIIIIIIIII": 0.125, "IIZIIIIIIIIZIIIIIIII": -0.125, "IIIIIIIIIIZIIIZIIIII": 0.125, "IIIIIIIIIIZIIZIIIIII": -0.125, "IIIIIIIIIIZIZIIIIIII": 0.125, "IIIIIIIIIZIIIIIIIIIZ": 0.125, "IIIIIIIIIZIIIIIIIIZI": -0.125, "IIIIIIIIIZIIIIIIIZII": 0.125, "IIIIIIIIIZIIIIIIZIII": -0.125, "IIIIIIIIIZIIIIIZIIII": 0.125, "IIIIIIIIIZIIIIZIIIII": -0.125, "IIIIIIIIIZIIIZIIIIII": 0.125, "IIIIIIIIIZIIZIIIIIII": -0.125, "IIIIIIIIIZIZIIIIIIII": 0.125, "IIIIIIIIIZZIIIIIIIII": -0.125, "IIIIIIIIZIIIIIIIIIIZ": -0.125, "IIIIIIIIIIZIIIIZIIII": -0.125, "IIIIIIIIZIIIIIIIIIZI": 0.125, "IIIIIIIIZIIIIIIIZIII": 0.125, "IIIIIIIIZIIIIIIZIIII": -0.125, "IIIIIIIIZIIIIIZIIIII": 0.125, "IIIIIIIIZIIIIZIIIIII": -0.125, "IIIIIIIIZIIIZIIIIIII": 0.125, "IIIIIIIIZIIZIIIIIIII": -0.125, "IIIIIIIIZIZIIIIIIIII": 0.125, "IIIIIIIZIIIIIIIIIIIZ": 0.125, "IIIIIIIZIIIIIIIIIIZI": -0.125, "IIIIIIIZIIIIIIIIIZII": 0.125, "IIIIIIIZIIIIIIIIZIII": -0.125, "IIIIIIIZIIIIIIIZIIII": 0.125, "IIIIIIIZIIIIIIZIIIII": -0.125, "IIIIIIIZIIIIIZIIIIII": 0.125, "IIIIIIIIZIIIIIIIIZII": -0.125, "IIIIIIIIIIZIIIIIZIII": 0.125, "IIIIIIIIIIZIIIIIIZII": -0.125, "IIIIIIIIIIZIIIIIIIZI": 0.125, "IIIIIIIIIIIIIIIIZIIZ": -0.125, "IIIIIIIIIIIIIIIIZIZI": 0.125, "IIIIIIIIIIIIIIIZIIIZ": 0.125, "IIIIIIIIIIIIIIIZIIZI": -0.125, "IIIIIIIIIIIIIIIZIZII": 0.125, "IIIIIIIIIIIIIIIZZIII": -0.125, "IIIIIIIIIIIIIIZIIIIZ": -0.125, "IIIIIIIIIIIIIIZIIIZI": 0.125, "IIIIIIIIIIIIIIZIIZII": -0.125, "IIIIIIIIIIIIIIZIZIII": 0.125, "IIIIIIIIIIIIIZIIIIIZ": 0.125, "IIIIIIIIIIIIIZIIIIZI": -0.125, "IIIIIIIIIIIIIZIIIZII": 0.125, "IIIIIIIIIIIIIZIIZIII": -0.125, "IIIIIIIIIIIIIZIZIIII": 0.125, "IIIIIIIIIIIIIZZIIIII": -0.125, "IIIIIIIIIIIIZIIIIIIZ": -0.125, "IIIIIIIIIIZIIIIIIIIZ": -0.125, "IIIIIIIIIIIZZIIIIIII": -0.125, "IIIIIIIIIIIZIZIIIIII": 0.125, "IIIIIIIIIIIZIIZIIIII": -0.125, "IIIIIIIIIIIZIIIZIIII": 0.125, "IIIIIIIIIIIZIIIIZIII": -0.125, "IIIIIIIZIIIIZIIIIIII": -0.125, "IIIIIIIIIIIZIIIIIZII": 0.125, "IIIIIIIIIIIZIIIIIIIZ": 0.125, "IIIIIIIIIIIIZIZIIIII": 0.125, "IIIIIIIIIIIIZIIZIIII": -0.125, "IIIIIIIIIIIIZIIIZIII": 0.125, "IIIIIIIIIIIIZIIIIZII": -0.125, "IIIIIIIIIIIIZIIIIIZI": 0.125, "IIIIIIIIIIIZIIIIIIZI": -0.125, "IIIIIIIIYXIIIIIIIIXY": -0.125, "IIIIIIIZIIIZIIIIIIII": 0.125, "IIIIIIIZIZIIIIIIIIII": 0.125, "IIIIZIIIIIIZIIIIIIII": -0.125, "IIIIZIIIIIZIIIIIIIII": 0.125, "IIIIZIIIIZIIIIIIIIII": -0.125, "IIIIZIIIZIIIIIIIIIII": 0.125, "IIIIZIIZIIIIIIIIIIII": -0.125, "IIIIZIZIIIIIIIIIIIII": 0.125, "IIIZIIIIIIIIIIIIIIIZ": 0.125, "IIIZIIIIIIIIIIIIIIZI": -0.125, "IIIZIIIIIIIIIIIIIZII": 0.125, "IIIZIIIIIIIIIIIIZIII": -0.125, "IIIZIIIIIIIIIIIZIIII": 0.125, "IIIZIIIIIIIIIIZIIIII": -0.125, "IIIZIIIIIIIIIZIIIIII": 0.125, "IIIZIIIIIIIIZIIIIIII": -0.125, "IIIIZIIIIIIIZIIIIIII": 0.125, "IIIZIIIIIIIZIIIIIIII": 0.125, "IIIZIIIIIZIIIIIIIIII": 0.125, "IIIZIIIIZIIIIIIIIIII": -0.125, "IIIZIIIZIIIIIIIIIIII": 0.125, "IIIZIIZIIIIIIIIIIIII": -0.125, "IIIZIZIIIIIIIIIIIIII": 0.125, "IIIZZIIIIIIIIIIIIIII": -0.125, "IIZIIIIIIIIIIIIIIIIZ": -0.125, "IIZIIIIIIIIIIIIIIIZI": 0.125, "IIZIIIIIIIIIIIIIIZII": -0.125, "IIZIIIIIIIIIIIIIZIII": 0.125, "IIZIIIIIIIIIIIIZIIII": -0.125, "IIZIIIIIIIIIIIZIIIII": 0.125, "IIZIIIIIIIIIIZIIIIII": -0.125, "IIZIIIIIIIIIZIIIIIII": 0.125, "IIIZIIIIIIZIIIIIIIII": -0.125, "IIIIZIIIIIIIIZIIIIII": -0.125, "IIIIZIIIIIIIIIZIIIII": 0.125, "IIIIZIIIIIIIIIIZIIII": -0.125, "IIIIIIIZZIIIIIIIIIII": -0.125, "IIIIIIZIIIIIIIIIIIIZ": -0.125, "IIIIIIZIIIIIIIIIIIZI": 0.125, "IIIIIIZIIIIIIIIIIZII": -0.125, "IIIIIIZIIIIIIIIIZIII": 0.125, "IIIIIIZIIIIIIIIZIIII": -0.125, "IIIIIIZIIIIIIIZIIIII": 0.125, "IIIIIIZIIIIIIZIIIIII": -0.125, "IIIIIIZIIIIIZIIIIIII": 0.125, "IIIIIIZIIIIZIIIIIIII": -0.125, "IIIIIIZIIIZIIIIIIIII": 0.125, "IIIIIIZIIZIIIIIIIIII": -0.125, "IIIIIIZIZIIIIIIIIIII": 0.125, "IIIIIZIIIIIIIIIIIIIZ": 0.125, "IIIIIZIIIIIIIIIIIIZI": -0.125, "IIIIIZIIIIIIIIIIIZII": 0.125, "IIIIIZIIIIIIIIIIZIII": -0.125, "IIIIZIIIIIIIIIIIZIII": 0.125, "IIIIZIIIIIIIIIIIIZII": -0.125, "IIIIZIIIIIIIIIIIIIZI": 0.125, "IIIIZIIIIIIIIIIIIIIZ": -0.125, "IIIIIZZIIIIIIIIIIIII": -0.125, "IIIIIZIZIIIIIIIIIIII": 0.125, "IIIIIIIZIIZIIIIIIIII": -0.125, "IIIIIZIIZIIIIIIIIIII": -0.125, "IIIIIZIIIIZIIIIIIIII": -0.125, "IIIIIZIIIIIZIIIIIIII": 0.125, "IIIIIZIIIIIIZIIIIIII": -0.125, "IIIIIZIIIIIIIZIIIIII": 0.125, "IIIIIZIIIIIIIIZIIIII": -0.125, "IIIIIZIIIIIIIIIZIIII": 0.125, "IIIIIZIIIZIIIIIIIIII": 0.125, "IIIIIIIIYXIIIIIIIIYX": 0.125, "IIIIIIIIYYIIIIIIXXII": 0.125, "IIIIIIIIXYIIIIIIYXII": -0.125, "IIXXIIIIIIYYIIIIIIII": 0.125, "IIYXIIIIIIXYIIIIIIII": -0.125, "IIYXIIIIIIYXIIIIIIII": 0.125, "IIXYIIIIXYIIIIIIIIII": 0.125, "IIXYIIIIYXIIIIIIIIII": -0.125, "IIYYIIIIXXIIIIIIIIII": 0.125, "IIYYIIIIYYIIIIIIIIII": 0.125, "IIXXIIIIXXIIIIIIIIII": 0.125, "IIXXIIIIYYIIIIIIIIII": 0.125, "IIYXIIIIXYIIIIIIIIII": -0.125, "IIYXIIIIYXIIIIIIIIII": 0.125, "IIXYIIXYIIIIIIIIIIII": 0.125, "IIXYIIYXIIIIIIIIIIII": -0.125, "IIYYIIXXIIIIIIIIIIII": 0.125, "IIXXIIIIIIXXIIIIIIII": 0.125, "IIYYIIYYIIIIIIIIIIII": 0.125, "IIXXIIYYIIIIIIIIIIII": 0.125, "IIYXIIXYIIIIIIIIIIII": -0.125, "IIYXIIYXIIIIIIIIIIII": 0.125, "IIXYXYIIIIIIIIIIIIII": 0.125, "IIXYYXIIIIIIIIIIIIII": -0.125, "IIYYXXIIIIIIIIIIIIII": 0.125, "IIYYYYIIIIIIIIIIIIII": 0.125, "IIXXXXIIIIIIIIIIIIII": 0.125, "IIXXYYIIIIIIIIIIIIII": 0.125, "IIYXXYIIIIIIIIIIIIII": -0.125, "IIYXYXIIIIIIIIIIIIII": 0.125, "XYIIIIIIIIIIIIIIIIXY": 0.125, "XYIIIIIIIIIIIIIIIIYX": -0.125, "YYIIIIIIIIIIIIIIIIXX": 0.125, "IIXXIIXXIIIIIIIIIIII": 0.125, "YYIIIIIIIIIIIIIIIIYY": 0.125, "IIYYIIIIIIYYIIIIIIII": 0.125, "IIXYIIIIIIYXIIIIIIII": -0.125, "IIYYIIIIIIIIIIIIIIYY": 0.125, "IIXXIIIIIIIIIIIIIIXX": 0.125, "IIXXIIIIIIIIIIIIIIYY": 0.125, "IIYXIIIIIIIIIIIIIIXY": -0.125, "IIYXIIIIIIIIIIIIIIYX": 0.125, "IIXYIIIIIIIIIIIIXYII": 0.125, "IIXYIIIIIIIIIIIIYXII": -0.125, "IIYYIIIIIIIIIIIIXXII": 0.125, "IIYYIIIIIIIIIIIIYYII": 0.125, "IIXXIIIIIIIIIIIIXXII": 0.125, "IIXXIIIIIIIIIIIIYYII": 0.125, "IIYXIIIIIIIIIIIIXYII": -0.125, "IIYXIIIIIIIIIIIIYXII": 0.125, "IIXYIIIIIIIIIIXYIIII": 0.125, "IIYYIIIIIIXXIIIIIIII": 0.125, "IIXYIIIIIIIIIIYXIIII": -0.125, "IIYYIIIIIIIIIIYYIIII": 0.125, "IIXXIIIIIIIIIIXXIIII": 0.125, "IIXXIIIIIIIIIIYYIIII": 0.125, "IIYXIIIIIIIIIIXYIIII": -0.125, "IIYXIIIIIIIIIIYXIIII": 0.125, "IIXYIIIIIIIIXYIIIIII": 0.125, "IIXYIIIIIIIIYXIIIIII": -0.125, "IIYYIIIIIIIIXXIIIIII": 0.125, "IIYYIIIIIIIIYYIIIIII": 0.125, "IIXXIIIIIIIIXXIIIIII": 0.125, "IIXXIIIIIIIIYYIIIIII": 0.125, "IIYXIIIIIIIIXYIIIIII": -0.125, "IIYXIIIIIIIIYXIIIIII": 0.125, "IIXYIIIIIIXYIIIIIIII": 0.125, "IIYYIIIIIIIIIIXXIIII": 0.125, "XXIIIIIIIIIIIIIIIIXX": 0.125, "XXIIIIIIIIIIIIIIIIYY": 0.125, "YXIIIIIIIIIIIIIIIIXY": -0.125, "YYIIIIIIXXIIIIIIIIII": 0.125, "YYIIIIIIYYIIIIIIIIII": 0.125, "XXIIIIIIXXIIIIIIIIII": 0.125, "XXIIIIIIYYIIIIIIIIII": 0.125, "YXIIIIIIXYIIIIIIIIII": -0.125, "YXIIIIIIYXIIIIIIIIII": 0.125, "XYIIIIXYIIIIIIIIIIII": 0.125, "XYIIIIYXIIIIIIIIIIII": -0.125, "YYIIIIXXIIIIIIIIIIII": 0.125, "YYIIIIYYIIIIIIIIIIII": 0.125, "XXIIIIXXIIIIIIIIIIII": 0.125, "XXIIIIYYIIIIIIIIIIII": 0.125, "YXIIIIXYIIIIIIIIIIII": -0.125, "YXIIIIYXIIIIIIIIIIII": 0.125, "XYIIIIIIYXIIIIIIIIII": -0.125, "XYIIXYIIIIIIIIIIIIII": 0.125, "YYIIXXIIIIIIIIIIIIII": 0.125, "YYIIYYIIIIIIIIIIIIII": 0.125, "XXIIXXIIIIIIIIIIIIII": 0.125, "XXIIYYIIIIIIIIIIIIII": 0.125, "YXIIXYIIIIIIIIIIIIII": -0.125, "YXIIYXIIIIIIIIIIIIII": 0.125, "XYXYIIIIIIIIIIIIIIII": 0.125, "XYYXIIIIIIIIIIIIIIII": -0.125, "YYXXIIIIIIIIIIIIIIII": 0.125, "YYYYIIIIIIIIIIIIIIII": 0.125, "XXXXIIIIIIIIIIIIIIII": 0.125, "XXYYIIIIIIIIIIIIIIII": 0.125, "YXXYIIIIIIIIIIIIIIII": -0.125, "YXYXIIIIIIIIIIIIIIII": 0.125, "XYIIYXIIIIIIIIIIIIII": -0.125, "XYIIIIIIXYIIIIIIIIII": 0.125, "YXIIIIIIIIYXIIIIIIII": 0.125, "YXIIIIIIIIXYIIIIIIII": -0.125, "YXIIIIIIIIIIIIIIIIYX": 0.125, "XYIIIIIIIIIIIIIIXYII": 0.125, "XYIIIIIIIIIIIIIIYXII": -0.125, "YYIIIIIIIIIIIIIIXXII": 0.125, "YYIIIIIIIIIIIIIIYYII": 0.125, "XXIIIIIIIIIIIIIIXXII": 0.125, "XXIIIIIIIIIIIIIIYYII": 0.125, "YXIIIIIIIIIIIIIIXYII": -0.125, "YXIIIIIIIIIIIIIIYXII": 0.125, "XYIIIIIIIIIIIIXYIIII": 0.125, "XYIIIIIIIIIIIIYXIIII": -0.125, "YYIIIIIIIIIIIIXXIIII": 0.125, "YYIIIIIIIIIIIIYYIIII": 0.125, "XXIIIIIIIIIIIIXXIIII": 0.125, "XXIIIIIIIIIIIIYYIIII": 0.125, "YXIIIIIIIIIIIIXYIIII": -0.125, "YXIIIIIIIIIIIIYXIIII": 0.125, "XXIIIIIIIIYYIIIIIIII": 0.125, "XXIIIIIIIIXXIIIIIIII": 0.125, "YYIIIIIIIIYYIIIIIIII": 0.125, "YYIIIIIIIIXXIIIIIIII": 0.125, "XYIIIIIIIIYXIIIIIIII": -0.125, "XYIIIIIIIIXYIIIIIIII": 0.125, "IIYYIIIIIIIIIIIIIIXX": 0.125, "YXIIIIIIIIIIYXIIIIII": 0.125, "XXIIIIIIIIIIYYIIIIII": 0.125, "XXIIIIIIIIIIXXIIIIII": 0.125, "YYIIIIIIIIIIYYIIIIII": 0.125, "YYIIIIIIIIIIXXIIIIII": 0.125, "XYIIIIIIIIIIYXIIIIII": -0.125, "XYIIIIIIIIIIXYIIIIII": 0.125, "YXIIIIIIIIIIXYIIIIII": -0.125, "IIIIIIIIXYIIIIIIXYII": 0.125, "IIXYIIIIIIIIIIIIIIYX": -0.125, "IIIIYXYXIIIIIIIIIIII": 0.125, "IIIIIIXXIIIIIIIIIIXX": 0.125, "IIIIIIXXIIIIIIIIIIYY": 0.125, "IIIIIIYXIIIIIIIIIIXY": -0.125, "IIIIIIYXIIIIIIIIIIYX": 0.125, "IIIIIIXYIIIIIIIIXYII": 0.125, "IIIIIIXYIIIIIIIIYXII": -0.125, "IIIIIIYYIIIIIIIIXXII": 0.125, "IIIIIIYYIIIIIIIIYYII": 0.125, "IIIIIIXXIIIIIIIIXXII": 0.125, "IIIIIIXXIIIIIIIIYYII": 0.125, "IIIIIIYXIIIIIIIIXYII": -0.125, "IIIIIIYXIIIIIIIIYXII": 0.125, "IIIIIIXYIIIIIIXYIIII": 0.125, "IIIIIIXYIIIIIIYXIIII": -0.125, "IIIIIIYYIIIIIIIIIIYY": 0.125, "IIIIIIYYIIIIIIXXIIII": 0.125, "IIIIIIXXIIIIIIXXIIII": 0.125, "IIIIIIXXIIIIIIYYIIII": 0.125, "IIIIIIYXIIIIIIXYIIII": -0.125, "IIIIIIYXIIIIIIYXIIII": 0.125, "IIIIIIXYIIIIXYIIIIII": 0.125, "IIIIIIXYIIIIYXIIIIII": -0.125, "IIIIIIYYIIIIXXIIIIII": 0.125, "IIIIIIYYIIIIYYIIIIII": 0.125, "IIIIIIXXIIIIXXIIIIII": 0.125, "IIIIIIXXIIIIYYIIIIII": 0.125, "IIIIIIYXIIIIXYIIIIII": -0.125, "IIIIIIYXIIIIYXIIIIII": 0.125, "IIIIIIXYIIXYIIIIIIII": 0.125, "IIIIIIXYIIYXIIIIIIII": -0.125, "IIIIIIYYIIIIIIYYIIII": 0.125, "IIIIIIYYIIXXIIIIIIII": 0.125, "IIIIIIYYIIIIIIIIIIXX": 0.125, "IIIIIIXYIIIIIIIIIIXY": 0.125, "IIIIIIIIIIIIIIIIIZZI": -0.125, "IIIIIIIIYYIIIIIIYYII": 0.125, "IIIIIIIIXXIIIIIIXXII": 0.125, "IIIIIIIIXXIIIIIIYYII": 0.125, "IIIIIIIIYXIIIIIIXYII": -0.125, "IIIIIIIIYXIIIIIIYXII": 0.125, "IIIIIIIIXYIIIIXYIIII": 0.125, "IIIIIIIIXYIIIIYXIIII": -0.125, "IIIIIIIIYYIIIIXXIIII": 0.125, "IIIIIIIIYYIIIIYYIIII": 0.125, "IIIIIIIIXXIIIIXXIIII": 0.125, "IIIIIIIIXXIIIIYYIIII": 0.125, "IIIIIIIIYXIIIIXYIIII": -0.125, "IIIIIIIIYXIIIIYXIIII": 0.125, "IIIIIIXYIIIIIIIIIIYX": -0.125, "IIIIIIIIXYIIXYIIIIII": 0.125, "IIIIIIIIYYIIXXIIIIII": 0.125, "IIIIIIIIYYIIYYIIIIII": 0.125, "IIIIIIIIXXIIXXIIIIII": 0.125, "IIIIIIIIXXIIYYIIIIII": 0.125, "IIIIIIIIYXIIXYIIIIII": -0.125, "IIIIIIIIYXIIYXIIIIII": 0.125, "IIIIIIIIXYXYIIIIIIII": 0.125, "IIIIIIIIXYYXIIIIIIII": -0.125, "IIIIIIIIYYXXIIIIIIII": 0.125, "IIIIIIIIYYYYIIIIIIII": 0.125, "IIIIIIIIXXXXIIIIIIII": 0.125, "IIIIIIIIXXYYIIIIIIII": 0.125, "IIIIIIIIYXXYIIIIIIII": -0.125, "IIIIIIIIYXYXIIIIIIII": 0.125, "IIIIIIIIXYIIYXIIIIII": -0.125, "IIIIIIYYIIYYIIIIIIII": 0.125, "IIIIIIXXIIXXIIIIIIII": 0.125, "IIIIIIXXIIYYIIIIIIII": 0.125, "IIIIXYIIIIIIYXIIIIII": -0.125, "IIIIYYIIIIIIXXIIIIII": 0.125, "IIIIYYIIIIIIYYIIIIII": 0.125, "IIIIXXIIIIIIXXIIIIII": 0.125, "IIIIXXIIIIIIYYIIIIII": 0.125, "IIIIYXIIIIIIXYIIIIII": -0.125, "IIIIYXIIIIIIYXIIIIII": 0.125, "IIIIXYIIIIXYIIIIIIII": 0.125, "IIIIXYIIIIYXIIIIIIII": -0.125, "IIIIYYIIIIXXIIIIIIII": 0.125, "IIIIYYIIIIYYIIIIIIII": 0.125, "IIIIXXIIIIXXIIIIIIII": 0.125, "IIIIXXIIIIYYIIIIIIII": 0.125, "IIIIYXIIIIXYIIIIIIII": -0.125, "IIIIXYIIIIIIXYIIIIII": 0.125, "IIIIYXIIIIYXIIIIIIII": 0.125, "IIIIXYIIYXIIIIIIIIII": -0.125, "IIIIYYIIXXIIIIIIIIII": 0.125, "IIIIYYIIYYIIIIIIIIII": 0.125, "IIIIXXIIXXIIIIIIIIII": 0.125, "IIIIXXIIYYIIIIIIIIII": 0.125, "IIIIYXIIXYIIIIIIIIII": -0.125, "IIIIYXIIYXIIIIIIIIII": 0.125, "IIIIXYXYIIIIIIIIIIII": 0.125, "IIIIXYYXIIIIIIIIIIII": -0.125, "IIIIYYXXIIIIIIIIIIII": 0.125, "IIIIYYYYIIIIIIIIIIII": 0.125, "IIIIXXXXIIIIIIIIIIII": 0.125, "IIIIXXYYIIIIIIIIIIII": 0.125, "IIIIYXXYIIIIIIIIIIII": -0.125, "IIIIXYIIXYIIIIIIIIII": 0.125, "IIIIYXIIIIIIIIYXIIII": 0.125, "IIIIYXIIIIIIIIXYIIII": -0.125, "IIIIXXIIIIIIIIYYIIII": 0.125, "IIIIIIYXIIXYIIIIIIII": -0.125, "IIIIIIYXIIYXIIIIIIII": 0.125, "IIIIIIXYXYIIIIIIIIII": 0.125, "IIIIIIXYYXIIIIIIIIII": -0.125, "IIIIIIYYXXIIIIIIIIII": 0.125, "IIIIIIYYYYIIIIIIIIII": 0.125, "IIIIIIXXXXIIIIIIIIII": 0.125, "IIIIIIXXYYIIIIIIIIII": 0.125, "IIIIIIYXXYIIIIIIIIII": -0.125, "IIIIIIYXYXIIIIIIIIII": 0.125, "IIIIXYIIIIIIIIIIIIXY": 0.125, "IIIIXYIIIIIIIIIIIIYX": -0.125, "IIIIYYIIIIIIIIIIIIXX": 0.125, "IIIIYYIIIIIIIIIIIIYY": 0.125, "IIIIXXIIIIIIIIIIIIXX": 0.125, "IIIIXXIIIIIIIIIIIIYY": 0.125, "IIIIYXIIIIIIIIIIIIXY": -0.125, "IIIIXXIIIIIIIIXXIIII": 0.125, "IIIIYYIIIIIIIIYYIIII": 0.125, "IIIIYYIIIIIIIIXXIIII": 0.125, "IIIIXYIIIIIIIIYXIIII": -0.125, "IIIIXYIIIIIIIIXYIIII": 0.125, "IIIIYXIIIIIIIIIIYXII": 0.125, "IIXYIIIIIIIIIIIIIIXY": 0.125, "IIIIYXIIIIIIIIIIXYII": -0.125, "IIIIXXIIIIIIIIIIXXII": 0.125, "IIIIYYIIIIIIIIIIYYII": 0.125, "IIIIYYIIIIIIIIIIXXII": 0.125, "IIIIXYIIIIIIIIIIYXII": -0.125, "IIIIXYIIIIIIIIIIXYII": 0.125, "IIIIYXIIIIIIIIIIIIYX": 0.125, "IIIIXXIIIIIIIIIIYYII": 0.125, "IIIIIIIIIIIIIIIIIZIZ": 0.125}, "UCCSD_operator": {"IIIIIIIIYXIIIIXXIIII": -0.010220468786316954, "IIIIIIIIXXIIIIYXIIII": 0.010220468786316954, "IIIIIIIIYYIIIIYXIIII": -0.010220468786316954, "IIIIIIIIYXIIIIYYIIII": 0.010220468786316954, "IIIIIIIIYYIIIIXYIIII": -0.010220468786316954, "IIIIIIIIXXIIIIXYIIII": 0.010220468786316954, "IIIIIIIIXYIIIIXXIIII": -0.010220468786316954, "IIIIIIIIXYIIIIYYIIII": 0.010220468786316954, "IIIIIIIIIIXXIIIIYXII": 0.01022046878631692, "IIIIIIIIIIYYIIIIYXII": -0.01022046878631692, "IIIIIIIIIIYXIIIIYYII": 0.01022046878631692, "IIIIIIIIIIXYIIIIYYII": 0.01022046878631692, "IIIIIIIIIIXYIIIIXXII": -0.01022046878631692, "IIIIIIIIIIXXIIIIXYII": 0.01022046878631692, "IIIIIIIIIIYYIIIIXYII": -0.01022046878631692, "IIIIIIIIIIYXIIIIXXII": -0.01022046878631692, "IIIIIIIIIXZZZZZYIIII": -0.009545846227078568, "IIIIIIIIIYZZZZZXIIII": 0.009545846227078568, "IIIIIIIIYZZZZZXIIIII": 0.009545846227078568, "IIIIIIIIXZZZZZYIIIII": -0.009545846227078568, "IIIIIIIIIIIXZZZZZYII": -0.00954584622707796, "IIIIIIIIIIIYZZZZZXII": 0.00954584622707796, "IIIIIIIIIIYZZZZZXIII": 0.00954584622707796, "IIIIIIIIIIXZZZZZYIII": -0.00954584622707796, "IIIIIIIIIIIIYYIIYXII": -0.007199503749229178, "IIIIIIIIIIIIYXIIYYII": 0.007199503749229178, "IIIIIIIIIIIIXXIIYXII": 0.007199503749229178, "IIIIIIIIIIIIXXIIXYII": 0.007199503749229178, "IIIIIIIIIIIIXYIIXXII": -0.007199503749229178, "IIIIIIIIIIIIYXIIXXII": -0.007199503749229178, "IIIIIIIIIIIIXYIIYYII": 0.007199503749229178, "IIIIIIIIIIIIYYIIXYII": -0.007199503749229178, "IIIIIIIIIIIIXXYXIIII": 0.0071995037492291565, "IIIIIIIIIIIIYYYXIIII": -0.0071995037492291565, "IIIIIIIIIIIIXYYYIIII": 0.0071995037492291565, "IIIIIIIIIIIIYXYYIIII": 0.0071995037492291565, "IIIIIIIIIIIIXYXXIIII": -0.0071995037492291565, "IIIIIIIIIIIIXXXYIIII": 0.0071995037492291565, "IIIIIIIIIIIIYYXYIIII": -0.0071995037492291565, "IIIIIIIIIIIIYXXXIIII": -0.0071995037492291565, "IIIIIIIIYZZYIIYZZXII": -0.007147761298953494, "IIIIIIIIYZZXIIYZZYII": 0.007147761298953494, "IIIIIIIIXZZYIIYZZYII": 0.007147761298953494, "IIIIIIIIYZZYIIXZZYII": -0.007147761298953494, "IIIIIIIIXZZXIIXZZYII": 0.007147761298953494, "IIIIIIIIXZZYIIXZZXII": -0.007147761298953494, "IIIIIIIIYZZXIIXZZXII": -0.007147761298953494, "IIIIIIIIIXYIIIIXXIII": -0.007147761298953494, "IIIIIIIIXZZXIIYZZXII": 0.007147761298953494, "IIIIIIIIIXXIIIIXYIII": 0.007147761298953494, "IIIIIIIIIYYIIIIXYIII": -0.007147761298953494, "IIIIIIIIIYXIIIIYYIII": 0.007147761298953494, "IIIIIIIIIYYIIIIYXIII": -0.007147761298953494, "IIIIIIIIIXXIIIIYXIII": 0.007147761298953494, "IIIIIIIIIYXIIIIXXIII": -0.007147761298953494, "IIIIIIIIIXYIIIIYYIII": 0.007147761298953494, "IIIIIIIIXZYIIIXZXIII": -0.005149861537140919, "IIIIIIIIIYZYIIIXZYII": -0.005149861537140919, "IIIIIIIIXZXIIIYZXIII": 0.005149861537140919, "IIIIIIIIYZYIIIYZXIII": -0.005149861537140919, "IIIIIIIIYZXIIIYZYIII": 0.005149861537140919, "IIIIIIIIXZYIIIYZYIII": 0.005149861537140919, "IIIIIIIIIXZYIIIYZYII": 0.005149861537140919, "IIIIIIIIIYZXIIIXZXII": -0.005149861537140919, "IIIIIIIIIXZYIIIXZXII": -0.005149861537140919, "IIIIIIIIIXZXIIIXZYII": 0.005149861537140919, "IIIIIIIIYZYIIIXZYIII": -0.005149861537140919, "IIIIIIIIXZXIIIXZYIII": 0.005149861537140919, "IIIIIIIIYZXIIIXZXIII": -0.005149861537140919, "IIIIIIIIIYZXIIIYZYII": 0.005149861537140919, "IIIIIIIIIXZXIIIYZXII": 0.005149861537140919, "IIIIIIIIIYZYIIIYZXII": -0.005149861537140919, "IIIIIIIIIIIIIXZZZZZY": 0.0036239005913890716, "IIIIIIIIIIIIIYZZZZZX": -0.0036239005913890716, "IIIIIIIIIIIIYZZZZZXI": -0.0036239005913890716, "IIIIIIIIIIIIXZZZZZYI": 0.0036239005913890716, "IIIIIIXYIIIIIIXXIIII": -0.0029594324466164, "IIIIIIXXIIIIIIXYIIII": 0.0029594324466164, "IIIIIIYXIIIIIIYYIIII": 0.0029594324466164, "IIIIIIXYIIIIIIYYIIII": 0.0029594324466164, "IIIIIIXXIIIIIIYXIIII": 0.0029594324466164, "IIIIIIYXIIIIIIXXIIII": -0.0029594324466164, "IIIIIIYYIIIIIIYXIIII": -0.0029594324466164, "IIIIIIYYIIIIIIXYIIII": -0.0029594324466164, "IIIIIIYYIIIIIIIIXYII": -0.0029594324466163963, "IIIIIIYXIIIIIIIIXXII": -0.0029594324466163963, "IIIIIIXYIIIIIIIIXXII": -0.0029594324466163963, "IIIIIIXXIIIIIIIIXYII": 0.0029594324466163963, "IIIIIIXYIIIIIIIIYYII": 0.0029594324466163963, "IIIIIIYYIIIIIIIIYXII": -0.0029594324466163963, "IIIIIIYXIIIIIIIIYYII": 0.0029594324466163963, "IIIIIIXXIIIIIIIIYXII": 0.0029594324466163963, "IIIIIXZZXIIIIIYZZZZX": 0.0028471808542831073, "IIIIIYZZYIIIIIYZZZZX": -0.0028471808542831073, "IIIIIYZZXIIIIIYZZZZY": 0.0028471808542831073, "IIIIYZZZZXIIIIIYZZYI": 0.0028471808542831073, "IIIIYZZZZYIIIIIYZZXI": -0.0028471808542831073, "IIIIXZZZZXIIIIIYZZXI": 0.0028471808542831073, "IIIIXZZZZXIIIIIXZZYI": 0.0028471808542831073, "IIIIIYZZYIIIIIXZZZZY": -0.0028471808542831073, "IIIIIXZZXIIIIIXZZZZY": 0.0028471808542831073, "IIIIIXZZYIIIIIXZZZZX": -0.0028471808542831073, "IIIIYZZZZYIIIIIXZZYI": -0.0028471808542831073, "IIIIIYZZXIIIIIXZZZZX": -0.0028471808542831073, "IIIIXZZZZYIIIIIYZZYI": 0.0028471808542831073, "IIIIYZZZZXIIIIIXZZXI": -0.0028471808542831073, "IIIIXZZZZYIIIIIXZZXI": -0.0028471808542831073, "IIIIIXZZYIIIIIYZZZZY": 0.0028471808542831073, "IIIIXZZZZZZYIIIIIYYI": 0.002847180854283104, "IIIIIYZZZZYIIIIIXZZY": -0.002847180854283104, "IIIIYZZZZZZXIIIIIXXI": -0.002847180854283104, "IIIIXZZZZZZYIIIIIXXI": -0.002847180854283104, "IIIIXZZZZZZXIIIIIXYI": 0.002847180854283104, "IIIIYZZZZZZYIIIIIXYI": -0.002847180854283104, "IIIIYZZZZZZXIIIIIYYI": 0.002847180854283104, "IIIIYZZZZZZYIIIIIYXI": -0.002847180854283104, "IIIIXZZZZZZXIIIIIYXI": 0.002847180854283104, "IIIIIXZZZZXIIIIIYZZX": 0.002847180854283104, "IIIIIYZZZZYIIIIIYZZX": -0.002847180854283104, "IIIIIYZZZZXIIIIIYZZY": 0.002847180854283104, "IIIIIXZZZZYIIIIIYZZY": 0.002847180854283104, "IIIIIYZZZZXIIIIIXZZX": -0.002847180854283104, "IIIIIXZZZZXIIIIIXZZY": 0.002847180854283104, "IIIIIXZZZZYIIIIIXZZX": -0.002847180854283104, "IIIIIIIIIIIIYYIIIIXY": -0.002599565027623532, "IIIIIIIIIIIIXXIIIIYX": 0.002599565027623532, "IIIIIIIIIIIIYYIIIIYX": -0.002599565027623532, "IIIIIIIIIIIIYXIIIIYY": 0.002599565027623532, "IIIIIIIIIIIIYXIIIIXX": -0.002599565027623532, "IIIIIIIIIIIIXYIIIIXX": -0.002599565027623532, "IIIIIIIIIIIIXXIIIIXY": 0.002599565027623532, "IIIIIIIIIIIIXYIIIIYY": 0.002599565027623532, "IIIIIIIIXZZZYIXZZZXI": -0.0024980674136519526, "IIIIIIIIIXZZZXIYZZZX": 0.0024980674136519526, "IIIIIIIIXZZZXIXZZZYI": 0.0024980674136519526, "IIIIIIIIYZZZXIXZZZXI": -0.0024980674136519526, "IIIIIIIIXZZZYIYZZZYI": 0.0024980674136519526, "IIIIIIIIYZZZXIYZZZYI": 0.0024980674136519526, "IIIIIIIIYZZZYIYZZZXI": -0.0024980674136519526, "IIIIIIIIXZZZXIYZZZXI": 0.0024980674136519526, "IIIIIIIIYZZZYIXZZZYI": -0.0024980674136519526, "IIIIIIIIIXZZZYIXZZZX": -0.0024980674136519526, "IIIIIIIIIYZZZYIXZZZY": -0.0024980674136519526, "IIIIIIIIIXZZZXIXZZZY": 0.0024980674136519526, "IIIIIIIIIYZZZXIXZZZX": -0.0024980674136519526, "IIIIIIIIIYZZZXIYZZZY": 0.0024980674136519526, "IIIIIIIIIYZZZYIYZZZX": -0.0024980674136519526, "IIIIIIIIIXZZZYIYZZZY": 0.0024980674136519526, "IIIIIIIIIIYZYIIIXZYI": -0.002498067413651949, "IIIIIIIIIIIXZXIIIYZX": 0.002498067413651949, "IIIIIIIIIIXZXIIIXZYI": 0.002498067413651949, "IIIIIIIIIIIYZYIIIYZX": -0.002498067413651949, "IIIIIIIIIIXZYIIIXZXI": -0.002498067413651949, "IIIIIIIIIIYZXIIIXZXI": -0.002498067413651949, "IIIIIIIIIIIYZXIIIYZY": 0.002498067413651949, "IIIIIIIIIIIXZYIIIXZX": -0.002498067413651949, "IIIIIIIIIIIXZYIIIYZY": 0.002498067413651949, "IIIIIIIIIIIYZXIIIXZX": -0.002498067413651949, "IIIIIIIIIIXZYIIIYZYI": 0.002498067413651949, "IIIIIIIIIIIXZXIIIXZY": 0.002498067413651949, "IIIIIIIIIIIYZYIIIXZY": -0.002498067413651949, "IIIIIIIIIIXZXIIIYZXI": 0.002498067413651949, "IIIIIIIIIIYZXIIIYZYI": 0.002498067413651949, "IIIIIIIIIIYZYIIIYZXI": -0.002498067413651949, "IIIIIIYZZZZZZXIIYYII": -0.0024533821896589787, "IIIIIIIXZZZZXIIIYXII": 0.0024533821896589787, "IIIIIIIYZZZZYIIIYXII": -0.0024533821896589787, "IIIIIIIYZZZZXIIIYYII": 0.0024533821896589787, "IIIIIIIXZZZZYIIIYYII": 0.0024533821896589787, "IIIIIIIYZZZZXIIIXXII": -0.0024533821896589787, "IIIIIIIXZZZZXIIIXYII": 0.0024533821896589787, "IIIIIIIYZZZZYIIIXYII": -0.0024533821896589787, "IIIIIIXZZZZZZXIIYXII": -0.0024533821896589787, "IIIIIIIXZZZZYIIIXXII": -0.0024533821896589787, "IIIIIIYZZZZZZYIIYXII": 0.0024533821896589787, "IIIIIIYZZZZZZYIIXYII": 0.0024533821896589787, "IIIIIIXZZZZZZXIIXYII": -0.0024533821896589787, "IIIIIIXZZZZZZYIIXXII": 0.0024533821896589787, "IIIIIIYZZZZZZXIIXXII": 0.0024533821896589787, "IIIIIIXZZZZZZYIIYYII": -0.0024533821896589787, "IIIIIIXZZZZZZYXXIIII": 0.0024533821896589735, "IIIIIIXZZZZZZXXYIIII": -0.0024533821896589735, "IIIIIIYZZZZZZYXYIIII": 0.0024533821896589735, "IIIIIIIYZZZZXIYYIIII": 0.0024533821896589735, "IIIIIIXZZZZZZXYXIIII": -0.0024533821896589735, "IIIIIIYZZZZZZXXXIIII": 0.0024533821896589735, "IIIIIIXZZZZZZYYYIIII": -0.0024533821896589735, "IIIIIIIXZZZZXIYXIIII": 0.0024533821896589735, "IIIIIIYZZZZZZYYXIIII": 0.0024533821896589735, "IIIIIIYZZZZZZXYYIIII": -0.0024533821896589735, "IIIIIIIXZZZZXIXYIIII": 0.0024533821896589735, "IIIIIIIXZZZZYIXXIIII": -0.0024533821896589735, "IIIIIIIYZZZZXIXXIIII": -0.0024533821896589735, "IIIIIIIYZZZZYIYXIIII": -0.0024533821896589735, "IIIIIIIYZZZZYIXYIIII": -0.0024533821896589735, "IIIIIIIXZZZZYIYYIIII": 0.0024533821896589735, "IIIIXXIIIIIIIIIIIIYX": 0.0021928859888324303, "IIIIYYIIIIIIIIIIIIYX": -0.0021928859888324303, "IIIIYXIIIIIIIIIIIIYY": 0.0021928859888324303, "IIIIXYIIIIIIIIIIIIYY": 0.0021928859888324303, "IIIIYXIIIIIIIIIIIIXX": -0.0021928859888324303, "IIIIXXIIIIIIIIIIIIXY": 0.0021928859888324303, "IIIIYYIIIIIIIIIIIIXY": -0.0021928859888324303, "IIIIXYIIIIIIIIIIIIXX": -0.0021928859888324303, "IIIIIIIIIYYIIIXZZYII": 0.0019978997618125753, "IIIIIIIIIXXIIIXZZYII": -0.0019978997618125753, "IIIIIIIIIXYIIIXZZXII": 0.0019978997618125753, "IIIIIIIIIYXIIIXZZXII": 0.0019978997618125753, "IIIIIIIIIXYIIIYZZYII": -0.0019978997618125753, "IIIIIIIIIYXIIIYZZYII": -0.0019978997618125753, "IIIIIIIIIYYIIIYZZXII": 0.0019978997618125753, "IIIIIIIIIXXIIIYZZXII": -0.0019978997618125753, "IIIIIIIIXZZYIIIXXIII": 0.0019978997618125753, "IIIIIIIIXZZXIIIXYIII": -0.0019978997618125753, "IIIIIIIIYZZYIIIXYIII": 0.0019978997618125753, "IIIIIIIIYZZXIIIXXIII": 0.0019978997618125753, "IIIIIIIIXZZYIIIYYIII": -0.0019978997618125753, "IIIIIIIIYZZYIIIYXIII": 0.0019978997618125753, "IIIIIIIIYZZXIIIYYIII": -0.0019978997618125753, "IIIIIIIIXZZXIIIYXIII": -0.0019978997618125753, "IIIIIIIXZZZZZZZZZZZY": -0.001820020963859084, "IIIIIIYZZZZZZZZZZZXI": 0.001820020963859084, "IIIIIIIYZZZZZZZZZZZX": 0.001820020963859084, "IIIIIIXZZZZZZZZZZZYI": -0.001820020963859084, "IIIIIIIIXZZZZYYZZZZY": 0.0018104025200988587, "IIIIIIIIYZZZZXYZZZZY": 0.0018104025200988587, "IIIIIIIIYZZZZYYZZZZX": -0.0018104025200988587, "IIIIIIIIXZZZZXYZZZZX": 0.0018104025200988587, "IIIIIIIIYZZZZXXZZZZX": -0.0018104025200988587, "IIIIIIIIYZZZZYXZZZZY": -0.0018104025200988587, "IIIIIIIIXZZZZYXZZZZX": -0.0018104025200988587, "IIIIIIIIIYZZXIIYZZYI": 0.0018104025200988587, "IIIIIIIIIXZZYIIYZZYI": 0.0018104025200988587, "IIIIIIIIIXZZXIIYZZXI": 0.0018104025200988587, "IIIIIIIIIYZZXIIXZZXI": -0.0018104025200988587, "IIIIIIIIIXZZYIIXZZXI": -0.0018104025200988587, "IIIIIIIIIXZZXIIXZZYI": 0.0018104025200988587, "IIIIIIIIIYZZYIIXZZYI": -0.0018104025200988587, "IIIIIIIIXZZZZXXZZZZY": 0.0018104025200988587, "IIIIIIIIIYZZYIIYZZXI": -0.0018104025200988587, "IIIIIIIIIIIXYIIIIXXI": -0.0018104025200988564, "IIIIIIIIIIIYXIIIIXXI": -0.0018104025200988564, "IIIIIIIIIIIXYIIIIYYI": 0.0018104025200988564, "IIIIIIIIIIXZZXIIYZZX": 0.0018104025200988564, "IIIIIIIIIIYZZYIIYZZX": -0.0018104025200988564, "IIIIIIIIIIYZZXIIYZZY": 0.0018104025200988564, "IIIIIIIIIIIXXIIIIXYI": 0.0018104025200988564, "IIIIIIIIIIXZZYIIYZZY": 0.0018104025200988564, "IIIIIIIIIIXZZYIIXZZX": -0.0018104025200988564, "IIIIIIIIIIXZZXIIXZZY": 0.0018104025200988564, "IIIIIIIIIIYZZYIIXZZY": -0.0018104025200988564, "IIIIIIIIIIIXXIIIIYXI": 0.0018104025200988564, "IIIIIIIIIIIYYIIIIYXI": -0.0018104025200988564, "IIIIIIIIIIIYXIIIIYYI": 0.0018104025200988564, "IIIIIIIIIIYZZXIIXZZX": -0.0018104025200988564, "IIIIIIIIIIIYYIIIIXYI": -0.0018104025200988564, "IIIIIYZZZYIIIIIYZZZX": -0.0014446321221077186, "IIIIXZZZXIIIIIYZZZXI": 0.0014446321221077186, "IIIIYZZZYIIIIIYZZZXI": -0.0014446321221077186, "IIIIYZZZXIIIIIYZZZYI": 0.0014446321221077186, "IIIIXZZZYIIIIIYZZZYI": 0.0014446321221077186, "IIIIYZZZXIIIIIXZZZXI": -0.0014446321221077186, "IIIIXZZZYIIIIIXZZZXI": -0.0014446321221077186, "IIIIXZZZXIIIIIXZZZYI": 0.0014446321221077186, "IIIIYZZZYIIIIIXZZZYI": -0.0014446321221077186, "IIIIIXZZZXIIIIIYZZZX": 0.0014446321221077186, "IIIIIYZZZYIIIIIXZZZY": -0.0014446321221077186, "IIIIIYZZZXIIIIIYZZZY": 0.0014446321221077186, "IIIIIYZZZXIIIIIXZZZX": -0.0014446321221077186, "IIIIIXZZZYIIIIIYZZZY": 0.0014446321221077186, "IIIIIXZZZYIIIIIXZZZX": -0.0014446321221077186, "IIIIIXZZZXIIIIIXZZZY": 0.0014446321221077186, "IIIIIXZZZZZXIIIIIXZY": 0.0014446321221077162, "IIIIIYZZZZZYIIIIIXZY": -0.0014446321221077162, "IIIIIXZZZZZYIIIIIXZX": -0.0014446321221077162, "IIIIXZZZZZXIIIIIYZXI": 0.0014446321221077162, "IIIIYZZZZZYIIIIIYZXI": -0.0014446321221077162, "IIIIYZZZZZXIIIIIYZYI": 0.0014446321221077162, "IIIIXZZZZZYIIIIIYZYI": 0.0014446321221077162, "IIIIYZZZZZXIIIIIXZXI": -0.0014446321221077162, "IIIIXZZZZZYIIIIIXZXI": -0.0014446321221077162, "IIIIXZZZZZXIIIIIXZYI": 0.0014446321221077162, "IIIIYZZZZZYIIIIIXZYI": -0.0014446321221077162, "IIIIIYZZZZZXIIIIIXZX": -0.0014446321221077162, "IIIIIXZZZZZYIIIIIYZY": 0.0014446321221077162, "IIIIIYZZZZZXIIIIIYZY": 0.0014446321221077162, "IIIIIYZZZZZYIIIIIYZX": -0.0014446321221077162, "IIIIIXZZZZZXIIIIIYZX": 0.0014446321221077162, "IIIIYZZZZYIIIIXZZZZY": 0.0014025487321753887, "IIIIXZZZZYIIIIXZZZZX": 0.0014025487321753887, "IIIIXZZZZXIIIIXZZZZY": -0.0014025487321753887, "IIIIYZZZZXIIIIXZZZZX": 0.0014025487321753887, "IIIIYZZZZXIIIIYZZZZY": -0.0014025487321753887, "IIIIYZZZZYIIIIYZZZZX": 0.0014025487321753887, "IIIIXZZZZXIIIIYZZZZX": -0.0014025487321753887, "IIIIXZZZZYIIIIYZZZZY": -0.0014025487321753887, "IIIIIYZZYIIIIIIXZZYI": 0.0014025487321753887, "IIIIIXZZXIIIIIIYZZXI": -0.0014025487321753887, "IIIIIYZZYIIIIIIYZZXI": 0.0014025487321753887, "IIIIIYZZXIIIIIIYZZYI": -0.0014025487321753887, "IIIIIYZZXIIIIIIXZZXI": 0.0014025487321753887, "IIIIIXZZYIIIIIIXZZXI": 0.0014025487321753887, "IIIIIXZZXIIIIIIXZZYI": -0.0014025487321753887, "IIIIIXZZYIIIIIIYZZYI": -0.0014025487321753887, "IIIIIYZZZZXIIIIIIXXI": 0.0014025487321753876, "IIIIIXZZZZXIIIIIIXYI": -0.0014025487321753876, "IIIIIXZZZZYIIIIIIXXI": 0.0014025487321753876, "IIIIIXZZZZYIIIIIIYYI": -0.0014025487321753876, "IIIIXZZZZZZXIIIIYZZX": -0.0014025487321753876, "IIIIYZZZZZZYIIIIYZZX": 0.0014025487321753876, "IIIIYZZZZZZXIIIIYZZY": -0.0014025487321753876, "IIIIXZZZZZZYIIIIYZZY": -0.0014025487321753876, "IIIIYZZZZZZXIIIIXZZX": 0.0014025487321753876, "IIIIIYZZZZYIIIIIIXYI": 0.0014025487321753876, "IIIIXZZZZZZXIIIIXZZY": -0.0014025487321753876, "IIIIYZZZZZZYIIIIXZZY": 0.0014025487321753876, "IIIIIXZZZZXIIIIIIYXI": -0.0014025487321753876, "IIIIIYZZZZYIIIIIIYXI": 0.0014025487321753876, "IIIIIYZZZZXIIIIIIYYI": -0.0014025487321753876, "IIIIXZZZZZZYIIIIXZZX": 0.0014025487321753876, "IIIIIIIYYIIIIIXZZZZY": 0.0013997689239028267, "IIIIIIXZZYIIIIIXZZXI": 0.0013997689239028267, "IIIIIIYZZXIIIIIXZZXI": 0.0013997689239028267, "IIIIIIXZZYIIIIIYZZYI": -0.0013997689239028267, "IIIIIIYZZXIIIIIYZZYI": -0.0013997689239028267, "IIIIIIYZZYIIIIIYZZXI": 0.0013997689239028267, "IIIIIIXZZXIIIIIYZZXI": -0.0013997689239028267, "IIIIIIXZZXIIIIIXZZYI": -0.0013997689239028267, "IIIIIIYZZYIIIIIXZZYI": 0.0013997689239028267, "IIIIIIIXXIIIIIXZZZZY": -0.0013997689239028267, "IIIIIIIXYIIIIIXZZZZX": 0.0013997689239028267, "IIIIIIIXXIIIIIYZZZZX": -0.0013997689239028267, "IIIIIIIYYIIIIIYZZZZX": 0.0013997689239028267, "IIIIIIIYXIIIIIYZZZZY": -0.0013997689239028267, "IIIIIIIXYIIIIIYZZZZY": -0.0013997689239028267, "IIIIIIIYXIIIIIXZZZZX": 0.0013997689239028267, "IIIIIIIXZZYIIIIIYZZY": -0.0013997689239028256, "IIIIIIIYZZYIIIIIYZZX": 0.0013997689239028256, "IIIIIIIYZZXIIIIIYZZY": -0.0013997689239028256, "IIIIIIIXZZYIIIIIXZZX": 0.0013997689239028256, "IIIIIIIXZZXIIIIIXZZY": -0.0013997689239028256, "IIIIIIIYZZYIIIIIXZZY": 0.0013997689239028256, "IIIIIIYZZZZYIIIIIXYI": 0.0013997689239028256, "IIIIIIXZZZZXIIIIIXYI": -0.0013997689239028256, "IIIIIIIYZZXIIIIIXZZX": 0.0013997689239028256, "IIIIIIXZZZZYIIIIIXXI": 0.0013997689239028256, "IIIIIIYZZZZXIIIIIXXI": 0.0013997689239028256, "IIIIIIXZZZZYIIIIIYYI": -0.0013997689239028256, "IIIIIIIXZZXIIIIIYZZX": -0.0013997689239028256, "IIIIIIYZZZZXIIIIIYYI": -0.0013997689239028256, "IIIIIIYZZZZYIIIIIYXI": 0.0013997689239028256, "IIIIIIXZZZZXIIIIIYXI": -0.0013997689239028256, "IIIIIIIXZXIIIIIXZZZY": -0.001280826234117315, "IIIIIIIXZYIIIIIXZZZX": 0.001280826234117315, "IIIIIIIYZXIIIIIXZZZX": 0.001280826234117315, "IIIIIIIYZYIIIIIXZZZY": 0.001280826234117315, "IIIIIIIXZYIIIIIYZZZY": -0.001280826234117315, "IIIIIIIYZXIIIIIYZZZY": -0.001280826234117315, "IIIIIIIYZYIIIIIYZZZX": 0.001280826234117315, "IIIIIIIXZXIIIIIYZZZX": -0.001280826234117315, "IIIIIIYZYIIIIIXZZZYI": 0.001280826234117315, "IIIIIIYZXIIIIIYZZZYI": -0.001280826234117315, "IIIIIIXZXIIIIIYZZZXI": -0.001280826234117315, "IIIIIIYZYIIIIIYZZZXI": 0.001280826234117315, "IIIIIIYZXIIIIIXZZZXI": 0.001280826234117315, "IIIIIIXZYIIIIIXZZZXI": 0.001280826234117315, "IIIIIIXZXIIIIIXZZZYI": -0.001280826234117315, "IIIIIIXZYIIIIIYZZZYI": -0.001280826234117315, "IIIIIIIXZZZYIIIIIXZX": 0.0012808262341173146, "IIIIIIIXZZZXIIIIIXZY": -0.0012808262341173146, "IIIIIIIYZZZYIIIIIYZX": 0.0012808262341173146, "IIIIIIIYZZZYIIIIIXZY": 0.0012808262341173146, "IIIIIIIXZZZXIIIIIYZX": -0.0012808262341173146, "IIIIIIXZZZXIIIIIXZYI": -0.0012808262341173146, "IIIIIIIYZZZXIIIIIYZY": -0.0012808262341173146, "IIIIIIIXZZZYIIIIIYZY": -0.0012808262341173146, "IIIIIIIYZZZXIIIIIXZX": 0.0012808262341173146, "IIIIIIXZZZXIIIIIYZXI": -0.0012808262341173146, "IIIIIIYZZZYIIIIIXZYI": 0.0012808262341173146, "IIIIIIYZZZYIIIIIYZXI": 0.0012808262341173146, "IIIIIIYZZZXIIIIIYZYI": -0.0012808262341173146, "IIIIIIXZZZYIIIIIYZYI": -0.0012808262341173146, "IIIIIIYZZZXIIIIIXZXI": 0.0012808262341173146, "IIIIIIXZZZYIIIIIXZXI": 0.0012808262341173146, "IIIIIIIIYXIIIIIIIIYY": 0.001138205570842223, "IIIIIIIIXYIIIIIIIIYY": 0.001138205570842223, "IIIIIIIIYXIIIIIIIIXX": -0.001138205570842223, "IIIIIIIIXYIIIIIIIIXX": -0.001138205570842223, "IIIIIIIIXXIIIIIIIIXY": 0.001138205570842223, "IIIIIIIIYYIIIIIIIIXY": -0.001138205570842223, "IIIIIIIIXXIIIIIIIIYX": 0.001138205570842223, "IIIIIIIIYYIIIIIIIIYX": -0.001138205570842223, "IIIIIIIIIIYYIIIIIIYX": -0.0011382055708422224, "IIIIIIIIIIXXIIIIIIYX": 0.0011382055708422224, "IIIIIIIIIIXYIIIIIIYY": 0.0011382055708422224, "IIIIIIIIIIYXIIIIIIXX": -0.0011382055708422224, "IIIIIIIIIIYYIIIIIIXY": -0.0011382055708422224, "IIIIIIIIIIXXIIIIIIXY": 0.0011382055708422224, "IIIIIIIIIIXYIIIIIIXX": -0.0011382055708422224, "IIIIIIIIIIYXIIIIIIYY": 0.0011382055708422224, "IIIIIIIIYXIIIIIIXXII": -0.0010748077255508489, "IIIIIIIIXYIIIIIIYYII": 0.0010748077255508489, "IIIIIIIIYXIIIIIIYYII": 0.0010748077255508489, "IIIIIIIIYYIIIIIIYXII": -0.0010748077255508489, "IIIIIIIIYYIIIIIIXYII": -0.0010748077255508489, "IIIIIIIIXXIIIIIIXYII": 0.0010748077255508489, "IIIIIIIIXYIIIIIIXXII": -0.0010748077255508489, "IIIIIIIIXXIIIIIIYXII": 0.0010748077255508489, "IIIIIIIIIIYYIIXYIIII": -0.001074807725550847, "IIIIIIIIIIXXIIYXIIII": 0.001074807725550847, "IIIIIIIIIIYYIIYXIIII": -0.001074807725550847, "IIIIIIIIIIYXIIYYIIII": 0.001074807725550847, "IIIIIIIIIIYXIIXXIIII": -0.001074807725550847, "IIIIIIIIIIXYIIXXIIII": -0.001074807725550847, "IIIIIIIIIIXXIIXYIIII": 0.001074807725550847, "IIIIIIIIIIXYIIYYIIII": 0.001074807725550847, "IIIIYYIIIIIIIIYXIIII": -0.0010237358140966707, "IIIIYXIIIIIIIIYYIIII": 0.0010237358140966707, "IIIIXYIIIIIIIIYYIIII": 0.0010237358140966707, "IIIIXXIIIIIIIIYXIIII": 0.0010237358140966707, "IIIIXXIIIIIIIIXYIIII": 0.0010237358140966707, "IIIIYYIIIIIIIIXYIIII": -0.0010237358140966707, "IIIIYXIIIIIIIIXXIIII": -0.0010237358140966707, "IIIIXYIIIIIIIIXXIIII": -0.0010237358140966707, "IIIIXYIIIIIIIIIIXXII": -0.0010237358140966688, "IIIIYYIIIIIIIIIIXYII": -0.0010237358140966688, "IIIIXXIIIIIIIIIIXYII": 0.0010237358140966688, "IIIIYXIIIIIIIIIIXXII": -0.0010237358140966688, "IIIIXYIIIIIIIIIIYYII": 0.0010237358140966688, "IIIIYXIIIIIIIIIIYYII": 0.0010237358140966688, "IIIIYYIIIIIIIIIIYXII": -0.0010237358140966688, "IIIIXXIIIIIIIIIIYXII": 0.0010237358140966688, "IIIIYZZZZZZZZYIIIIXY": 0.0009389767024160204, "IIIIXZZZZZZZZXIIIIXY": -0.0009389767024160204, "IIIIXZZZZZZZZXIIIIYX": -0.0009389767024160204, "IIIIYZZZZZZZZYIIIIYX": 0.0009389767024160204, "IIIIYZZZZZZZZXIIIIYY": -0.0009389767024160204, "IIIIXZZZZZZZZYIIIIYY": -0.0009389767024160204, "IIIIYZZZZZZZZXIIIIXX": 0.0009389767024160204, "IIIIXZZZZZZZZYIIIIXX": 0.0009389767024160204, "IIIIIYZZZZZZYIIIIIYX": -0.0009389767024160204, "IIIIIYZZZZZZXIIIIIYY": 0.0009389767024160204, "IIIIIYZZZZZZYIIIIIXY": -0.0009389767024160204, "IIIIIXZZZZZZYIIIIIYY": 0.0009389767024160204, "IIIIIXZZZZZZXIIIIIYX": 0.0009389767024160204, "IIIIIYZZZZZZXIIIIIXX": -0.0009389767024160204, "IIIIIXZZZZZZYIIIIIXX": -0.0009389767024160204, "IIIIIXZZZZZZXIIIIIXY": 0.0009389767024160204, "IIIIIYXIIIIIIIIIIIYY": 0.0008693752357647658, "IIIIIYYIIIIIIIIIIIYX": -0.0008693752357647658, "IIIIIXXIIIIIIIIIIIYX": 0.0008693752357647658, "IIIIXZZXIIIIIIIIIIXY": -0.0008693752357647658, "IIIIYZZXIIIIIIIIIIYY": -0.0008693752357647658, "IIIIXZZYIIIIIIIIIIYY": -0.0008693752357647658, "IIIIYZZXIIIIIIIIIIXX": 0.0008693752357647658, "IIIIXZZYIIIIIIIIIIXX": 0.0008693752357647658, "IIIIYZZYIIIIIIIIIIXY": 0.0008693752357647658, "IIIIIYXIIIIIIIIIIIXX": -0.0008693752357647658, "IIIIXZZXIIIIIIIIIIYX": -0.0008693752357647658, "IIIIIXYIIIIIIIIIIIYY": 0.0008693752357647658, "IIIIIYYIIIIIIIIIIIXY": -0.0008693752357647658, "IIIIYZZYIIIIIIIIIIYX": 0.0008693752357647658, "IIIIIXYIIIIIIIIIIIXX": -0.0008693752357647658, "IIIIIXXIIIIIIIIIIIXY": 0.0008693752357647658, "IIIIIIXXIIIIIIIIIIYX": 0.0008688777065043695, "IIIIIIYYIIIIIIIIIIYX": -0.0008688777065043695, "IIIIIIYXIIIIIIIIIIYY": 0.0008688777065043695, "IIIIIIXYIIIIIIIIIIYY": 0.0008688777065043695, "IIIIIIXYIIIIIIIIIIXX": -0.0008688777065043695, "IIIIIIXXIIIIIIIIIIXY": 0.0008688777065043695, "IIIIIIYYIIIIIIIIIIXY": -0.0008688777065043695, "IIIIIIYXIIIIIIIIIIXX": -0.0008688777065043695, "IIIIIIIIYZZZZYIYZZXI": -0.0006876648935530939, "IIIIIIIIYZZZZXIYZZYI": 0.0006876648935530939, "IIIIIIIIXZZZZYIYZZYI": 0.0006876648935530939, "IIIIIIIIXZZZZYIXZZXI": -0.0006876648935530939, "IIIIIIIIXZZZZXIXZZYI": 0.0006876648935530939, "IIIIIIIIYZZZZXIXZZXI": -0.0006876648935530939, "IIIIIIIIXZZZZXIYZZXI": 0.0006876648935530939, "IIIIIIIIYZZZZYIXZZYI": -0.0006876648935530939, "IIIIIIIIIYZZYIYZZZZX": -0.0006876648935530939, "IIIIIIIIIYZZYIXZZZZY": -0.0006876648935530939, "IIIIIIIIIXZZXIXZZZZY": 0.0006876648935530939, "IIIIIIIIIXZZYIXZZZZX": -0.0006876648935530939, "IIIIIIIIIXZZXIYZZZZX": 0.0006876648935530939, "IIIIIIIIIYZZXIXZZZZX": -0.0006876648935530939, "IIIIIIIIIYZZXIYZZZZY": 0.0006876648935530939, "IIIIIIIIIXZZYIYZZZZY": 0.0006876648935530939, "IIIIIIIIIIYZZYIIIYXI": -0.0006876648935530929, "IIIIIIIIIIXZZXIIIYXI": 0.0006876648935530929, "IIIIIIIIIIIYYIIIYZZX": -0.0006876648935530929, "IIIIIIIIIIIYXIIIYZZY": 0.0006876648935530929, "IIIIIIIIIIIXYIIIYZZY": 0.0006876648935530929, "IIIIIIIIIIIYXIIIXZZX": -0.0006876648935530929, "IIIIIIIIIIIXYIIIXZZX": -0.0006876648935530929, "IIIIIIIIIIIXXIIIXZZY": 0.0006876648935530929, "IIIIIIIIIIIYYIIIXZZY": -0.0006876648935530929, "IIIIIIIIIIXZZXIIIXYI": 0.0006876648935530929, "IIIIIIIIIIIXXIIIYZZX": 0.0006876648935530929, "IIIIIIIIIIYZZYIIIXYI": -0.0006876648935530929, "IIIIIIIIIIXZZYIIIXXI": -0.0006876648935530929, "IIIIIIIIIIYZZXIIIXXI": -0.0006876648935530929, "IIIIIIIIIIXZZYIIIYYI": 0.0006876648935530929, "IIIIIIIIIIYZZXIIIYYI": 0.0006876648935530929, "IIIIIYZZZZZZXIIIYYII": -0.0006235819394930388, "IIIIIYZZZZZZYIIIYXII": 0.0006235819394930388, "IIIIXZZZZZZZZYIIXXII": -0.0006235819394930388, "IIIIIXZZZZZZXIIIYXII": -0.0006235819394930388, "IIIIIXZZZZZZYIIIYYII": -0.0006235819394930388, "IIIIIYZZZZZZXIIIXXII": 0.0006235819394930388, "IIIIXZZZZZZZZXIIXYII": 0.0006235819394930388, "IIIIYZZZZZZZZYIIXYII": -0.0006235819394930388, "IIIIYZZZZZZZZYIIYXII": -0.0006235819394930388, "IIIIXZZZZZZZZXIIYXII": 0.0006235819394930388, "IIIIYZZZZZZZZXIIXXII": -0.0006235819394930388, "IIIIXZZZZZZZZYIIYYII": 0.0006235819394930388, "IIIIYZZZZZZZZXIIYYII": 0.0006235819394930388, "IIIIIYZZZZZZYIIIXYII": 0.0006235819394930388, "IIIIIXZZZZZZXIIIXYII": -0.0006235819394930388, "IIIIIXZZZZZZYIIIXXII": 0.0006235819394930388, "IIIIXZZZZZZZZYYYIIII": 0.0006235819394930345, "IIIIYZZZZZZZZXXXIIII": -0.0006235819394930345, "IIIIXZZZZZZZZYXXIIII": -0.0006235819394930345, "IIIIXZZZZZZZZXXYIIII": 0.0006235819394930345, "IIIIYZZZZZZZZYXYIIII": -0.0006235819394930345, "IIIIYZZZZZZZZYYXIIII": -0.0006235819394930345, "IIIIXZZZZZZZZXYXIIII": 0.0006235819394930345, "IIIIYZZZZZZZZXYYIIII": 0.0006235819394930345, "IIIIIXZZZZZZYIYYIIII": -0.0006235819394930345, "IIIIIYZZZZZZYIYXIIII": 0.0006235819394930345, "IIIIIYZZZZZZYIXYIIII": 0.0006235819394930345, "IIIIIXZZZZZZXIXYIIII": -0.0006235819394930345, "IIIIIYZZZZZZXIYYIIII": -0.0006235819394930345, "IIIIIXZZZZZZYIXXIIII": 0.0006235819394930345, "IIIIIYZZZZZZXIXXIIII": 0.0006235819394930345, "IIIIIXZZZZZZXIYXIIII": -0.0006235819394930345, "IIIIIXZZZZZZZZZZZZZY": 0.0005785200523544911, "IIIIYZZZZZZZZZZZZZXI": -0.0005785200523544911, "IIIIXZZZZZZZZZZZZZYI": 0.0005785200523544911, "IIIIIYZZZZZZZZZZZZZX": -0.0005785200523544911, "IIIIYZZYIIIIIIXYIIII": -0.0005499609581934734, "IIIIXZZXIIIIIIXYIIII": 0.0005499609581934734, "IIIIXZZYIIIIIIXXIIII": -0.0005499609581934734, "IIIIYZZXIIIIIIXXIIII": -0.0005499609581934734, "IIIIIYYIIIIIIIXYIIII": 0.0005499609581934734, "IIIIIXXIIIIIIIXYIIII": -0.0005499609581934734, "IIIIIXYIIIIIIIXXIIII": 0.0005499609581934734, "IIIIIYXIIIIIIIXXIIII": 0.0005499609581934734, "IIIIXZZYIIIIIIYYIIII": 0.0005499609581934734, "IIIIXZZXIIIIIIYXIIII": 0.0005499609581934734, "IIIIYZZYIIIIIIYXIIII": -0.0005499609581934734, "IIIIIXYIIIIIIIYYIIII": -0.0005499609581934734, "IIIIYZZXIIIIIIYYIIII": 0.0005499609581934734, "IIIIIYYIIIIIIIYXIIII": 0.0005499609581934734, "IIIIIYXIIIIIIIYYIIII": -0.0005499609581934734, "IIIIIXXIIIIIIIYXIIII": -0.0005499609581934734, "IIIIYZZXIIIIIIIIYYII": 0.0005499609581934681, "IIIIXZZXIIIIIIIIYXII": 0.0005499609581934681, "IIIIYZZYIIIIIIIIYXII": -0.0005499609581934681, "IIIIXZZYIIIIIIIIYYII": 0.0005499609581934681, "IIIIIYXIIIIIIIIIXXII": 0.0005499609581934681, "IIIIIXYIIIIIIIIIXXII": 0.0005499609581934681, "IIIIIXXIIIIIIIIIXYII": -0.0005499609581934681, "IIIIIYYIIIIIIIIIXYII": 0.0005499609581934681, "IIIIIXXIIIIIIIIIYXII": -0.0005499609581934681, "IIIIIYYIIIIIIIIIYXII": 0.0005499609581934681, "IIIIIYXIIIIIIIIIYYII": -0.0005499609581934681, "IIIIXZZXIIIIIIIIXYII": 0.0005499609581934681, "IIIIXZZYIIIIIIIIXXII": -0.0005499609581934681, "IIIIYZZXIIIIIIIIXXII": -0.0005499609581934681, "IIIIYZZYIIIIIIIIXYII": -0.0005499609581934681, "IIIIIXYIIIIIIIIIYYII": -0.0005499609581934681, "IIIIIIYZZZZZZXIIIIYY": 0.00029156444130504125, "IIIIIIYZZZZZZYIIIIYX": -0.00029156444130504125, "IIIIIIYZZZZZZYIIIIXY": -0.00029156444130504125, "IIIIIIXZZZZZZXIIIIXY": 0.00029156444130504125, "IIIIIIXZZZZZZYIIIIXX": -0.00029156444130504125, "IIIIIIYZZZZZZXIIIIXX": -0.00029156444130504125, "IIIIIIXZZZZZZYIIIIYY": 0.00029156444130504125, "IIIIIIIYZZZZYIIIIIYX": 0.00029156444130504125, "IIIIIIIXZZZZXIIIIIYX": -0.00029156444130504125, "IIIIIIIYZZZZXIIIIIYY": -0.00029156444130504125, "IIIIIIIYZZZZXIIIIIXX": 0.00029156444130504125, "IIIIIIIYZZZZYIIIIIXY": 0.00029156444130504125, "IIIIIIIXZZZZXIIIIIXY": -0.00029156444130504125, "IIIIIIIXZZZZYIIIIIXX": 0.00029156444130504125, "IIIIIIXZZZZZZXIIIIYX": 0.00029156444130504125, "IIIIIIIXZZZZYIIIIIYY": -0.00029156444130504125, "IIYZZZZZZZZZZXIIYYII": 0.00015549302142505762, "IIYZZZZZZZZZZYIIYXII": -0.00015549302142505762, "IIXZZZZZZZZZZXIIYXII": 0.00015549302142505762, "IIYZZZZZZZZZZYIIXYII": -0.00015549302142505762, "IIXZZZZZZZZZZYIIXXII": -0.00015549302142505762, "IIYZZZZZZZZZZXIIXXII": -0.00015549302142505762, "IIXZZZZZZZZZZYIIYYII": 0.00015549302142505762, "IIXZZZZZZZZZZXIIXYII": 0.00015549302142505762, "IIIXZZZZZZZZYIIIXXII": 0.00015549302142505762, "IIIYZZZZZZZZXIIIXXII": 0.00015549302142505762, "IIIXZZZZZZZZYIIIYYII": -0.00015549302142505762, "IIIXZZZZZZZZXIIIXYII": -0.00015549302142505762, "IIIYZZZZZZZZYIIIXYII": 0.00015549302142505762, "IIIYZZZZZZZZXIIIYYII": -0.00015549302142505762, "IIIYZZZZZZZZYIIIYXII": 0.00015549302142505762, "IIIXZZZZZZZZXIIIYXII": -0.00015549302142505762, "IIIXZZZZZZZZXIYXIIII": -0.00015549302142505735, "IIIYZZZZZZZZYIYXIIII": 0.00015549302142505735, "IIIYZZZZZZZZXIYYIIII": -0.00015549302142505735, "IIYZZZZZZZZZZYXYIIII": -0.00015549302142505735, "IIXZZZZZZZZZZXXYIIII": 0.00015549302142505735, "IIYZZZZZZZZZZXXXIIII": -0.00015549302142505735, "IIXZZZZZZZZZZYYYIIII": 0.00015549302142505735, "IIYZZZZZZZZZZXYYIIII": 0.00015549302142505735, "IIXZZZZZZZZZZXYXIIII": 0.00015549302142505735, "IIXZZZZZZZZZZYXXIIII": -0.00015549302142505735, "IIYZZZZZZZZZZYYXIIII": -0.00015549302142505735, "IIIXZZZZZZZZYIYYIIII": -0.00015549302142505735, "IIIYZZZZZZZZXIXXIIII": 0.00015549302142505735, "IIIXZZZZZZZZYIXXIIII": 0.00015549302142505735, "IIIYZZZZZZZZYIXYIIII": 0.00015549302142505735, "IIIXZZZZZZZZXIXYIIII": -0.00015549302142505735, "IIXZZZZZZZZZZXIIIIYX": 0.00014453994759264704, "IIYZZZZZZZZZZYIIIIYX": -0.00014453994759264704, "IIYZZZZZZZZZZXIIIIYY": 0.00014453994759264704, "IIXZZZZZZZZZZYIIIIYY": 0.00014453994759264704, "IIYZZZZZZZZZZXIIIIXX": -0.00014453994759264704, "IIIXZZZZZZZZXIIIIIXY": -0.00014453994759264704, "IIIXZZZZZZZZYIIIIIXX": 0.00014453994759264704, "IIIYZZZZZZZZXIIIIIXX": 0.00014453994759264704, "IIIXZZZZZZZZYIIIIIYY": -0.00014453994759264704, "IIIYZZZZZZZZXIIIIIYY": -0.00014453994759264704, "IIIYZZZZZZZZYIIIIIYX": 0.00014453994759264704, "IIIXZZZZZZZZXIIIIIYX": -0.00014453994759264704, "IIIYZZZZZZZZYIIIIIXY": 0.00014453994759264704, "IIXZZZZZZZZZZYIIIIXX": -0.00014453994759264704, "IIXZZZZZZZZZZXIIIIXY": 0.00014453994759264704, "IIYZZZZZZZZZZYIIIIXY": -0.00014453994759264704, "IIXYIIIIIIIIIIIIIIXX": -0.00012714719454653582, "IIXXIIIIIIIIIIIIIIXY": 0.00012714719454653582, "IIYYIIIIIIIIIIIIIIXY": -0.00012714719454653582, "IIXXIIIIIIIIIIIIIIYX": 0.00012714719454653582, "IIYYIIIIIIIIIIIIIIYX": -0.00012714719454653582, "IIYXIIIIIIIIIIIIIIYY": 0.00012714719454653582, "IIXYIIIIIIIIIIIIIIYY": 0.00012714719454653582, "IIYXIIIIIIIIIIIIIIXX": -0.00012714719454653582, "IIIIIIYZZXIIIIYZZZZY": 0.00011894268978551167, "IIIIIIIYYIIIIIIYZZXI": -0.00011894268978551167, "IIIIIIYZZYIIIIXZZZZY": -0.00011894268978551167, "IIIIIIXZZXIIIIXZZZZY": 0.00011894268978551167, "IIIIIIXZZXIIIIYZZZZX": 0.00011894268978551167, "IIIIIIXZZYIIIIXZZZZX": -0.00011894268978551167, "IIIIIIYZZYIIIIYZZZZX": -0.00011894268978551167, "IIIIIIYZZXIIIIXZZZZX": -0.00011894268978551167, "IIIIIIXZZYIIIIYZZZZY": 0.00011894268978551167, "IIIIIIIYXIIIIIIYZZYI": 0.00011894268978551167, "IIIIIIIXXIIIIIIYZZXI": 0.00011894268978551167, "IIIIIIIYYIIIIIIXZZYI": -0.00011894268978551167, "IIIIIIIXXIIIIIIXZZYI": 0.00011894268978551167, "IIIIIIIXYIIIIIIXZZXI": -0.00011894268978551167, "IIIIIIIYXIIIIIIXZZXI": -0.00011894268978551167, "IIIIIIIXYIIIIIIYZZYI": 0.00011894268978551167, "IIIIIIXZZZZXIIIIYZZX": 0.00011894268978551086, "IIIIIIYZZZZYIIIIYZZX": -0.00011894268978551086, "IIIIIIYZZZZXIIIIYZZY": 0.00011894268978551086, "IIIIIIYZZZZXIIIIXZZX": -0.00011894268978551086, "IIIIIIXZZZZYIIIIXZZX": -0.00011894268978551086, "IIIIIIXZZZZXIIIIXZZY": 0.00011894268978551086, "IIIIIIYZZZZYIIIIXZZY": -0.00011894268978551086, "IIIIIIXZZZZYIIIIYZZY": 0.00011894268978551086, "IIIIIIIXZZYIIIIIIXXI": -0.00011894268978551086, "IIIIIIIYZZXIIIIIIYYI": 0.00011894268978551086, "IIIIIIIXZZXIIIIIIXYI": 0.00011894268978551086, "IIIIIIIYZZYIIIIIIXYI": -0.00011894268978551086, "IIIIIIIXZZYIIIIIIYYI": 0.00011894268978551086, "IIIIIIIYZZYIIIIIIYXI": -0.00011894268978551086, "IIIIIIIXZZXIIIIIIYXI": 0.00011894268978551086, "IIIIIIIYZZXIIIIIIXXI": -0.00011894268978551086, "YXIIIIIIIIIIIIIIIIXX": -0.00011050966741221791, "XYIIIIIIIIIIIIIIIIYY": 0.00011050966741221791, "YYIIIIIIIIIIIIIIIIXY": -0.00011050966741221791, "XXIIIIIIIIIIIIIIIIXY": 0.00011050966741221791, "XYIIIIIIIIIIIIIIIIXX": -0.00011050966741221791, "XXIIIIIIIIIIIIIIIIYX": 0.00011050966741221791, "YXIIIIIIIIIIIIIIIIYY": 0.00011050966741221791, "YYIIIIIIIIIIIIIIIIYX": -0.00011050966741221791, "IIXZZZZZYIIIIIXZZZXI": 9.570927178688232e-05, "IIXZZZZZXIIIIIXZZZYI": -9.570927178688232e-05, "IIYZZZZZYIIIIIXZZZYI": 9.570927178688232e-05, "IIYZZZZZXIIIIIYZZZYI": -9.570927178688232e-05, "IIYZZZZZYIIIIIYZZZXI": 9.570927178688232e-05, "IIIXZZZZZXIIIIIYZZZX": -9.570927178688232e-05, "IIXZZZZZXIIIIIYZZZXI": -9.570927178688232e-05, "IIIYZZZZZYIIIIIYZZZX": 9.570927178688232e-05, "IIIYZZZZZXIIIIIYZZZY": -9.570927178688232e-05, "IIXZZZZZYIIIIIYZZZYI": -9.570927178688232e-05, "IIYZZZZZXIIIIIXZZZXI": 9.570927178688232e-05, "IIIYZZZZZYIIIIIXZZZY": 9.570927178688232e-05, "IIIXZZZZZYIIIIIXZZZX": 9.570927178688232e-05, "IIIXZZZZZXIIIIIXZZZY": -9.570927178688232e-05, "IIIYZZZZZXIIIIIXZZZX": 9.570927178688232e-05, "IIIXZZZZZYIIIIIYZZZY": -9.570927178688232e-05, "IIIYZZZZZZZXIIIIIXZX": 9.570927178688213e-05, "IIIXZZZZZZZYIIIIIYZY": -9.570927178688213e-05, "IIIYZZZZZZZXIIIIIYZY": -9.570927178688213e-05, "IIIYZZZZZZZYIIIIIYZX": 9.570927178688213e-05, "IIIXZZZZZZZYIIIIIXZX": 9.570927178688213e-05, "IIIXZZZZZZZXIIIIIYZX": -9.570927178688213e-05, "IIYZZZZZZZXIIIIIXZXI": 9.570927178688213e-05, "IIXZZZZZZZYIIIIIXZXI": 9.570927178688213e-05, "IIIYZZZZZZZYIIIIIXZY": 9.570927178688213e-05, "IIYZZZZZZZYIIIIIXZYI": 9.570927178688213e-05, "IIXZZZZZZZXIIIIIXZYI": -9.570927178688213e-05, "IIXZZZZZZZYIIIIIYZYI": -9.570927178688213e-05, "IIXZZZZZZZXIIIIIYZXI": -9.570927178688213e-05, "IIYZZZZZZZYIIIIIYZXI": 9.570927178688213e-05, "IIIXZZZZZZZXIIIIIXZY": -9.570927178688213e-05, "IIYZZZZZZZXIIIIIYZYI": -9.570927178688213e-05, "IIIXZZZZZZZZZZZZZZZY": 8.660998183724251e-05, "IIIYZZZZZZZZZZZZZZZX": -8.660998183724251e-05, "IIYZZZZZZZZZZZZZZZXI": -8.660998183724251e-05, "IIXZZZZZZZZZZZZZZZYI": 8.660998183724251e-05, "IIXZZZZYIIIIIIIIXXII": 7.805513405053108e-05, "IIYZZZZXIIIIIIIIYYII": -7.805513405053108e-05, "IIYZZZZYIIIIIIIIYXII": 7.805513405053108e-05, "IIXZZZZXIIIIIIIIYXII": -7.805513405053108e-05, "IIIYZZYIIIIIIIIIXYII": -7.805513405053108e-05, "IIIXZZXIIIIIIIIIXYII": 7.805513405053108e-05, "IIIXZZYIIIIIIIIIXXII": -7.805513405053108e-05, "IIIYZZYIIIIIIIIIYXII": -7.805513405053108e-05, "IIIYZZXIIIIIIIIIXXII": -7.805513405053108e-05, "IIIXZZYIIIIIIIIIYYII": 7.805513405053108e-05, "IIXZZZZYIIIIIIIIYYII": -7.805513405053108e-05, "IIYZZZZXIIIIIIIIXXII": 7.805513405053108e-05, "IIIYZZXIIIIIIIIIYYII": 7.805513405053108e-05, "IIXZZZZXIIIIIIIIXYII": -7.805513405053108e-05, "IIIXZZXIIIIIIIIIYXII": 7.805513405053108e-05, "IIYZZZZYIIIIIIIIXYII": 7.805513405053108e-05, "IIIYZZXIIIIIIIXXIIII": -7.805513405053095e-05, "IIIXZZYIIIIIIIYYIIII": 7.805513405053095e-05, "IIIYZZXIIIIIIIYYIIII": 7.805513405053095e-05, "IIIYZZYIIIIIIIYXIIII": -7.805513405053095e-05, "IIIXZZYIIIIIIIXXIIII": -7.805513405053095e-05, "IIIXZZXIIIIIIIXYIIII": 7.805513405053095e-05, "IIIYZZYIIIIIIIXYIIII": -7.805513405053095e-05, "IIIXZZXIIIIIIIYXIIII": 7.805513405053095e-05, "IIYZZZZYIIIIIIXYIIII": 7.805513405053095e-05, "IIXZZZZXIIIIIIYXIIII": -7.805513405053095e-05, "IIYZZZZYIIIIIIYXIIII": 7.805513405053095e-05, "IIYZZZZXIIIIIIYYIIII": -7.805513405053095e-05, "IIXZZZZYIIIIIIYYIIII": -7.805513405053095e-05, "IIYZZZZXIIIIIIXXIIII": 7.805513405053095e-05, "IIXZZZZYIIIIIIXXIIII": 7.805513405053095e-05, "IIXZZZZXIIIIIIXYIIII": -7.805513405053095e-05, "YZZZZZZZYIIIIIXZZZYI": 7.753362442708715e-05, "XZZZZZZZXIIIIIXZZZYI": -7.753362442708715e-05, "XZZZZZZZYIIIIIXZZZXI": 7.753362442708715e-05, "XZZZZZZZYIIIIIYZZZYI": -7.753362442708715e-05, "YZZZZZZZXIIIIIYZZZYI": -7.753362442708715e-05, "YZZZZZZZYIIIIIYZZZXI": 7.753362442708715e-05, "YZZZZZZZXIIIIIXZZZXI": 7.753362442708715e-05, "XZZZZZZZXIIIIIYZZZXI": -7.753362442708715e-05, "YZZZZZZZZZXIIIIIXZXI": 7.753362442708715e-05, "XZZZZZZZZZXIIIIIYZXI": -7.753362442708715e-05, "YZZZZZZZZZYIIIIIYZXI": 7.753362442708715e-05, "YZZZZZZZZZXIIIIIYZYI": -7.753362442708715e-05, "IXZZZZZZZXIIIIIYZZZX": -7.753362442708715e-05, "IYZZZZZZZYIIIIIYZZZX": 7.753362442708715e-05, "IYZZZZZZZXIIIIIYZZZY": -7.753362442708715e-05, "IXZZZZZZZYIIIIIYZZZY": -7.753362442708715e-05, "XZZZZZZZZZYIIIIIYZYI": -7.753362442708715e-05, "IXZZZZZZZYIIIIIXZZZX": 7.753362442708715e-05, "IYZZZZZZZZZXIIIIIYZY": -7.753362442708715e-05, "IYZZZZZZZZZYIIIIIYZX": 7.753362442708715e-05, "IXZZZZZZZZZXIIIIIYZX": -7.753362442708715e-05, "IYZZZZZZZXIIIIIXZZZX": 7.753362442708715e-05, "YZZZZZZZZZYIIIIIXZYI": 7.753362442708715e-05, "XZZZZZZZZZXIIIIIXZYI": -7.753362442708715e-05, "XZZZZZZZZZYIIIIIXZXI": 7.753362442708715e-05, "IYZZZZZZZYIIIIIXZZZY": 7.753362442708715e-05, "IXZZZZZZZXIIIIIXZZZY": -7.753362442708715e-05, "IXZZZZZZZZZYIIIIIYZY": -7.753362442708715e-05, "IYZZZZZZZZZYIIIIIXZY": 7.753362442708715e-05, "IXZZZZZZZZZXIIIIIXZY": -7.753362442708715e-05, "IYZZZZZZZZZXIIIIIXZX": 7.753362442708715e-05, "IXZZZZZZZZZYIIIIIXZX": 7.753362442708715e-05, "IIYYIIIIIIIIIIIIXYII": -7.487800718324426e-05, "IIXXIIIIIIIIIIIIXYII": 7.487800718324426e-05, "IIXYIIIIIIIIIIIIXXII": -7.487800718324426e-05, "IIXXIIIIIIIIIIIIYXII": 7.487800718324426e-05, "IIXYIIIIIIIIIIIIYYII": 7.487800718324426e-05, "IIYXIIIIIIIIIIIIYYII": 7.487800718324426e-05, "IIYYIIIIIIIIIIIIYXII": -7.487800718324426e-05, "IIYXIIIIIIIIIIIIXXII": -7.487800718324426e-05, "IIXXIIIIIIIIIIYXIIII": 7.487800718324414e-05, "IIYYIIIIIIIIIIYXIIII": -7.487800718324414e-05, "IIYXIIIIIIIIIIYYIIII": 7.487800718324414e-05, "IIXYIIIIIIIIIIYYIIII": 7.487800718324414e-05, "IIYXIIIIIIIIIIXXIIII": -7.487800718324414e-05, "IIXYIIIIIIIIIIXXIIII": -7.487800718324414e-05, "IIXXIIIIIIIIIIXYIIII": 7.487800718324414e-05, "IIYYIIIIIIIIIIXYIIII": -7.487800718324414e-05, "IIXZZZZZZXIIIIXZZZZY": -6.469970121331808e-05, "IIXZZZZZZYIIIIXZZZZX": 6.469970121331808e-05, "IIXZZZZZZYIIIIYZZZZY": -6.469970121331808e-05, "IIIXZZZZXIIIIIIYZZXI": -6.469970121331808e-05, "IIYZZZZZZXIIIIYZZZZY": -6.469970121331808e-05, "IIYZZZZZZYIIIIYZZZZX": 6.469970121331808e-05, "IIXZZZZZZXIIIIYZZZZX": -6.469970121331808e-05, "IIYZZZZZZYIIIIXZZZZY": 6.469970121331808e-05, "IIYZZZZZZXIIIIXZZZZX": 6.469970121331808e-05, "IIIYZZZZYIIIIIIXZZYI": 6.469970121331808e-05, "IIIXZZZZXIIIIIIXZZYI": -6.469970121331808e-05, "IIIXZZZZYIIIIIIXZZXI": 6.469970121331808e-05, "IIIYZZZZXIIIIIIXZZXI": 6.469970121331808e-05, "IIIXZZZZYIIIIIIYZZYI": -6.469970121331808e-05, "IIIYZZZZYIIIIIIYZZXI": 6.469970121331808e-05, "IIIYZZZZXIIIIIIYZZYI": -6.469970121331808e-05, "IIYZZZZZZZZXIIIIYZZY": -6.469970121331797e-05, "IIYZZZZZZZZYIIIIYZZX": 6.469970121331797e-05, "IIXZZZZZZZZXIIIIYZZX": -6.469970121331797e-05, "IIYZZZZZZZZXIIIIXZZX": 6.469970121331797e-05, "IIIYZZZZZZYIIIIIIXYI": 6.469970121331797e-05, "IIIXZZZZZZXIIIIIIXYI": -6.469970121331797e-05, "IIYZZZZZZZZYIIIIXZZY": 6.469970121331797e-05, "IIIXZZZZZZYIIIIIIXXI": 6.469970121331797e-05, "IIIYZZZZZZXIIIIIIXXI": 6.469970121331797e-05, "IIIXZZZZZZYIIIIIIYYI": -6.469970121331797e-05, "IIIYZZZZZZYIIIIIIYXI": 6.469970121331797e-05, "IIIXZZZZZZXIIIIIIYXI": -6.469970121331797e-05, "IIXZZZZZZZZXIIIIXZZY": -6.469970121331797e-05, "IIXZZZZZZZZYIIIIXZZX": 6.469970121331797e-05, "IIXZZZZZZZZYIIIIYZZY": -6.469970121331797e-05, "IIIYZZZZZZXIIIIIIYYI": -6.469970121331797e-05, "IIYZZXIIIIIIIIIIYYII": 5.7863911372914587e-05, "IIXZZYIIIIIIIIIIYYII": 5.7863911372914587e-05, "IIIYXIIIIIIIIIIIYYII": -5.7863911372914587e-05, "IIIYYIIIIIIIIIIIYXII": 5.7863911372914587e-05, "IIYZZXIIIIIIIIIIXXII": -5.7863911372914587e-05, "IIXZZYIIIIIIIIIIXXII": -5.7863911372914587e-05, "IIXZZXIIIIIIIIIIXYII": 5.7863911372914587e-05, "IIYZZYIIIIIIIIIIXYII": -5.7863911372914587e-05, "IIIYYIIIIIIIIIIIXYII": 5.7863911372914587e-05, "IIIXXIIIIIIIIIIIXYII": -5.7863911372914587e-05, "IIIXYIIIIIIIIIIIXXII": 5.7863911372914587e-05, "IIYZZYIIIIIIIIIIYXII": -5.7863911372914587e-05, "IIIXXIIIIIIIIIIIYXII": -5.7863911372914587e-05, "IIIYXIIIIIIIIIIIXXII": 5.7863911372914587e-05, "IIIXYIIIIIIIIIIIYYII": -5.7863911372914587e-05, "IIXZZXIIIIIIIIIIYXII": 5.7863911372914587e-05, "IIIXXIIIIIIIIIYXIIII": -5.786391137291434e-05, "IIIXYIIIIIIIIIXXIIII": 5.786391137291434e-05, "IIIYYIIIIIIIIIYXIIII": 5.786391137291434e-05, "IIXZZXIIIIIIIIYXIIII": 5.786391137291434e-05, "IIYZZYIIIIIIIIYXIIII": -5.786391137291434e-05, "IIYZZXIIIIIIIIYYIIII": 5.786391137291434e-05, "IIIXXIIIIIIIIIXYIIII": -5.786391137291434e-05, "IIYZZYIIIIIIIIXYIIII": -5.786391137291434e-05, "IIXZZXIIIIIIIIXYIIII": 5.786391137291434e-05, "IIXZZYIIIIIIIIXXIIII": -5.786391137291434e-05, "IIYZZXIIIIIIIIXXIIII": -5.786391137291434e-05, "IIIYXIIIIIIIIIXXIIII": 5.786391137291434e-05, "IIIXYIIIIIIIIIYYIIII": -5.786391137291434e-05, "IIXZZYIIIIIIIIYYIIII": 5.786391137291434e-05, "IIIYYIIIIIIIIIXYIIII": 5.786391137291434e-05, "IIIYXIIIIIIIIIYYIIII": -5.786391137291434e-05, "XZZZZYIIIIIIIIYYIIII": 5.3282011642962604e-05, "YZZZZXIIIIIIIIXXIIII": -5.3282011642962604e-05, "IXZZXIIIIIIIIIYXIIII": -5.3282011642962604e-05, "IYZZYIIIIIIIIIYXIIII": 5.3282011642962604e-05, "IYZZXIIIIIIIIIYYIIII": -5.3282011642962604e-05, "XZZZZXIIIIIIIIXYIIII": 5.3282011642962604e-05, "XZZZZYIIIIIIIIXXIIII": -5.3282011642962604e-05, "YZZZZYIIIIIIIIYXIIII": -5.3282011642962604e-05, "YZZZZXIIIIIIIIYYIIII": 5.3282011642962604e-05, "IXZZYIIIIIIIIIXXIIII": 5.3282011642962604e-05, "IYZZYIIIIIIIIIXYIIII": 5.3282011642962604e-05, "IXZZXIIIIIIIIIXYIIII": -5.3282011642962604e-05, "XZZZZXIIIIIIIIYXIIII": 5.3282011642962604e-05, "IYZZXIIIIIIIIIXXIIII": 5.3282011642962604e-05, "IXZZYIIIIIIIIIYYIIII": -5.3282011642962604e-05, "YZZZZYIIIIIIIIXYIIII": -5.3282011642962604e-05, "IXZZXIIIIIIIIIIIXYII": -5.328201164296244e-05, "IXZZYIIIIIIIIIIIXXII": 5.328201164296244e-05, "IYZZXIIIIIIIIIIIXXII": 5.328201164296244e-05, "IXZZYIIIIIIIIIIIYYII": -5.328201164296244e-05, "IYZZXIIIIIIIIIIIYYII": -5.328201164296244e-05, "IYZZYIIIIIIIIIIIYXII": 5.328201164296244e-05, "IXZZXIIIIIIIIIIIYXII": -5.328201164296244e-05, "XZZZZXIIIIIIIIIIYXII": 5.328201164296244e-05, "YZZZZXIIIIIIIIIIYYII": 5.328201164296244e-05, "XZZZZYIIIIIIIIIIYYII": 5.328201164296244e-05, "YZZZZXIIIIIIIIIIXXII": -5.328201164296244e-05, "XZZZZYIIIIIIIIIIXXII": -5.328201164296244e-05, "YZZZZYIIIIIIIIIIYXII": -5.328201164296244e-05, "XZZZZXIIIIIIIIIIXYII": 5.328201164296244e-05, "IYZZYIIIIIIIIIIIXYII": 5.328201164296244e-05, "YZZZZYIIIIIIIIIIXYII": -5.328201164296244e-05, "XZZZZZZZZYIIIIXZZZZX": 5.1434939395810166e-05, "IXZZZZZZXIIIIIIYZZXI": -5.1434939395810166e-05, "IYZZZZZZYIIIIIIYZZXI": 5.1434939395810166e-05, "IYZZZZZZXIIIIIIYZZYI": -5.1434939395810166e-05, "IXZZZZZZYIIIIIIYZZYI": -5.1434939395810166e-05, "IXZZZZZZYIIIIIIXZZXI": 5.1434939395810166e-05, "IXZZZZZZXIIIIIIXZZYI": -5.1434939395810166e-05, "IYZZZZZZYIIIIIIXZZYI": 5.1434939395810166e-05, "IYZZZZZZXIIIIIIXZZXI": 5.1434939395810166e-05, "XZZZZZZZZYIIIIYZZZZY": -5.1434939395810166e-05, "YZZZZZZZZYIIIIYZZZZX": 5.1434939395810166e-05, "XZZZZZZZZXIIIIXZZZZY": -5.1434939395810166e-05, "YZZZZZZZZYIIIIXZZZZY": 5.1434939395810166e-05, "YZZZZZZZZXIIIIYZZZZY": -5.1434939395810166e-05, "YZZZZZZZZXIIIIXZZZZX": 5.1434939395810166e-05, "XZZZZZZZZXIIIIYZZZZX": -5.1434939395810166e-05, "XZZZZZZZZZZXIIIIXZZY": -5.143493939581013e-05, "XZZZZZZZZZZYIIIIXZZX": 5.143493939581013e-05, "YZZZZZZZZZZXIIIIXZZX": 5.143493939581013e-05, "YZZZZZZZZZZYIIIIYZZX": 5.143493939581013e-05, "YZZZZZZZZZZXIIIIYZZY": -5.143493939581013e-05, "XZZZZZZZZZZYIIIIYZZY": -5.143493939581013e-05, "XZZZZZZZZZZXIIIIYZZX": -5.143493939581013e-05, "IXZZZZZZZZXIIIIIIYXI": -5.143493939581013e-05, "IYZZZZZZZZXIIIIIIXXI": 5.143493939581013e-05, "IXZZZZZZZZYIIIIIIYYI": -5.143493939581013e-05, "IYZZZZZZZZXIIIIIIYYI": -5.143493939581013e-05, "IYZZZZZZZZYIIIIIIYXI": 5.143493939581013e-05, "IXZZZZZZZZXIIIIIIXYI": -5.143493939581013e-05, "IXZZZZZZZZYIIIIIIXXI": 5.143493939581013e-05, "IYZZZZZZZZYIIIIIIXYI": 5.143493939581013e-05, "YZZZZZZZZZZYIIIIXZZY": 5.143493939581013e-05, "YZZZZZZYIIIIIIXYIIII": -5.1065298588001004e-05, "XZZZZZZXIIIIIIXYIIII": 5.1065298588001004e-05, "XZZZZZZYIIIIIIXXIIII": -5.1065298588001004e-05, "IYZZZZYIIIIIIIXYIIII": 5.1065298588001004e-05, "IXZZZZXIIIIIIIXYIIII": -5.1065298588001004e-05, "IXZZZZYIIIIIIIXXIIII": 5.1065298588001004e-05, "IXZZZZYIIIIIIIYYIIII": -5.1065298588001004e-05, "IYZZZZXIIIIIIIXXIIII": 5.1065298588001004e-05, "YZZZZZZXIIIIIIYYIIII": 5.1065298588001004e-05, "YZZZZZZYIIIIIIYXIIII": -5.1065298588001004e-05, "XZZZZZZXIIIIIIYXIIII": 5.1065298588001004e-05, "XZZZZZZYIIIIIIYYIIII": 5.1065298588001004e-05, "IXZZZZXIIIIIIIYXIIII": -5.1065298588001004e-05, "IYZZZZYIIIIIIIYXIIII": 5.1065298588001004e-05, "IYZZZZXIIIIIIIYYIIII": -5.1065298588001004e-05, "YZZZZZZXIIIIIIXXIIII": -5.1065298588001004e-05, "YZZZZZZXIIIIIIIIXXII": -5.106529858800089e-05, "XZZZZZZYIIIIIIIIYYII": 5.106529858800089e-05, "XZZZZZZXIIIIIIIIYXII": 5.106529858800089e-05, "YZZZZZZYIIIIIIIIYXII": -5.106529858800089e-05, "YZZZZZZXIIIIIIIIYYII": 5.106529858800089e-05, "XZZZZZZYIIIIIIIIXXII": -5.106529858800089e-05, "YZZZZZZYIIIIIIIIXYII": -5.106529858800089e-05, "IYZZZZYIIIIIIIIIYXII": 5.106529858800089e-05, "IYZZZZXIIIIIIIIIYYII": -5.106529858800089e-05, "XZZZZZZXIIIIIIIIXYII": 5.106529858800089e-05, "IXZZZZXIIIIIIIIIYXII": -5.106529858800089e-05, "IXZZZZYIIIIIIIIIYYII": -5.106529858800089e-05, "IXZZZZYIIIIIIIIIXXII": 5.106529858800089e-05, "IXZZZZXIIIIIIIIIXYII": -5.106529858800089e-05, "IYZZZZYIIIIIIIIIXYII": 5.106529858800089e-05, "IYZZZZXIIIIIIIIIXXII": 5.106529858800089e-05, "XXIIIIIIIIIIIIXYIIII": 3.198996672253003e-05, "YYIIIIIIIIIIIIXYIIII": -3.198996672253003e-05, "XYIIIIIIIIIIIIXXIIII": -3.198996672253003e-05, "XYIIIIIIIIIIIIYYIIII": 3.198996672253003e-05, "XXIIIIIIIIIIIIYXIIII": 3.198996672253003e-05, "YXIIIIIIIIIIIIXXIIII": -3.198996672253003e-05, "YXIIIIIIIIIIIIYYIIII": 3.198996672253003e-05, "YYIIIIIIIIIIIIYXIIII": -3.198996672253003e-05, "XYIIIIIIIIIIIIIIYYII": 3.1989966722529937e-05, "YYIIIIIIIIIIIIIIYXII": -3.1989966722529937e-05, "XXIIIIIIIIIIIIIIYXII": 3.1989966722529937e-05, "XYIIIIIIIIIIIIIIXXII": -3.1989966722529937e-05, "XXIIIIIIIIIIIIIIXYII": 3.1989966722529937e-05, "YYIIIIIIIIIIIIIIXYII": -3.1989966722529937e-05, "YXIIIIIIIIIIIIIIXXII": -3.1989966722529937e-05, "YXIIIIIIIIIIIIIIYYII": 3.1989966722529937e-05, "IIYZZZZZZXIIIIIXZZXI": 3.100957057356424e-05, "IIYZZZZZZYIIIIIYZZXI": 3.100957057356424e-05, "IIIYZZZZYIIIIIXZZZZY": 3.100957057356424e-05, "IIYZZZZZZXIIIIIYZZYI": -3.100957057356424e-05, "IIXZZZZZZYIIIIIYZZYI": -3.100957057356424e-05, "IIXZZZZZZXIIIIIYZZXI": -3.100957057356424e-05, "IIIXZZZZXIIIIIXZZZZY": -3.100957057356424e-05, "IIIXZZZZYIIIIIXZZZZX": 3.100957057356424e-05, "IIIYZZZZXIIIIIXZZZZX": 3.100957057356424e-05, "IIIYZZZZYIIIIIYZZZZX": 3.100957057356424e-05, "IIIXZZZZXIIIIIYZZZZX": -3.100957057356424e-05, "IIIYZZZZXIIIIIYZZZZY": -3.100957057356424e-05, "IIIXZZZZYIIIIIYZZZZY": -3.100957057356424e-05, "IIXZZZZZZYIIIIIXZZXI": 3.100957057356424e-05, "IIXZZZZZZXIIIIIXZZYI": -3.100957057356424e-05, "IIYZZZZZZYIIIIIXZZYI": 3.100957057356424e-05, "IIYZZZZZZZZYIIIIIYXI": 3.100957057356416e-05, "IIXZZZZZZZZXIIIIIYXI": -3.100957057356416e-05, "IIXZZZZZZZZYIIIIIYYI": -3.100957057356416e-05, "IIYZZZZZZZZXIIIIIXXI": 3.100957057356416e-05, "IIXZZZZZZZZYIIIIIXXI": 3.100957057356416e-05, "IIXZZZZZZZZXIIIIIXYI": -3.100957057356416e-05, "IIYZZZZZZZZXIIIIIYYI": -3.100957057356416e-05, "IIIYZZZZZZXIIIIIYZZY": -3.100957057356416e-05, "IIIYZZZZZZYIIIIIXZZY": 3.100957057356416e-05, "IIIXZZZZZZXIIIIIXZZY": -3.100957057356416e-05, "IIIXZZZZZZYIIIIIXZZX": 3.100957057356416e-05, "IIIYZZZZZZXIIIIIXZZX": 3.100957057356416e-05, "IIIXZZZZZZYIIIIIYZZY": -3.100957057356416e-05, "IIIXZZZZZZXIIIIIYZZX": -3.100957057356416e-05, "IIIYZZZZZZYIIIIIYZZX": 3.100957057356416e-05, "IIYZZZZZZZZYIIIIIXYI": 3.100957057356416e-05, "IIIYZZYIIIIIIIIIIIXY": -2.8293151420546086e-05, "IIIYZZXIIIIIIIIIIIXX": -2.8293151420546086e-05, "IIIXZZXIIIIIIIIIIIXY": 2.8293151420546086e-05, "IIIXZZYIIIIIIIIIIIXX": -2.8293151420546086e-05, "IIIXZZXIIIIIIIIIIIYX": 2.8293151420546086e-05, "IIIYZZYIIIIIIIIIIIYX": -2.8293151420546086e-05, "IIIYZZXIIIIIIIIIIIYY": 2.8293151420546086e-05, "IIIXZZYIIIIIIIIIIIYY": 2.8293151420546086e-05, "IIYZZZZYIIIIIIIIIIXY": 2.8293151420546086e-05, "IIYZZZZYIIIIIIIIIIYX": 2.8293151420546086e-05, "IIYZZZZXIIIIIIIIIIYY": -2.8293151420546086e-05, "IIXZZZZYIIIIIIIIIIYY": -2.8293151420546086e-05, "IIYZZZZXIIIIIIIIIIXX": 2.8293151420546086e-05, "IIXZZZZYIIIIIIIIIIXX": 2.8293151420546086e-05, "IIXZZZZXIIIIIIIIIIXY": -2.8293151420546086e-05, "IIXZZZZXIIIIIIIIIIYX": -2.8293151420546086e-05, "IXZZZZZZZZYIIIIIXZZX": 2.6098685031277017e-05, "IYZZZZZZZZXIIIIIXZZX": 2.6098685031277017e-05, "IXZZZZZZZZYIIIIIYZZY": -2.6098685031277017e-05, "IYZZZZZZZZXIIIIIYZZY": -2.6098685031277017e-05, "IYZZZZZZZZYIIIIIYZZX": 2.6098685031277017e-05, "IXZZZZZZZZXIIIIIYZZX": -2.6098685031277017e-05, "IYZZZZZZZZYIIIIIXZZY": 2.6098685031277017e-05, "YZZZZZZZZZZYIIIIIYXI": 2.6098685031277017e-05, "XZZZZZZZZZZXIIIIIYXI": -2.6098685031277017e-05, "YZZZZZZZZZZXIIIIIYYI": -2.6098685031277017e-05, "XZZZZZZZZZZYIIIIIYYI": -2.6098685031277017e-05, "YZZZZZZZZZZXIIIIIXXI": 2.6098685031277017e-05, "IXZZZZZZZZXIIIIIXZZY": -2.6098685031277017e-05, "XZZZZZZZZZZYIIIIIXXI": 2.6098685031277017e-05, "XZZZZZZZZZZXIIIIIXYI": -2.6098685031277017e-05, "YZZZZZZZZZZYIIIIIXYI": 2.6098685031277017e-05, "IYZZZZZZXIIIIIYZZZZY": -2.609868503127698e-05, "IXZZZZZZXIIIIIYZZZZX": -2.609868503127698e-05, "IYZZZZZZYIIIIIYZZZZX": 2.609868503127698e-05, "XZZZZZZZZXIIIIIYZZXI": -2.609868503127698e-05, "IXZZZZZZYIIIIIYZZZZY": -2.609868503127698e-05, "IYZZZZZZXIIIIIXZZZZX": 2.609868503127698e-05, "IXZZZZZZYIIIIIXZZZZX": 2.609868503127698e-05, "IXZZZZZZXIIIIIXZZZZY": -2.609868503127698e-05, "IYZZZZZZYIIIIIXZZZZY": 2.609868503127698e-05, "XZZZZZZZZYIIIIIYZZYI": -2.609868503127698e-05, "YZZZZZZZZYIIIIIXZZYI": 2.609868503127698e-05, "XZZZZZZZZXIIIIIXZZYI": -2.609868503127698e-05, "XZZZZZZZZYIIIIIXZZXI": 2.609868503127698e-05, "YZZZZZZZZXIIIIIXZZXI": 2.609868503127698e-05, "YZZZZZZZZXIIIIIYZZYI": -2.609868503127698e-05, "YZZZZZZZZYIIIIIYZZXI": 2.609868503127698e-05, "IYZZXIIIIIIIIIIIIIXX": 1.6528868950380487e-05, "IXZZYIIIIIIIIIIIIIYY": -1.6528868950380487e-05, "YZZZZYIIIIIIIIIIIIYX": -1.6528868950380487e-05, "IYZZYIIIIIIIIIIIIIYX": 1.6528868950380487e-05, "IXZZXIIIIIIIIIIIIIYX": -1.6528868950380487e-05, "IXZZYIIIIIIIIIIIIIXX": 1.6528868950380487e-05, "IYZZXIIIIIIIIIIIIIYY": -1.6528868950380487e-05, "IYZZYIIIIIIIIIIIIIXY": 1.6528868950380487e-05, "YZZZZXIIIIIIIIIIIIYY": 1.6528868950380487e-05, "XZZZZYIIIIIIIIIIIIYY": 1.6528868950380487e-05, "YZZZZXIIIIIIIIIIIIXX": -1.6528868950380487e-05, "XZZZZYIIIIIIIIIIIIXX": -1.6528868950380487e-05, "XZZZZXIIIIIIIIIIIIXY": 1.6528868950380487e-05, "XZZZZXIIIIIIIIIIIIYX": 1.6528868950380487e-05, "IXZZXIIIIIIIIIIIIIXY": -1.6528868950380487e-05, "YZZZZYIIIIIIIIIIIIXY": -1.6528868950380487e-05, "IYZZZZZZZZZZYIXYIIII": -1.4048669338366068e-05, "IXZZZZZZZZZZXIYXIIII": 1.4048669338366068e-05, "IYZZZZZZZZZZYIYXIIII": -1.4048669338366068e-05, "IXZZZZZZZZZZXIXYIIII": 1.4048669338366068e-05, "IXZZZZZZZZZZYIYYIIII": 1.4048669338366068e-05, "IYZZZZZZZZZZXIXXIIII": -1.4048669338366068e-05, "IXZZZZZZZZZZYIXXIIII": -1.4048669338366068e-05, "IYZZZZZZZZZZXIYYIIII": 1.4048669338366068e-05, "XZZZZZZZZZZZZYYYIIII": -1.4048669338366068e-05, "YZZZZZZZZZZZZXXXIIII": 1.4048669338366068e-05, "XZZZZZZZZZZZZYXXIIII": 1.4048669338366068e-05, "XZZZZZZZZZZZZXXYIIII": -1.4048669338366068e-05, "YZZZZZZZZZZZZYXYIIII": 1.4048669338366068e-05, "XZZZZZZZZZZZZXYXIIII": -1.4048669338366068e-05, "YZZZZZZZZZZZZYYXIIII": 1.4048669338366068e-05, "YZZZZZZZZZZZZXYYIIII": -1.4048669338366068e-05, "IXZZZZZZZZZZXIIIYXII": 1.4048669338366035e-05, "IYZZZZZZZZZZYIIIYXII": -1.4048669338366035e-05, "IYZZZZZZZZZZXIIIYYII": 1.4048669338366035e-05, "IXZZZZZZZZZZYIIIYYII": 1.4048669338366035e-05, "IYZZZZZZZZZZXIIIXXII": -1.4048669338366035e-05, "IXZZZZZZZZZZYIIIXXII": -1.4048669338366035e-05, "YZZZZZZZZZZZZYIIXYII": 1.4048669338366035e-05, "XZZZZZZZZZZZZXIIXYII": -1.4048669338366035e-05, "XZZZZZZZZZZZZYIIXXII": 1.4048669338366035e-05, "YZZZZZZZZZZZZXIIXXII": 1.4048669338366035e-05, "XZZZZZZZZZZZZYIIYYII": -1.4048669338366035e-05, "YZZZZZZZZZZZZXIIYYII": -1.4048669338366035e-05, "YZZZZZZZZZZZZYIIYXII": 1.4048669338366035e-05, "XZZZZZZZZZZZZXIIYXII": -1.4048669338366035e-05, "IXZZZZZZZZZZXIIIXYII": 1.4048669338366035e-05, "IYZZZZZZZZZZYIIIXYII": -1.4048669338366035e-05, "XZZZZZZXIIIIIIIIIIYX": 1.2344938686713796e-05, "YZZZZZZYIIIIIIIIIIYX": -1.2344938686713796e-05, "YZZZZZZXIIIIIIIIIIYY": 1.2344938686713796e-05, "XZZZZZZYIIIIIIIIIIYY": 1.2344938686713796e-05, "YZZZZZZXIIIIIIIIIIXX": -1.2344938686713796e-05, "XZZZZZZXIIIIIIIIIIXY": 1.2344938686713796e-05, "YZZZZZZYIIIIIIIIIIXY": -1.2344938686713796e-05, "XZZZZZZYIIIIIIIIIIXX": -1.2344938686713796e-05, "IYZZZZYIIIIIIIIIIIXY": 1.2344938686713796e-05, "IXZZZZXIIIIIIIIIIIYX": -1.2344938686713796e-05, "IYZZZZYIIIIIIIIIIIYX": 1.2344938686713796e-05, "IXZZZZYIIIIIIIIIIIYY": -1.2344938686713796e-05, "IYZZZZXIIIIIIIIIIIYY": -1.2344938686713796e-05, "IXZZZZYIIIIIIIIIIIXX": 1.2344938686713796e-05, "IXZZZZXIIIIIIIIIIIXY": -1.2344938686713796e-05, "IYZZZZXIIIIIIIIIIIXX": 1.2344938686713796e-05, "IXZZZZZZZZZZZZZZZZZY": -8.03616816845068e-06, "IYZZZZZZZZZZZZZZZZZX": 8.03616816845068e-06, "XZZZZZZZZZZZZZZZZZYI": -8.03616816845068e-06, "YZZZZZZZZZZZZZZZZZXI": 8.03616816845068e-06, "YZZZZZZZZZZZZYIIIIXY": 5.175719808067567e-06, "IXZZZZZZZZZZYIIIIIXX": -5.175719808067567e-06, "IYZZZZZZZZZZXIIIIIXX": -5.175719808067567e-06, "IXZZZZZZZZZZYIIIIIYY": 5.175719808067567e-06, "IYZZZZZZZZZZXIIIIIYY": 5.175719808067567e-06, "IYZZZZZZZZZZYIIIIIYX": -5.175719808067567e-06, "IXZZZZZZZZZZXIIIIIYX": 5.175719808067567e-06, "XZZZZZZZZZZZZXIIIIYX": -5.175719808067567e-06, "YZZZZZZZZZZZZYIIIIYX": 5.175719808067567e-06, "YZZZZZZZZZZZZXIIIIYY": -5.175719808067567e-06, "XZZZZZZZZZZZZYIIIIYY": -5.175719808067567e-06, "YZZZZZZZZZZZZXIIIIXX": 5.175719808067567e-06, "XZZZZZZZZZZZZYIIIIXX": 5.175719808067567e-06, "IXZZZZZZZZZZXIIIIIXY": 5.175719808067567e-06, "XZZZZZZZZZZZZXIIIIXY": -5.175719808067567e-06, "IYZZZZZZZZZZYIIIIIXY": -5.175719808067567e-06, "IYYIIIIIIIIIIIIIIIXY": -2.5922532772833316e-06, "IXXIIIIIIIIIIIIIIIXY": 2.5922532772833316e-06, "IXYIIIIIIIIIIIIIIIXX": -2.5922532772833316e-06, "YZZXIIIIIIIIIIIIIIYY": -2.5922532772833316e-06, "IYXIIIIIIIIIIIIIIIYY": 2.5922532772833316e-06, "IYYIIIIIIIIIIIIIIIYX": -2.5922532772833316e-06, "IXYIIIIIIIIIIIIIIIYY": 2.5922532772833316e-06, "IYXIIIIIIIIIIIIIIIXX": -2.5922532772833316e-06, "IXXIIIIIIIIIIIIIIIYX": 2.5922532772833316e-06, "XZZYIIIIIIIIIIIIIIYY": -2.5922532772833316e-06, "YZZXIIIIIIIIIIIIIIXX": 2.5922532772833316e-06, "XZZYIIIIIIIIIIIIIIXX": 2.5922532772833316e-06, "XZZXIIIIIIIIIIIIIIXY": -2.5922532772833316e-06, "YZZYIIIIIIIIIIIIIIXY": 2.5922532772833316e-06, "YZZYIIIIIIIIIIIIIIYX": 2.5922532772833316e-06, "XZZXIIIIIIIIIIIIIIYX": -2.5922532772833316e-06, "YZZXIIIIIIIIIIXXIIII": 2.1103348129421323e-06, "IXXIIIIIIIIIIIYXIIII": 2.1103348129421323e-06, "IYYIIIIIIIIIIIYXIIII": -2.1103348129421323e-06, "IYXIIIIIIIIIIIYYIIII": 2.1103348129421323e-06, "IXYIIIIIIIIIIIYYIIII": 2.1103348129421323e-06, "IYXIIIIIIIIIIIXXIIII": -2.1103348129421323e-06, "IYYIIIIIIIIIIIXYIIII": -2.1103348129421323e-06, "IXXIIIIIIIIIIIXYIIII": 2.1103348129421323e-06, "YZZXIIIIIIIIIIYYIIII": -2.1103348129421323e-06, "YZZYIIIIIIIIIIYXIIII": 2.1103348129421323e-06, "XZZXIIIIIIIIIIYXIIII": -2.1103348129421323e-06, "XZZYIIIIIIIIIIXXIIII": 2.1103348129421323e-06, "XZZYIIIIIIIIIIYYIIII": -2.1103348129421323e-06, "YZZYIIIIIIIIIIXYIIII": 2.1103348129421323e-06, "XZZXIIIIIIIIIIXYIIII": -2.1103348129421323e-06, "IXYIIIIIIIIIIIXXIIII": -2.1103348129421323e-06, "XZZXIIIIIIIIIIIIYXII": -2.1103348129421306e-06, "YZZXIIIIIIIIIIIIYYII": -2.1103348129421306e-06, "YZZYIIIIIIIIIIIIYXII": 2.1103348129421306e-06, "IXYIIIIIIIIIIIIIYYII": 2.1103348129421306e-06, "IXXIIIIIIIIIIIIIYXII": 2.1103348129421306e-06, "XZZYIIIIIIIIIIIIXXII": 2.1103348129421306e-06, "YZZXIIIIIIIIIIIIXXII": 2.1103348129421306e-06, "XZZXIIIIIIIIIIIIXYII": -2.1103348129421306e-06, "XZZYIIIIIIIIIIIIYYII": -2.1103348129421306e-06, "YZZYIIIIIIIIIIIIXYII": 2.1103348129421306e-06, "IYYIIIIIIIIIIIIIXYII": -2.1103348129421306e-06, "IXYIIIIIIIIIIIIIXXII": -2.1103348129421306e-06, "IYXIIIIIIIIIIIIIXXII": -2.1103348129421306e-06, "IYXIIIIIIIIIIIIIYYII": 2.1103348129421306e-06, "IYYIIIIIIIIIIIIIYXII": -2.1103348129421306e-06, "IXXIIIIIIIIIIIIIXYII": 2.1103348129421306e-06}}, "hf_method_fallback": "standard", "generation_time_s": 20.01, "timestamp": "2026-03-10T21:42:48.088412+00:00", "formula_latex": "$\\mathrm{CO}$"}}