{"n_qubits": 8, "qubits": [1, 2, 3, 4, 5, 6, 7, 8], "fci_energy": -14.581910918559808, "hf_energy": -14.485091815270266, "CS_SRE": [0.38075967757964496, 0.45596847593800804, 0.9432758661168209, 0.7099684968631634, 0.70777557520331, 0.7055297782228719, 0.7055795542032117, 0.7050329318442979], "CS_energy": [-14.556653506404784, -14.562562729544588, -14.575110679940362, -14.58028724916869, -14.58090196336603, -14.58152686421409, -14.58167935985922, -14.581910918559876], "overlaps": [0.8023709486004742, 0.7597071586522324, 0.595468590346524, 0.6950587279470648, 0.7033027359143358, 0.7114662265068551, 0.7112877426075671, 0.7112143038567651], "solver": "scipy", "data": {"molecule_id": "BeH+_singlet_Coov", "qubit_encoding": "JW", "unit": "Angstrom", "basis": "sto-3g", "charge": 1, "multiplicity": 1, "spin": 0, "geometry": "Be 0.0000000000 0.0000000000 -0.6713000000\nH 0.0000000000 0.0000000000 2.0139000000", "n_qubits": 12, "n_particles": {"total": 4, "alpha": 2, "beta": 2}, "hf_array": [1, 1, 1, 1, 0, 0, 0, 0, 0, 0, 0, 0], "hf_method": "pyscf.scf.hf_symm.SymAdaptedRHF", "convergence_threshold": 1e-06, "point_group": {"groupname": "Coov", "topgroup": "Coov"}, "alpha": 2.0, "calculated_properties": {"HF": {"energy": -14.485091815270266, "converged": true}, "MP2": {"energy": -14.540002649495325, "converged": null}, "CISD": {"energy": -14.581763020490007, "converged": true}, "CCSD": {"energy": -14.581812767072975, "converged": true, "t1_diagnostic": 0.09437630668988352}, "FCI": {"energy": -14.581910918559808, "converged": true, "spin_matches_target": true, "multiplicity": 0.9999999999999987, "oscillatory_converged": false, "oscillation_energy_change": null}}, "auxiliary_operators": {"number_operator": {"IIIIIIIIIIII": 6.0, "ZIIIIIIIIIII": -0.5, "IZIIIIIIIIII": -0.5, "IIZIIIIIIIII": -0.5, "IIIZIIIIIIII": -0.5, "IIIIZIIIIIII": -0.5, "IIIIIZIIIIII": -0.5, "IIIIIIZIIIII": -0.5, "IIIIIIIZIIII": -0.5, "IIIIIIIIZIII": -0.5, "IIIIIIIIIZII": -0.5, "IIIIIIIIIIZI": -0.5, "IIIIIIIIIIIZ": -0.5}, "N_alpha": {"IIIIIIIIIIII": 3.0, "ZIIIIIIIIIII": -0.5, "IIZIIIIIIIII": -0.5, "IIIIZIIIIIII": -0.5, "IIIIIIZIIIII": -0.5, "IIIIIIIIZIII": -0.5, "IIIIIIIIIIZI": -0.5}, "N_beta": {"IIIIIIIIIIII": 3.0, "IZIIIIIIIIII": -0.5, "IIIZIIIIIIII": -0.5, "IIIIIZIIIIII": -0.5, "IIIIIIIZIIII": -0.5, "IIIIIIIIIZII": -0.5, "IIIIIIIIIIIZ": -0.5}, "S^2_operator": {"IIIIIIIIIIII": 2.25, "IIZZIIIIIIII": -0.375, "IIIIIIIIIIZZ": -0.375, "IIIIZZIIIIII": -0.375, "IIIIIIZZIIII": -0.375, "IIIIIIIIZZII": -0.375, "ZZIIIIIIIIII": -0.375, "IIIIIIYXYXII": 0.125, "IIIIIIIIYYYY": 0.125, "IIIIIIIIYYXX": 0.125, "IIIIIIIIXYYX": -0.125, "IIIIIIIIXYXY": 0.125, "IIIIYYIIIIXX": 0.125, "ZIZIIIIIIIII": 0.125, "ZIIZIIIIIIII": -0.125, "ZIIIZIIIIIII": 0.125, "ZIIIIZIIIIII": -0.125, "ZIIIIIZIIIII": 0.125, "ZIIIIIIZIIII": -0.125, "ZIIIIIIIZIII": 0.125, "ZIIIIIIIIZII": -0.125, "ZIIIIIIIIIZI": 0.125, "ZIIIIIIIIIIZ": -0.125, "IZZIIIIIIIII": -0.125, "IIIIIIIIXXXX": 0.125, "IIIIXYIIIIXY": 0.125, "IIIIIIIIXXYY": 0.125, "IIIIIIIIYXYX": 0.125, "IIIIIIYXXYII": -0.125, "IIIIIIXXYYII": 0.125, "IIIIIIXXXXII": 0.125, "IIIIIIYYYYII": 0.125, "IIIIIIYYXXII": 0.125, "IIIIIIXYYXII": -0.125, "IIIIIIXYXYII": 0.125, "IIIIIIYXIIYX": 0.125, "IIIIIIYXIIXY": -0.125, "IIIIIIXXIIYY": 0.125, "IIIIIIXXIIXX": 0.125, "IIIIXYIIIIYX": -0.125, "IIIIIIYYIIYY": 0.125, "IIIIIIYYIIXX": 0.125, "IIIIIIXYIIYX": -0.125, "IIIIIIXYIIXY": 0.125, "IZIZIIIIIIII": 0.125, "IIIIIIIIYXXY": -0.125, "IZIIZIIIIIII": -0.125, "IZIIIIZIIIII": -0.125, "IIIIYYIIIIYY": 0.125, "IIIIZIIIIZII": -0.125, "IIIIZIIIIIZI": 0.125, "IIIIZIIIIIIZ": -0.125, "IIIIIZZIIIII": -0.125, "IIIIIZIZIIII": 0.125, "IIIIIZIIZIII": -0.125, "IIIIIZIIIZII": 0.125, "IIIIIZIIIIZI": -0.125, "IIIIIZIIIIIZ": 0.125, "IIIIIIZIZIII": 0.125, "IIIIIIZIIZII": -0.125, "IIIIIIZIIIZI": 0.125, "IIIIIIZIIIIZ": -0.125, "IIIIIIIZZIII": -0.125, "IIIIIIIZIZII": 0.125, "IIIIIIIZIIZI": -0.125, "IIIIIIIZIIIZ": 0.125, "IIIIIIIIZIZI": 0.125, "IIIIIIIIZIIZ": -0.125, "IIIIZIIIZIII": 0.125, "IIIIZIIZIIII": -0.125, "IIIIZIZIIIII": 0.125, "IIIZIIIIIIIZ": 0.125, "IZIIIIIZIIII": 0.125, "IZIIIIIIZIII": -0.125, "IZIIIIIIIZII": 0.125, "IZIIIIIIIIZI": -0.125, "IZIIIIIIIIIZ": 0.125, "IIZIZIIIIIII": 0.125, "IIZIIZIIIIII": -0.125, "IIZIIIZIIIII": 0.125, "IIZIIIIZIIII": -0.125, "IZIIIZIIIIII": 0.125, "IIZIIIIIZIII": 0.125, "IIZIIIIIIIZI": 0.125, "IIZIIIIIIIIZ": -0.125, "IIIZZIIIIIII": -0.125, "IIIZIZIIIIII": 0.125, "IIIZIIZIIIII": -0.125, "IIIZIIIZIIII": 0.125, "IIIZIIIIZIII": -0.125, "IIIZIIIIIZII": 0.125, "IIIZIIIIIIZI": -0.125, "IIZIIIIIIZII": -0.125, "IIIIXXIIIIXX": 0.125, "IIIIYXIIIIXY": -0.125, "IIIIIIIIIZZI": -0.125, "XYIIIIXYIIII": 0.125, "YXIIIIIIYXII": 0.125, "YXIIIIIIXYII": -0.125, "XXIIIIIIYYII": 0.125, "XXIIIIIIXXII": 0.125, "YYIIIIIIYYII": 0.125, "YYIIIIIIXXII": 0.125, "XYIIIIIIYXII": -0.125, "XYIIIIIIXYII": 0.125, "YXIIIIIIIIYX": 0.125, "YXIIIIIIIIXY": -0.125, "XXIIIIIIIIYY": 0.125, "XXIIIIIIIIXX": 0.125, "YYIIIIIIIIYY": 0.125, "YYIIIIIIIIXX": 0.125, "XYIIIIIIIIYX": -0.125, "XYIIIIIIIIXY": 0.125, "IIYXYXIIIIII": 0.125, "IIYXXYIIIIII": -0.125, "XYIIIIYXIIII": -0.125, "IIXXYYIIIIII": 0.125, "YYIIIIXXIIII": 0.125, "XXIIIIXXIIII": 0.125, "YXYXIIIIIIII": 0.125, "YXXYIIIIIIII": -0.125, "XXYYIIIIIIII": 0.125, "XXXXIIIIIIII": 0.125, "YYYYIIIIIIII": 0.125, "YYXXIIIIIIII": 0.125, "XYYXIIIIIIII": -0.125, "XYXYIIIIIIII": 0.125, "YXIIYXIIIIII": 0.125, "YXIIXYIIIIII": -0.125, "XXIIYYIIIIII": 0.125, "XXIIXXIIIIII": 0.125, "YYIIYYIIIIII": 0.125, "YYIIXXIIIIII": 0.125, "XYIIYXIIIIII": -0.125, "XYIIXYIIIIII": 0.125, "YXIIIIYXIIII": 0.125, "YXIIIIXYIIII": -0.125, "XXIIIIYYIIII": 0.125, "YYIIIIYYIIII": 0.125, "IIXXXXIIIIII": 0.125, "IIYYYYIIIIII": 0.125, "IIYYXXIIIIII": 0.125, "IIXYIIIIIIYX": -0.125, "IIXYIIIIIIXY": 0.125, "IIIIYXYXIIII": 0.125, "IIIIYXXYIIII": -0.125, "IIIIXXYYIIII": 0.125, "IIIIXXXXIIII": 0.125, "IIIIYYYYIIII": 0.125, "IIIIYYXXIIII": 0.125, "IIIIXYYXIIII": -0.125, "IIIIXYXYIIII": 0.125, "IIIIYXIIYXII": 0.125, "IIIIYXIIXYII": -0.125, "IIIIXXIIYYII": 0.125, "IIIIXXIIXXII": 0.125, "IIIIYYIIYYII": 0.125, "IIIIYYIIXXII": 0.125, "IIIIXYIIYXII": -0.125, "IIIIXYIIXYII": 0.125, "IIIIYXIIIIYX": 0.125, "IIYYIIIIIIXX": 0.125, "IIYYIIIIIIYY": 0.125, "IIXXIIIIIIXX": 0.125, "IIXXIIIIIIYY": 0.125, "IIXYYXIIIIII": -0.125, "IIXYXYIIIIII": 0.125, "IIYXIIYXIIII": 0.125, "IIYXIIXYIIII": -0.125, "IIXXIIYYIIII": 0.125, "IIXXIIXXIIII": 0.125, "IIYYIIYYIIII": 0.125, "IIYYIIXXIIII": 0.125, "IIXYIIYXIIII": -0.125, "IIIIXXIIIIYY": 0.125, "IIXYIIXYIIII": 0.125, "IIYXIIIIXYII": -0.125, "IIXXIIIIYYII": 0.125, "IIXXIIIIXXII": 0.125, "IIYYIIIIYYII": 0.125, "IIYYIIIIXXII": 0.125, "IIXYIIIIYXII": -0.125, "IIXYIIIIXYII": 0.125, "IIYXIIIIIIYX": 0.125, "IIYXIIIIIIXY": -0.125, "IIYXIIIIYXII": 0.125, "IIIIIIIIIZIZ": 0.125}, "UCCSD_operator": {"IIYYXYIIIIII": -0.0719324179402199, "IIXXXYIIIIII": 0.0719324179402199, "IIYXXXIIIIII": -0.0719324179402199, "IIXYYYIIIIII": 0.0719324179402199, "IIXYXXIIIIII": -0.0719324179402199, "IIYXYYIIIIII": 0.0719324179402199, "IIYYYXIIIIII": -0.0719324179402199, "IIXXYXIIIIII": 0.0719324179402199, "IIIYZXIIIIII": 0.07000405043078377, "IIXZYIIIIIII": -0.07000405043078377, "IIYZXIIIIIII": 0.07000405043078377, "IIIXZYIIIIII": -0.07000405043078377, "IIIXZZZZZZZY": 0.06330278153075762, "IIIYZZZZZZZX": -0.06330278153075762, "IIXZZZZZZZYI": 0.06330278153075762, "IIYZZZZZZZXI": -0.06330278153075762, "IIXXIYZZZZXI": 0.014544805421578254, "IIYYIYZZZZXI": -0.014544805421578254, "IIYXIYZZZZYI": 0.014544805421578254, "IIYXIXZZZZXI": -0.014544805421578254, "IIXYIXZZZZXI": -0.014544805421578254, "IIXXIXZZZZYI": 0.014544805421578254, "IIXYIYZZZZYI": 0.014544805421578254, "IIXYYZZZZZZY": -0.014544805421578254, "IIXXXZZZZZZY": -0.014544805421578254, "IIXXYZZZZZZX": -0.014544805421578254, "IIYYYZZZZZZX": 0.014544805421578254, "IIYYXZZZZZZY": 0.014544805421578254, "IIYXYZZZZZZY": -0.014544805421578254, "IIYXXZZZZZZX": 0.014544805421578254, "IIXYXZZZZZZX": 0.014544805421578254, "IIYYIXZZZZYI": -0.014544805421578254, "IIYYIIIIIIXY": -0.00764707638823067, "IIXYIIIIIIXX": -0.00764707638823067, "IIYXIIIIIIXX": -0.00764707638823067, "IIXYIIIIIIYY": 0.00764707638823067, "IIXXIIIIIIXY": 0.00764707638823067, "IIYXIIIIIIYY": 0.00764707638823067, "IIYYIIIIIIYX": -0.00764707638823067, "IIXXIIIIIIYX": 0.00764707638823067, "IIXXIIYXIIII": 0.004940483193387833, "IIYYIIYXIIII": -0.004940483193387833, "IIYXIIYYIIII": 0.004940483193387833, "IIXYIIYYIIII": 0.004940483193387833, "IIYXIIXXIIII": -0.004940483193387833, "IIXYIIXXIIII": -0.004940483193387833, "IIXXIIXYIIII": 0.004940483193387833, "IIYYIIXYIIII": -0.004940483193387833, "IIXXIIIIYXII": 0.0049404831933878325, "IIYYIIIIXYII": -0.0049404831933878325, "IIYYIIIIYXII": -0.0049404831933878325, "IIYXIIIIYYII": 0.0049404831933878325, "IIXYIIIIYYII": 0.0049404831933878325, "IIXYIIIIXXII": -0.0049404831933878325, "IIXXIIIIXYII": 0.0049404831933878325, "IIYXIIIIXXII": -0.0049404831933878325, "YZZXIIIIYYII": 0.0003737653636216111, "XZZYIIIIYYII": 0.0003737653636216111, "XZZYIIIIXXII": -0.0003737653636216111, "XZZXIIIIXYII": 0.0003737653636216111, "YZZYIIIIXYII": -0.0003737653636216111, "YZZYIIIIYXII": -0.0003737653636216111, "YZZXIIIIXXII": -0.0003737653636216111, "XZZXIIIIYXII": 0.0003737653636216111, "YZZYIIXYIIII": -0.0003737653636216111, "XZZXIIXYIIII": 0.0003737653636216111, "XZZYIIXXIIII": -0.0003737653636216111, "YZZXIIXXIIII": -0.0003737653636216111, "XZZYIIYYIIII": 0.0003737653636216111, "YZZXIIYYIIII": 0.0003737653636216111, "YZZYIIYXIIII": -0.0003737653636216111, "IYYIIIYXIIII": 0.0003737653636216111, "XZZXIIYXIIII": 0.0003737653636216111, "IYYIIIIIXYII": 0.0003737653636216111, "IXXIIIIIXYII": -0.0003737653636216111, "IXYIIIIIXXII": 0.0003737653636216111, "IYXIIIIIXXII": 0.0003737653636216111, "IXYIIIIIYYII": -0.0003737653636216111, "IYXIIIIIYYII": -0.0003737653636216111, "IYYIIIIIYXII": 0.0003737653636216111, "IXXIIIIIYXII": -0.0003737653636216111, "IYYIIIXYIIII": 0.0003737653636216111, "IXXIIIXYIIII": -0.0003737653636216111, "IXYIIIXXIIII": 0.0003737653636216111, "IYXIIIXXIIII": 0.0003737653636216111, "IXYIIIYYIIII": -0.0003737653636216111, "IYXIIIYYIIII": -0.0003737653636216111, "IXXIIIYXIIII": -0.0003737653636216111, "IXXIIIIIIIXY": -0.00035675555096956646, "IYYIIIIIIIXY": 0.00035675555096956646, "YZZYIIIIIIXY": -0.00035675555096956646, "XZZXIIIIIIXY": 0.00035675555096956646, "XZZYIIIIIIXX": -0.00035675555096956646, "YZZXIIIIIIXX": -0.00035675555096956646, "XZZYIIIIIIYY": 0.00035675555096956646, "YZZXIIIIIIYY": 0.00035675555096956646, "YZZYIIIIIIYX": -0.00035675555096956646, "IXYIIIIIIIXX": 0.00035675555096956646, "IXXIIIIIIIYX": -0.00035675555096956646, "IYYIIIIIIIYX": 0.00035675555096956646, "XZZXIIIIIIYX": 0.00035675555096956646, "IYXIIIIIIIYY": -0.00035675555096956646, "IXYIIIIIIIYY": -0.00035675555096956646, "IYXIIIIIIIXX": 0.00035675555096956646, "IYZZZZZZZZZX": 0.00034058790603660864, "XZZZZZZZZZYI": -0.00034058790603660864, "YZZZZZZZZZXI": 0.00034058790603660864, "IXZZZZZZZZZY": -0.00034058790603660864, "YZZZXIIIIIII": -0.0002503259738515199, "XZZZYIIIIIII": 0.0002503259738515199, "IYZZZXIIIIII": -0.0002503259738515199, "IXZZZYIIIIII": 0.0002503259738515199, "YXIIIIXXIIII": -0.0001887131643004514, "XYIIIIYYIIII": 0.0001887131643004514, "YXIIIIIIXXII": -0.0001887131643004514, "YYIIIIYXIIII": -0.0001887131643004514, "XXIIIIYXIIII": 0.0001887131643004514, "YXIIIIYYIIII": 0.0001887131643004514, "XYIIIIXXIIII": -0.0001887131643004514, "XXIIIIIIXYII": 0.0001887131643004514, "YYIIIIIIXYII": -0.0001887131643004514, "XYIIIIIIYYII": 0.0001887131643004514, "XYIIIIIIXXII": -0.0001887131643004514, "YYIIIIIIYXII": -0.0001887131643004514, "XXIIIIIIYXII": 0.0001887131643004514, "YYIIIIXYIIII": -0.0001887131643004514, "XXIIIIXYIIII": 0.0001887131643004514, "YXIIIIIIYYII": 0.0001887131643004514, "XXIIIIIIIIXY": 0.0001818362327969745, "XYIIIIIIIIXX": -0.0001818362327969745, "YXIIIIIIIIXX": -0.0001818362327969745, "YXIIIIIIIIYY": 0.0001818362327969745, "YYIIIIIIIIYX": -0.0001818362327969745, "XXIIIIIIIIYX": 0.0001818362327969745, "YYIIIIIIIIXY": -0.0001818362327969745, "XYIIIIIIIIYY": 0.0001818362327969745, "XZZYYYIIIIII": -0.0001255995314779457, "YZZXYYIIIIII": -0.0001255995314779457, "YZZYYXIIIIII": 0.0001255995314779457, "XZZXYXIIIIII": -0.0001255995314779457, "IXXIYXIIIIII": 0.0001255995314779457, "IYYIYXIIIIII": -0.0001255995314779457, "IXYIYYIIIIII": 0.0001255995314779457, "IYXIXXIIIIII": -0.0001255995314779457, "IXYIXXIIIIII": -0.0001255995314779457, "IXXIXYIIIIII": 0.0001255995314779457, "IYXIYYIIIIII": 0.0001255995314779457, "IYYIXYIIIIII": -0.0001255995314779457, "YZZXXXIIIIII": 0.0001255995314779457, "XZZYXXIIIIII": 0.0001255995314779457, "XZZXXYIIIIII": -0.0001255995314779457, "YZZYXYIIIIII": 0.0001255995314779457, "XZZXIYZZZZXI": -9.704105613088311e-05, "YZZYIYZZZZXI": 9.704105613088311e-05, "YZZXIYZZZZYI": -9.704105613088311e-05, "XZZYIYZZZZYI": -9.704105613088311e-05, "XZZXIXZZZZYI": -9.704105613088311e-05, "YZZYIXZZZZYI": 9.704105613088311e-05, "YZZXIXZZZZXI": 9.704105613088311e-05, "XZZYIXZZZZXI": 9.704105613088311e-05, "IXXIYZZZZZZX": -9.704105613088311e-05, "IYYIXZZZZZZY": 9.704105613088311e-05, "IXYIXZZZZZZX": 9.704105613088311e-05, "IYXIXZZZZZZX": 9.704105613088311e-05, "IXXIXZZZZZZY": -9.704105613088311e-05, "IYXIYZZZZZZY": -9.704105613088311e-05, "IYYIYZZZZZZX": 9.704105613088311e-05, "IXYIYZZZZZZY": -9.704105613088311e-05, "XZZXXZZZZZZY": 9.581274026401806e-05, "XZZYXZZZZZZX": -9.581274026401806e-05, "YZZYYZZZZZZX": -9.581274026401806e-05, "XZZYYZZZZZZY": 9.581274026401806e-05, "YZZXYZZZZZZY": 9.581274026401806e-05, "YZZYXZZZZZZY": -9.581274026401806e-05, "YZZXXZZZZZZX": -9.581274026401806e-05, "IYYIIXZZZZYI": -9.581274026401806e-05, "IXXIIXZZZZYI": 9.581274026401806e-05, "IXYIIXZZZZXI": -9.581274026401806e-05, "XZZXYZZZZZZX": 9.581274026401806e-05, "IYXIIXZZZZXI": -9.581274026401806e-05, "IXYIIYZZZZYI": 9.581274026401806e-05, "IYXIIYZZZZYI": 9.581274026401806e-05, "IYYIIYZZZZXI": -9.581274026401806e-05, "IXXIIYZZZZXI": 9.581274026401806e-05, "XXIIXYIIIIII": 8.997933198547477e-05, "YYIIXYIIIIII": -8.997933198547477e-05, "XYIIXXIIIIII": -8.997933198547477e-05, "YXIIXXIIIIII": -8.997933198547477e-05, "XYIIYYIIIIII": 8.997933198547477e-05, "YXIIYYIIIIII": 8.997933198547477e-05, "YYIIYXIIIIII": -8.997933198547477e-05, "XXIIYXIIIIII": 8.997933198547477e-05, "YXIIXZZZZZZX": -3.631065147178751e-05, "XYIIXZZZZZZX": -3.631065147178751e-05, "XYIIYZZZZZZY": 3.631065147178751e-05, "YXIIYZZZZZZY": 3.631065147178751e-05, "YYIIYZZZZZZX": -3.631065147178751e-05, "XXIIYZZZZZZX": 3.631065147178751e-05, "XXIIXZZZZZZY": 3.631065147178751e-05, "YYIIXZZZZZZY": -3.631065147178751e-05, "YYIIIXZZZZYI": 3.631065147178751e-05, "XXIIIXZZZZYI": -3.631065147178751e-05, "XYIIIXZZZZXI": 3.631065147178751e-05, "YXIIIXZZZZXI": 3.631065147178751e-05, "YXIIIYZZZZYI": -3.631065147178751e-05, "YYIIIYZZZZXI": 3.631065147178751e-05, "XXIIIYZZZZXI": -3.631065147178751e-05, "XYIIIYZZZZYI": -3.631065147178751e-05, "IYZXIXZZZZZX": 1.2283158668650488e-06, "IXZYIYZZZZZY": -1.2283158668650488e-06, "IYZYIYZZZZZX": 1.2283158668650488e-06, "IXZXIYZZZZZX": -1.2283158668650488e-06, "IXZYIXZZZZZX": 1.2283158668650488e-06, "IYZXIYZZZZZY": -1.2283158668650488e-06, "YZXIYZZZZZYI": -1.2283158668650488e-06, "YZXIXZZZZZXI": 1.2283158668650488e-06, "XZYIYZZZZZYI": -1.2283158668650488e-06, "YZYIYZZZZZXI": 1.2283158668650488e-06, "XZXIYZZZZZXI": -1.2283158668650488e-06, "IYZYIXZZZZZY": 1.2283158668650488e-06, "IXZXIXZZZZZY": -1.2283158668650488e-06, "XZXIXZZZZZYI": -1.2283158668650488e-06, "XZYIXZZZZZXI": 1.2283158668650488e-06, "YZYIXZZZZZYI": 1.2283158668650488e-06}}, "hf_method_fallback": "standard", "generation_time_s": 7.947, "timestamp": "2026-03-10T21:33:13.312764+00:00", "formula_latex": "$\\mathrm{BeH^{+}}$"}}